Workbook

Sheet Entidades
A1: Entidades públicas: poder, presupuesto y posibles duplicidades
A2: 135 registros: 76 estatales + 3 creaciones legales de constitución no confirmada + 3 creaciones anunciadas o en tramitación, no constituidas + 53 autonómicos. Creados o transformados desde 2004. Inventario parcial, no censo exhaustivo. Las filas 127 a 136 de Hoja 1 (fondo verde) son altas del 14/10/2026.
A3: Columnas numéricas en EUR millones: 44,3 = 44,3 millones de euros. El texto original puede conservar euros. Vacío = sin cifra propia verificada; nunca sustituir por cero. Filtrar año y base antes de sumar. Duplicidad es un juicio de relación, NO una prueba de gasto inútil o doble financiación. Personal ocupado, puestos aprobados, crédito de personal y gasto ejecutado son medidas separadas; no sumar distintos años. Consulta: preceptivo no significa vinculante. No equivale a veto; distinguir ley, reglamento y plan. Pendiente no significa NO. La consulta o audiencia a asociaciones no significa consentimiento obligatorio (Ley 50/1997, art. 26.6). Revisados125 casos de consulta a nivel de las fuentes citadas;0 pendientes de esta pasada. No auditoría exhaustiva de toda la normativa sectorial. Informes preceptivos sectoriales verificados en varios órganos actuales e históricos; no equivalen a vetos. Pasada de consulta finalizada en las fuentes citadas. Personal ejecutado: obligaciones reconocidas cap1 hasta31/08/2026,8meses, no salario puro ni año completo. Pagos separados; ninguna ausencia sustituida por0. Añadido cierre2025:19 entidades con gasto anual cap1, separado de2026parcial. Emergencias: personas y crédito solo programa2.2.B, NO agencia entera.
A4: Resumen 2026 por base: suma propia verificada EUR millones y número de registros; NO sumar bases mezcladas
B5: Crédito total actualizado | C5: =SUMIFS('Hoja 1'!K2:K136,'Hoja 1'!L2:L136,2026,'Hoja 1'!M2:M136,B5) -> 10829.239 | D5: =COUNTIFS('Hoja 1'!L2:L136,2026,'Hoja 1'!M2:M136,B5,'Hoja 1'!K2:K136,">0") -> 24 | E5: ="Personal 2026 reconocido hasta 31/08 (IGAE), EUR millones ("&COUNTIFS('Hoja 1'!AQ2:AQ136,"<>",'Hoja 1'!AS2:AS136,"Hasta 31/08/2026:8 meses, NO año completo")&" entidades; NO salarios puros; otros cortes en Hoja 1, no se suman)" -> Personal 2026 reconocido hasta 31/08 (IGAE), EUR millones (22 entidades; NO salarios puros; otros cortes en Hoja 1, no se suman) | F5: =SUMIFS('Hoja 1'!AQ2:AQ136,'Hoja 1'!AR2:AR136,2026,'Hoja 1'!AS2:AS136,"Hasta 31/08/2026:8 meses, NO año completo") -> 737.209
B6: Crédito inicial aprobado | C6: =SUMIFS('Hoja 1'!K2:K136,'Hoja 1'!L2:L136,2026,'Hoja 1'!M2:M136,B6) -> 1002.092 | D6: =COUNTIFS('Hoja 1'!L2:L136,2026,'Hoja 1'!M2:M136,B6,'Hoja 1'!K2:K136,">0") -> 15 | E6: ="Pagos personal 2026 hasta 31/08, EUR millones ("&COUNT('Hoja 1'!BI2:BI136)&" entidades)" -> Pagos personal 2026 hasta 31/08, EUR millones (22 entidades) | F6: =SUM('Hoja 1'!BI2:BI136) -> 736.825
B7: Presupuesto propio aprobado | C7: =SUMIFS('Hoja 1'!K2:K136,'Hoja 1'!L2:L136,2026,'Hoja 1'!M2:M136,B7) -> 792.46274 | D7: =COUNTIFS('Hoja 1'!L2:L136,2026,'Hoja 1'!M2:M136,B7,'Hoja 1'!K2:K136,">0") -> 20 | E7: ="Gasto de personal 2025, año completo (cap.1 obligaciones; gastos de personal de cuentas en fundaciones/entes): "&COUNT('Hoja 1'!BP2:BP136)&" entidades, EUR millones; NO sumar con parcial 2026" -> Gasto de personal 2025, año completo (cap.1 obligaciones; gastos de personal de cuentas en fundaciones/entes): 27 entidades, EUR millones; NO sumar con parcial 2026 | F7: =SUM('Hoja 1'!BP2:BP136) -> 1144.5759
A9: Cobertura de campos en Hoja 1 (número de fichas con dato; 135 en total)
B10: Presupuesto propio (cualquier año/base) | C10: =COUNT('Hoja 1'!K2:K136) -> 61
B11: Sin presupuesto propio verificado en norma (órganos sin dotación) | C11: =COUNTIF('Hoja 1'!O2:O136,"Sin presupuesto propio: órgano*") -> 45
B12: Extinguidas / suprimidas | C12: =COUNTIF('Hoja 1'!O2:O136,"Sin presupuesto propio actual: supresión*") -> 10
B13: Sin cifra propia actual verificada (pendientes) | C13: =COUNTIF('Hoja 1'!O2:O136,"Sin cifra propia actual verificada") -> 14
B14: Crédito de personal (cap. 1 o gastos de personal) | C14: =COUNT('Hoja 1'!AL2:AL136) -> 44
B15: Gasto de personal ejecutado, columna AQ (año y corte variables; no sumar) | C15: =COUNT('Hoja 1'!AQ2:AQ136) -> 33
B16: Gasto de personal 2025 año completo | C16: =COUNT('Hoja 1'!BP2:BP136) -> 27
B17: Personas ocupadas (fecha variable; no sumar) | C17: =COUNT('Hoja 1'!AG2:AG136) -> 29
B18: Puestos aprobados / presupuestados | C18: =COUNT('Hoja 1'!AX2:AX136) -> 22
A20: Celdas con fondo amarillo en Hoja 1: completadas o corregidas el 12/10/2026. Filas con fondo verde: entidades añadidas el 14/10/2026. Detalle celda a celda en la hoja "Cambios 12-10-2026"; fuentes, páginas y huecos pendientes en "Verificación y pendientes".
A22: Clasificación de las 135 fichas según el P100 de Extramuros (juicio con criterios explícitos; motivo, base en el P100 y destino de cada una en Hoja 1)
C23: Fichas | D23: Con presupuesto propio 2026 | E23: Suma de presupuestos propios 2026, EUR millones (bases distintas: orden de magnitud, no total contable)
A24: Binario | B24: Útil | C24: =COUNTIF('Hoja 1'!BV2:BV136,B24) -> 32 | D24: =COUNTIFS('Hoja 1'!BV2:BV136,B24,'Hoja 1'!L2:L136,2026,'Hoja 1'!K2:K136,">0") -> 29 | E24: =SUMIFS('Hoja 1'!K2:K136,'Hoja 1'!BV2:BV136,B24,'Hoja 1'!L2:L136,2026) -> 10202.391
B25: No útil | C25: =COUNTIF('Hoja 1'!BV2:BV136,B25) -> 86 | D25: =COUNTIFS('Hoja 1'!BV2:BV136,B25,'Hoja 1'!L2:L136,2026,'Hoja 1'!K2:K136,">0") -> 29 | E25: =SUMIFS('Hoja 1'!K2:K136,'Hoja 1'!BV2:BV136,B25,'Hoja 1'!L2:L136,2026) -> 2340.3934
B26: Sin decisión en el P100 | C26: =COUNTIF('Hoja 1'!BV2:BV136,B26) -> 4 | D26: =COUNTIFS('Hoja 1'!BV2:BV136,B26,'Hoja 1'!L2:L136,2026,'Hoja 1'!K2:K136,">0") -> 1 | E26: =SUMIFS('Hoja 1'!K2:K136,'Hoja 1'!BV2:BV136,B26,'Hoja 1'!L2:L136,2026) -> 81.00922
B27: Extinguida | C27: =COUNTIF('Hoja 1'!BV2:BV136,B27) -> 13 | D27: =COUNTIFS('Hoja 1'!BV2:BV136,B27,'Hoja 1'!L2:L136,2026,'Hoja 1'!K2:K136,">0") -> 0 | E27: =SUMIFS('Hoja 1'!K2:K136,'Hoja 1'!BV2:BV136,B27,'Hoja 1'!L2:L136,2026) -> 0
A28: Veredicto | B28: Mantener | C28: =COUNTIF('Hoja 1'!BW2:BW136,B28) -> 28 | D28: =COUNTIFS('Hoja 1'!BW2:BW136,B28,'Hoja 1'!L2:L136,2026,'Hoja 1'!K2:K136,">0") -> 25 | E28: =SUMIFS('Hoja 1'!K2:K136,'Hoja 1'!BW2:BW136,B28,'Hoja 1'!L2:L136,2026) -> 9098.9938
B29: Reformar | C29: =COUNTIF('Hoja 1'!BW2:BW136,B29) -> 4 | D29: =COUNTIFS('Hoja 1'!BW2:BW136,B29,'Hoja 1'!L2:L136,2026,'Hoja 1'!K2:K136,">0") -> 4 | E29: =SUMIFS('Hoja 1'!K2:K136,'Hoja 1'!BW2:BW136,B29,'Hoja 1'!L2:L136,2026) -> 1103.3969
B30: Integrar | C30: =COUNTIF('Hoja 1'!BW2:BW136,B30) -> 34 | D30: =COUNTIFS('Hoja 1'!BW2:BW136,B30,'Hoja 1'!L2:L136,2026,'Hoja 1'!K2:K136,">0") -> 27 | E30: =SUMIFS('Hoja 1'!K2:K136,'Hoja 1'!BW2:BW136,B30,'Hoja 1'!L2:L136,2026) -> 2263.5233
B31: Suprimir | C31: =COUNTIF('Hoja 1'!BW2:BW136,B31) -> 52 | D31: =COUNTIFS('Hoja 1'!BW2:BW136,B31,'Hoja 1'!L2:L136,2026,'Hoja 1'!K2:K136,">0") -> 2 | E31: =SUMIFS('Hoja 1'!K2:K136,'Hoja 1'!BW2:BW136,B31,'Hoja 1'!L2:L136,2026) -> 76.87014
B32: Pendiente de decisión | C32: =COUNTIF('Hoja 1'!BW2:BW136,B32) -> 4 | D32: =COUNTIFS('Hoja 1'!BW2:BW136,B32,'Hoja 1'!L2:L136,2026,'Hoja 1'!K2:K136,">0") -> 1 | E32: =SUMIFS('Hoja 1'!K2:K136,'Hoja 1'!BW2:BW136,B32,'Hoja 1'!L2:L136,2026) -> 81.00922
B33: Extinguida | C33: =COUNTIF('Hoja 1'!BW2:BW136,B33) -> 13 | D33: =COUNTIFS('Hoja 1'!BW2:BW136,B33,'Hoja 1'!L2:L136,2026,'Hoja 1'!K2:K136,">0") -> 0 | E33: =SUMIFS('Hoja 1'!K2:K136,'Hoja 1'!BW2:BW136,B33,'Hoja 1'!L2:L136,2026) -> 0
A34: Función | B34: Servicio público directo | C34: =COUNTIF('Hoja 1'!BX2:BX136,B34) -> 31 | D34: =COUNTIFS('Hoja 1'!BX2:BX136,B34,'Hoja 1'!L2:L136,2026,'Hoja 1'!K2:K136,">0") -> 24 | E34: =SUMIFS('Hoja 1'!K2:K136,'Hoja 1'!BX2:BX136,B34,'Hoja 1'!L2:L136,2026) -> 3739.0019
B35: Regulación o inspección de terceros | C35: =COUNTIF('Hoja 1'!BX2:BX136,B35) -> 15 | D35: =COUNTIFS('Hoja 1'!BX2:BX136,B35,'Hoja 1'!L2:L136,2026,'Hoja 1'!K2:K136,">0") -> 15 | E35: =SUMIFS('Hoja 1'!K2:K136,'Hoja 1'!BX2:BX136,B35,'Hoja 1'!L2:L136,2026) -> 5433.3363
B36: Financiación y ayudas | C36: =COUNTIF('Hoja 1'!BX2:BX136,B36) -> 14 | D36: =COUNTIFS('Hoja 1'!BX2:BX136,B36,'Hoja 1'!L2:L136,2026,'Hoja 1'!K2:K136,">0") -> 11 | E36: =SUMIFS('Hoja 1'!K2:K136,'Hoja 1'!BX2:BX136,B36,'Hoja 1'!L2:L136,2026) -> 3405.5617
B37: Control interno y cumplimiento | C37: =COUNTIF('Hoja 1'!BX2:BX136,B37) -> 13 | D37: =COUNTIFS('Hoja 1'!BX2:BX136,B37,'Hoja 1'!L2:L136,2026,'Hoja 1'!K2:K136,">0") -> 9 | E37: =SUMIFS('Hoja 1'!K2:K136,'Hoja 1'!BX2:BX136,B37,'Hoja 1'!L2:L136,2026) -> 45.893442
B38: Consultivo o participación | C38: =COUNTIF('Hoja 1'!BX2:BX136,B38) -> 46 | D38: =COUNTIFS('Hoja 1'!BX2:BX136,B38,'Hoja 1'!L2:L136,2026,'Hoja 1'!K2:K136,">0") -> 0 | E38: =SUMIFS('Hoja 1'!K2:K136,'Hoja 1'!BX2:BX136,B38,'Hoja 1'!L2:L136,2026) -> 0
B39: Extinguida o no constituida | C39: =COUNTIF('Hoja 1'!BX2:BX136,B39) -> 16 | D39: =COUNTIFS('Hoja 1'!BX2:BX136,B39,'Hoja 1'!L2:L136,2026,'Hoja 1'!K2:K136,">0") -> 0 | E39: =SUMIFS('Hoja 1'!K2:K136,'Hoja 1'!BX2:BX136,B39,'Hoja 1'!L2:L136,2026) -> 0
A40: Base en el P100
B41: Explícito: el P100 nombra el organismo o su categoría | C41: =COUNTIF('Hoja 1'!CC2:CC136,"Explícito*") -> 63
B42: Aplicando el criterio del P100 (deducción nuestra) | C42: =COUNTIF('Hoja 1'!CC2:CC136,"Aplicando*") -> 55
B43: El P100 no trata la materia | C43: =COUNTIF('Hoja 1'!CC2:CC136,"El P100*") -> 4
A45: Criterio (alineado con el P100). Útil no es tener un contenido, es a qué sirve ese contenido. Un organismo es útil si cumple las tres condiciones: 1) su función es necesaria y cambia decisiones o mejora un servicio (un informe, un dictamen o un trámite de cumplimiento no cuenta; Costes del Estado 2); 2) nadie más la presta: con un organismo nacional basta, no hacen falta 17 autonómicos iguales (Costes 9, Organización del Estado 5, Impuestos 11 "una sola Agencia Tributaria", Estado 17 "una sola web"); 3) sirve a un fin del P100, no a un fin que el P100 elimina (p. ej. la cooperación al desarrollo autonómica: el P100 limita la cooperación a la humanitaria y a países que colaboren en el control migratorio, Costes 5). Veredictos: Mantener (cumple las tres), Reformar (se queda, con los cambios que pide el P100), Integrar (la función sigue, el organismo sobra: pasa al organismo nacional o a la consejería indicada en "destino"), Suprimir (ni la función ni el organismo), Pendiente de decisión (el P100 no trata la materia), Extinguida (ya no existe). Binario: Útil = Mantener o Reformar; No útil = Integrar o Suprimir (juzga el organismo, no la materia). "Explícito" = el P100 lo dice; "Aplicando el criterio" = deducción nuestra a partir del P100, a validar. "Exigida por la UE": se puede fusionar o redimensionar, no suprimir. Es un juicio, no un dato.
A47: Coste de personal de los órganos consultivos sin presupuesto propio (ESCENARIO, no dato publicado)
B48: Órganos consultivos o de participación | C48: =COUNTIF('Hoja 1'!BX2:BX136,"Consultivo o participación") -> 46
B49: Coste de personal por persona: mediana de la hoja (gasto 2025 / personas), EUR | C49: =MEDIAN('Hoja 1'!CH2:CH136) -> 56222.222
B50: Fichas con las que se calcula la mediana | C50: =COUNT('Hoja 1'!CH2:CH136) -> 21
B51: Si cada órgano ocupa 1 persona a tiempo completo: EUR millones al año | C51: =C48*C49*1/1000000 -> 2.5862222
B52: Si cada órgano ocupa 2 personas a tiempo completo: EUR millones al año | C52: =C48*C49*2/1000000 -> 5.1724444
B53: Si cada órgano ocupa 3 personas a tiempo completo: EUR millones al año | C53: =C48*C49*3/1000000 -> 7.7586667
A54: Las normas de estos órganos dicen que su coste lo absorbe el ministerio o la consejería (secretaría, unidad técnica, apoyo a reuniones), pero no lo publican por separado. Las personas a tiempo completo por órgano son un supuesto; el coste por persona sale de la hoja. Casos documentados en la columna "Coste de apoyo" de Hoja 1 (p. ej. 7 personas en el órgano de trabajo del Observatorio de la Vida Militar, 2015). Suprimir el órgano libera ese coste solo si se amortizan o reasignan los puestos que lo atienden.

Sheet Duplicidades por tema
A1: Tema | B1: Organismo estatal | C1: Andalucía | D1: Aragón | E1: Asturias | F1: Illes Balears | G1: Canarias | H1: Cantabria | I1: Castilla-La Mancha | J1: Castilla y León | K1: Cataluña | L1: Comunitat Valenciana | M1: Extremadura | N1: Galicia | O1: Madrid | P1: Murcia | Q1: Navarra | R1: País Vasco | S1: La Rioja | T1: CCAA con organismo propio | U1: CCAA sin verificar | V1: Organismos en total (Estado + CCAA, verificados) | W1: ¿Cubre el Estado esos territorios? | X1: Base competencial | Y1: Fuentes
A2: Agencias tributarias | B2: Agencia Estatal de Administración Tributaria (AEAT) | C2: Propio (ente): Agencia Tributaria de Andalucía (ATRIAN) | D2: Consejería | E2: Propio (ente): Ente Público de Servicios Tributarios del Principado de Asturias ('Tributas en Asturias') | F2: Propio (ente): Agencia Tributaria de las Illes Balears (ATIB) | G2: Propio (ente): Agencia Tributaria Canaria (ATC) | H2: Propio (ente): Agencia Cántabra de Administración Tributaria (ACAT) | I2: Consejería | J2: Consejería | K2: Propio (ente): Agència Tributària de Catalunya (ATC) | L2: Propio (ente): Agència Tributària Valenciana (ATV) | M2: Consejería | N2: Propio (ente): Axencia Tributaria de Galicia (ATRIGA) | O2: Consejería | P2: Propio (ente): Agencia Tributaria de la Región de Murcia (ATRM) | Q2: Propio (ente): Hacienda Foral de Navarra (organismo autónomo) | R2: Propio (órgano): Haciendas Forales de Álava, Bizkaia y Gipuzkoa (departamentos de Hacienda de las tres diputaciones forales) + Órgano de Coordinación Tributaria de Euskadi | S2: Consejería | T2: =COUNTIF(C2:S2,"Propio*") -> 11 | U2: =COUNTIF(C2:S2,"Sin verificar") -> 0 | V2: =1+T2 -> 12 | W2: Parcial. La AEAT cubre en todo el territorio común los tributos estatales no cedidos, pero los tributos cedidos los gestiona cada CA por ley, con agencia o con su DG. La función autonómica existe en las 15 CCAA de régimen común: la 'duplicidad' de las 10 agencias es de forma organizativa, no de función, porque las 6 CCAA sin agencia hacen lo mismo desde una DG. En territorio foral la AEAT no gestiona los tributos concertados o convenidos. | X2: Tributos cedidos: por la LOFCA y la ley de financiación autonómica, las CCAA de régimen común aplican por delegación los tributos cedidos (ISD, ITPAJD, tributos sobre el juego, etc.) y organizan libremente su administración tributaria (agencia o DG). La AEAT aplica los tributos estatales (IRPF, IVA, IS, IIEE) en todo el territorio común. Navarra (Convenio Económico) y el País Vasco (Concierto Económico, Ley 12/2002) tienen haciendas forales propias por la DA 1ª de la Constitución. | Y2: https://www.boe.es/eli/es-an/l/2007/12/18/23/con https://laadministracionaldia.inap.es/noticia.asp?id=1232456 https://www.boe.es/eli/es-ib/l/2008/04/14/3 https://boe.es/buscar/act.php?id=BOE-A-2014-9902 https://www.parcan.es/files/documentacion/dosieres/DOSS0221/DOSS0221DOC4682.PDF https://transparencia.castillalamancha.es/titular/33680 https://www.boe.es/diario_boe/txt.php?id=BOE-A-2007-15212 https://laadministracionaldia.inap.es/noticia.asp?id=1256956 https://doe.juntaex.es/pdfs/doe/2026/790o/26060892.pdf https://www.es.parlamentodegalicia.gal/sitios/web/BibliotecaLeisdeGalicia/Lei_15_2010.pdf https://www.comunidad.madrid/transparencia/unidad-organizativa-responsable/direccion-general-tributos https://www.parcan.es/files/documentacion/dosieres/DOSS0221/DOSS0221DOC4791.PDF https://laadministracionaldia.inap.es/noticia.asp?id=1239023 https://www.euskadi.eus/gobierno-vasco/contenidos/informacion/fisc_sytribvas/es_3222/indice_c.html https://larioja.org/tributos/en/enlaces-interes/competencias-direccion-general-tributos https://www.gobierno.jcyl.es/web/es/consejerias/direccion-general-tributos-financiacion.html https://gd.aragon.es/cgi-bin/ORGA/BRSCGI?CMD=VERDOC&BASE=ORGA&PIECE=ORGA&SEC=ORGABUSXI&DOCN=653
A3: Consejos de transparencia | B3: Consejo de Transparencia y Buen Gobierno (CTBG) | C3: Propio (ente): Consejo de Transparencia y Protección de Datos de Andalucía (CTPDA) | D3: Propio (órgano): Consejo de Transparencia de Aragón | E3: Lo cubre el Estado | F3: Lo cubre el Estado | G3: Propio (órgano): Comisionado de Transparencia y Acceso a la Información Pública de Canarias | H3: Lo cubre el Estado | I3: Propio (órgano): Consejo Regional de Transparencia y Buen Gobierno de Castilla-La Mancha | J3: Propio (órgano): Comisionado de Transparencia de Castilla y León (función atribuida al Procurador del Común) | K3: Propio (órgano): Comissió de Garantia del Dret d'Accés a la Informació Pública (GAIP) | L3: Propio (órgano): Consell de Transparència de la Comunitat Valenciana | M3: Lo cubre el Estado | N3: Propio (órgano): Comisión da Transparencia de Galicia | O3: Propio (órgano): Consejo de Transparencia y Protección de Datos de la Comunidad de Madrid | P3: Propio (órgano): Comisionado de Transparencia de la Región de Murcia | Q3: Propio (órgano): Consejo de Transparencia de Navarra | R3: Propio (órgano): Comisión Vasca de Acceso a la Información Pública | S3: Lo cubre el Estado | T3: =COUNTIF(C3:S3,"Propio*") -> 12 | U3: =COUNTIF(C3:S3,"Sin verificar") -> 0 | V3: =1+T3 -> 13 | W3: Sí, por convenio. En 2025-2026 el CTBG resuelve las reclamaciones de Asturias (nuevo convenio de 11/05/2026), Illes Balears (convenio 2025-2029), Cantabria, Extremadura y La Rioja, además de Ceuta y Melilla. La CA paga por reclamación resuelta (192,35 EUR en el convenio asturiano). CLM (hasta 31/10/2023) y Madrid (hasta 02/11/2021) dejaron el convenio al crear su órgano. | X3: Transparencia: cada administración puede atribuir la resolución de las reclamaciones de acceso a un órgano propio o convenirla con el CTBG (Ley 19/2013, art. 24 y DA 4ª). | Y3: https://consejodetransparencia.es/content/dam/ctransparencia/portal-ctbg/nosotros/cooperacion/acta_constitucion_COTAI.pdf https://consejodetransparencia.es/content/dam/ctransparencia/portal-ctbg/nosotros/memorias-y-plan-estrategico/memoria-2025/Memoria_2025_CTBG.pdf https://consejodetransparencia.es/content/dam/ctransparencia/portal-ctbg/nosotros/memorias-y-plan-estrategico/memoria-2025/Resumen_Ejecutivo_Memoria_2025_CTBG.pdf https://www.asturias.es/bopa/2026/06/26/2026-05300.pdf https://www.bocm.es/boletin/CM_Orden_BOCM/2024/05/23/BOCM-20240523-1.PDF https://www.comunidad.madrid/transparencia/sites/default/files/8._main_reglamento_ctpd.pdf https://boe.es/ccaa/borm/2024/158/s20598-20604.pdf https://www.boe.es/buscar/act.php?id=BOE-A-2014-7534
A4: Autoridades de protección de datos | B4: Agencia Española de Protección de Datos (AEPD) | C4: Propio (ente): Consejo de Transparencia y Protección de Datos de Andalucía (CTPDA) | D4: Lo cubre el Estado | E4: Lo cubre el Estado | F4: Lo cubre el Estado | G4: Lo cubre el Estado | H4: Lo cubre el Estado | I4: Lo cubre el Estado | J4: Lo cubre el Estado | K4: Propio (ente): Autoritat Catalana de Protecció de Dades (APDCAT) | L4: Lo cubre el Estado | M4: Lo cubre el Estado | N4: Lo cubre el Estado | O4: Lo cubre el Estado | P4: Lo cubre el Estado | Q4: Lo cubre el Estado | R4: Propio (ente): Autoridad Vasca de Protección de Datos (AVPD) | S4: Lo cubre el Estado | T4: =COUNTIF(C4:S4,"Propio*") -> 3 | U4: =COUNTIF(C4:S4,"Sin verificar") -> 0 | V4: =1+T4 -> 4 | W4: Sí, por defecto y por ley: la AEPD supervisa el sector público autonómico y local de las 14 CCAA sin autoridad propia, y a todo el sector privado en toda España. Madrid suprimió su agencia el 01/01/2013 y la AEPD asumió sus funciones. | X4: Protección de datos: el RGPD y la LOPDGDD (arts. 57-58) permiten a las CCAA crear autoridades de control para los tratamientos de su sector público y de las entidades locales de su territorio. En lo demás, y donde no las hay, es competente la AEPD. | Y4: https://www.aepd.es/la-agencia/transparencia/informacion-de-caracter-institucional-organizativa-y-de-planificacion/historia https://boe.es/boe/dias/2024/01/18/pdfs/BOE-A-2024-900.pdf https://www.euskadi.eus/web01-bopv/es/bopv2/datos/2024/12/2405865a.shtml https://www.comunidad.madrid/transparencia/sites/default/files/8._main_reglamento_ctpd.pdf
A5: Autoridades de defensa de la competencia | B5: Comisión Nacional de los Mercados y la Competencia (CNMC) | C5: Propio (ente): Agencia de la Competencia y de la Regulación Económica de Andalucía (antes Agencia de Defensa de la Competencia de Andalucía) | D5: Propio (órgano): Tribunal de Defensa de la Competencia de Aragón (resolución) + Servicio de Defensa de la Competencia (instrucción, en el departamento) | E5: Lo cubre el Estado | F5: Lo cubre el Estado | G5: Propio (órgano): Consejo Canario de Defensa de la Competencia (resolución) + Servicio de Defensa de la Competencia (instrucción) | H5: Lo cubre el Estado | I5: Lo cubre el Estado | J5: Propio (órgano): Órgano autonómico de defensa de la competencia de Castilla y León (instrucción + resolución; nombre a confirmar) | K5: Propio (ente): Autoritat Catalana de la Competència (ACCO) | L5: Propio (órgano): Comisión de Defensa de la Competencia de la Comunitat Valenciana | M5: Propio (órgano): Jurado de Defensa de la Competencia de Extremadura | N5: Propio (órgano): Comisión Galega da Competencia (órgano colegiado independiente adscrito al Instituto Galego do Consumo e da Competencia, OA) | O5: Consejería | P5: Consejería | Q5: Consejería | R5: Propio (ente): Autoridad Vasca de la Competencia (AVC) | S5: Lo cubre el Estado | T5: =COUNTIF(C5:S5,"Propio*") -> 9 | U5: =COUNTIF(C5:S5,"Sin verificar") -> 0 | V5: =1+T5 -> 10 | W5: Sí, por defecto: donde no hay órgano autonómico actúa la CNMC, y donde la CA solo instruye (Madrid, Murcia, Navarra) resuelve la CNMC. Los casos se reparten mediante el Consejo de Defensa de la Competencia. | X5: Defensa de la competencia: legislación estatal (Ley 15/2007). Las CCAA con competencia estatutaria ejecutan sobre conductas que afectan solo a su territorio, con puntos de conexión y asignación de casos según la Ley 1/2002 de coordinación; las conductas supraautonómicas corresponden siempre a la CNMC. | Y5: https://cnmc.es/la-cnmc-y-las-autoridades-de-competencia-autonomicas-han-celebrado-en-madrid-el-consejo-anual-de https://www.boe.es/buscar/act.php?id=BOE-A-2007-14406 https://derecholocal.es/?p=11702 https://dogv.gva.es/datos/2012/03/26/pdf/2012_3049.pdf https://laadministracionaldia.inap.es/noticia.asp?id=1057841 https://www.juntaex.es/w/0680923 https://www.lex.gal/es/normativa/detalle/10097/pdf/ https://www.boe.es/buscar/act.php?id=BOE-A-2012-2313 https://cnmc.es/sites/default/files/editor_contenidos/CNMC/Memorias/Resumen-ejecutivo-memoria-2024_.pdf
A6: Oficinas y agencias antifraude y de protección del informante | B6: Autoridad Independiente de Protección del Informante, A.A.I. (AIPI) | C6: Propio (ente): Oficina Andaluza contra el Fraude y la Corrupción (OAAF) | D6: No existe | E6: Propio (ente): Consejo de Transparencia y Buen Gobierno del Principado de Asturias | F6: No existe | G6: No existe | H6: No existe | I6: No existe | J6: Propio (órgano): Autoridad Independiente en materia de Corrupción de Castilla y León (AAICyL) | K6: Propio (ente): Oficina Antifraude de Cataluña (OAC) | L6: Propio (ente): Agencia de Prevención y Lucha contra el Fraude y la Corrupción de la Comunitat Valenciana (AVAF) | M6: No existe | N6: Propio (ente): Autoridad Gallega de Protección de la Persona Informante (AGPI) | O6: Propio (órgano): Consejo de Transparencia y Protección de Datos de la Comunidad de Madrid (CTPD) | P6: No existe | Q6: Propio (ente): Oficina de Buenas Prácticas y Anticorrupción de la Comunidad Foral de Navarra (OANA) | R6: Propio (ente): Autoridad Vasca de Transparencia – Gardena | S6: No existe | T6: =COUNTIF(C6:S6,"Propio*") -> 9 | U6: =COUNTIF(C6:S6,"Sin verificar") -> 0 | V6: =1+T6 -> 10 | W6: parcial: la AIPI cubre el sector público estatal; para el sector público de las CCAA sin autoridad propia requiere convenio con la Consejería competente, y el PAA 2026 no cita ninguno firmado (objetivo de 3 en 2026). Hoy hay 8 CCAA sin autoridad propia ni convenio verificado. | X6: Protección del informante: la Ley 2/2023 (art. 24) permite a cada comunidad designar su propia autoridad independiente para su sector público autonómico y local; si no la designa, la AIPI solo puede actuar en ese territorio mediante convenio (DA 2ª). Las oficinas antifraude previas son creación autonómica por autoorganización (casi todas adscritas al Parlamento). | Y6: https://www.proteccioninformante.gob.es/content/dam/aipi/documentos/PLAN_ACTUACION_ANUAL_2026_AIPI.pdf https://laadministracionaldia.inap.es/noticia.asp?id=1520499 https://www.cepc.gob.es/sites/default/files/2026-06/20260617-aipi.pdf https://laadministracionaldia.inap.es/noticia.asp?id=1249714 https://intranet.caib.es/eboibfront/pdf/es/2024/68/1162692 https://www.comunidad.madrid/consejo-transparencia/canal-externo-informante https://laadministracionaldia.inap.es/noticia.asp?id=1260634 https://www.boe.es/eli/es-ar/l/2017/06/01/5/con
A7: Agencias de calidad universitaria | B7: Agencia Nacional de Evaluación de la Calidad y Acreditación (ANECA) | C7: Propio (ente): Agencia para la Calidad Científica y Universitaria de Andalucía (ACCUA) | D7: Propio (ente): Agencia de Calidad y Prospectiva Universitaria de Aragón (ACPUA) | E7: Lo cubre el Estado | F7: Propio (ente): Agència de Qualitat Universitària de les Illes Balears (AQUIB) | G7: Propio (ente): Agencia Canaria de Calidad Universitaria y Evaluación Educativa (ACCUEE) | H7: Lo cubre el Estado | I7: Lo cubre el Estado | J7: Propio (ente): Agencia para la Calidad del Sistema Universitario de Castilla y León (ACSUCYL) | K7: Propio (ente): Agència per a la Qualitat del Sistema Universitari de Catalunya (AQU Catalunya) | L7: Propio (ente): Agència Valenciana d'Avaluació i Prospectiva (AVAP) | M7: Lo cubre el Estado | N7: Propio (ente): Axencia para a Calidade do Sistema Universitario de Galicia (ACSUG) | O7: Propio (ente): Fundación para el Conocimiento madri+d | P7: Lo cubre el Estado | Q7: Lo cubre el Estado | R7: Propio (ente): Agencia de Calidad del Sistema Universitario Vasco (Unibasq) | S7: Lo cubre el Estado | T7: =COUNTIF(C7:S7,"Propio*") -> 10 | U7: =COUNTIF(C7:S7,"Sin verificar") -> 0 | V7: =1+T7 -> 11 | W7: sí, por defecto: ANECA evalúa en las 7 CCAA sin agencia propia (Asturias, Cantabria, Castilla-La Mancha, Extremadura, Murcia, Navarra, La Rioja). Además las universidades pueden recurrir a cualquier agencia inscrita en EQAR. | X7: Garantía de calidad universitaria: la evaluación y acreditación de títulos e instituciones corresponde a ANECA o a las agencias autonómicas inscritas en EQAR, cada una en su ámbito (normativa universitaria estatal: LOSU y RD 822/2021). Las CCAA pueden crear su agencia; si no la crean, actúa ANECA. | Y7: https://eqar.eu/register/agencies https://www.aneca.es/en/reacu-network https://dogv.gva.es/datos/2024/01/12/pdf/2024_156.pdf https://www.inqaahe.org/wp-content/uploads/2025/02/D250.pdf https://intranet.caib.es/eboibfront/pdf/es/2021/98/1093428
A8: Evaluación de políticas públicas | B8: Agencia Estatal de Evaluación de Políticas Públicas | C8: Consejería | D8: Sin verificar | E8: Sin verificar | F8: Sin verificar | G8: Sin verificar | H8: Sin verificar | I8: Sin verificar | J8: Consejería | K8: Propio (ente): Institut Català d'Avaluació de Polítiques Públiques (Ivàlua) | L8: Sin verificar | M8: Sin verificar | N8: Sin verificar | O8: Sin verificar | P8: Sin verificar | Q8: Propio (órgano): Comisión Foral para la Evaluación de las Políticas Públicas y la Calidad de los Servicios Públicos | R8: Sin verificar | S8: Sin verificar | T8: =COUNTIF(C8:S8,"Propio*") -> 2 | U8: =COUNTIF(C8:S8,"Sin verificar") -> 13 | V8: =1+T8 -> 3 | W8: no: la Agencia estatal evalúa políticas de la AGE. Las CCAA cooperan en la red voluntaria REDEVAL y no se ha verificado ningún convenio de evaluación por encargo. | X8: Evaluación de políticas públicas: la Ley 27/2022 regula solo la AGE; cada comunidad organiza la evaluación de sus propias políticas por autoorganización, con ley propia o sin ella. La cooperación se hace por la red voluntaria REDEVAL (constituida en 2025: 13 CCAA y el Gobierno de España). | Y8: https://www.boe.es/diario_boe/txt.php?id=BOE-A-2026-2553 https://laadministracionaldia.inap.es/noticia.asp?id=1518225 https://www.boe.es/boe/dias/2026/07/28/pdfs/BOE-A-2026-16358.pdf https://laadministracionaldia.inap.es/noticia.asp?id=1516123 https://aecpa.es/files/view/pdf/congress-papers/17-0/3430 https://www.redalyc.org/journal/2815/281573431006/281573431006.pdf https://europeanevaluation.org/2026/02/05/spains-evaluation-awakening-a-decisive-momentum-from-quiet-reform-to-national-movement/
A9: Escuelas e institutos de formación de empleados públicos | B9: Instituto Nacional de Administración Pública (INAP) | C9: Propio (ente): Instituto Andaluz de Administración Pública (IAAP) | D9: Propio (órgano): Instituto Aragonés de Administración Pública (IAAP) | E9: Propio (órgano): Instituto Asturiano de Administración Pública 'Adolfo Posada' | F9: Propio (ente): Escuela Balear de Administración Pública (EBAP) | G9: Sin verificar | H9: Propio (ente): Instituto Cántabro de Administración Pública 'Rafael de la Sierra' (ICAP) | I9: Propio (órgano): Escuela de Administración Regional (EAR) | J9: Propio (órgano): Escuela de Administración Pública de Castilla y León (ECLAP) | K9: Propio (ente): Escola d'Administració Pública de Catalunya (EAPC) | L9: Sin verificar | M9: Sin verificar | N9: Propio (ente): Escola Galega de Administración Pública (EGAP) | O9: Sin verificar | P9: Propio (órgano): Escuela de Formación e Innovación de la Administración Pública de la Región de Murcia (EFIAP) | Q9: Consejería | R9: Propio (ente): Instituto Vasco de Administración Pública (IVAP) | S9: Propio (órgano): Escuela Riojana de Administración Pública (ERAP) | T9: =COUNTIF(C9:S9,"Propio*") -> 12 | U9: =COUNTIF(C9:S9,"Sin verificar") -> 4 | V9: =1+T9 -> 13 | W9: no: el INAP no forma al personal autonómico como servicio sustitutivo. Solo financia en parte (AFEDAP) y colabora con las escuelas autonómicas. | X9: Formación de empleados públicos: cada administración forma a su propio personal (autoorganización y función pública propia, TREBEP). El Estado coordina y financia en parte mediante el AFEDAP, que gestiona el INAP. | Y9: https://portal.inap.es/documents/10136/2292011/2022-MEMORIA.pdf/1f8338c1-e550-48bb-0c00-eefcbcd684af https://boe.es/boe/dias/2008/06/11/pdfs/A26873-26873.pdf
A10: Agencias de ciberseguridad | B10: INCIBE (S.M.E. Instituto Nacional de Ciberseguridad de España, sociedad mercantil estatal) y CCN-CERT (capacidad de respuesta del Centro Criptológico Nacional, integrado en el CNI) | C10: Propio (órgano): AndalucíaCERT (Centro de Seguridad TIC de Andalucía) | D10: Sin verificar | E10: Sin verificar | F10: Propio (ente): Agencia Balear de Digitalización, Ciberseguridad y Telecomunicaciones (ABDigital) | G10: Sin verificar | H10: Sin verificar | I10: Sin verificar | J10: Sin verificar | K10: Propio (ente): Agència de Ciberseguretat de Catalunya | L10: Propio (órgano): CSIRT-CV, Centro de Ciberseguridad de la Generalitat | M10: Sin verificar | N10: Propio (órgano): CSIRT.gal (Centro de Respuesta a Incidentes de Ciberseguridad de la Xunta) | O10: Propio (ente): Agencia de Ciberseguridad de la Comunidad de Madrid | P10: Sin verificar | Q10: Sin verificar | R10: Propio (ente): Agencia Vasca de Ciberseguridad (Zibersegurtasuneko Euskal Agentzia) | S10: Sin verificar | T10: =COUNTIF(C10:S10,"Propio*") -> 7 | U10: =COUNTIF(C10:S10,"Sin verificar") -> 10 | V10: =2+T10 -> 9 | W10: Sí, por ley y por defecto: el CCN-CERT ya es el CSIRT de referencia de todas las administraciones autonómicas. Varias CCAA sin agencia propia operan SOC o CSIRT integrados en la Red Nacional de SOC del CCN o con convenio con el CCN-CERT (p. ej. Baleares 2022, Galicia, Castilla y León). | X10: Seguridad pública, defensa y telecomunicaciones son competencias estatales (art. 149.1.21ª, 29ª CE). La normativa NIS (RD-ley 12/2018) designa CSIRT de referencia estatales: el CCN-CERT para el sector público y el INCIBE-CERT para el sector privado. Cada CCAA protege sus propios sistemas por autoorganización, aplicando el Esquema Nacional de Seguridad. | Y10: https://www.boe.es/eli/es-ct/l/2017/07/25/15 https://www.boe.es/diario_boe/txt.php?id=BOE-A-2023-17645 https://www.bocm.es/boletin/CM_Orden_BOCM/2026/07/14/BOCM-20260714-12.PDF https://www.caib.es/eboibfront/eli/es-ib/d/2025/12/19/63/dof/spa/pdf https://www.caib.es/sites/dgtic/es/soc/ https://sedian.juntadeandalucia.es/rfc-2350 https://laadministracionaldia.inap.es/noticia.asp?id=1515740 https://www.xunta.gal/hemeroteca/-/nova/157128/centro-respuesta-incidentes-ciberseguridad-xunta-entra-red-nacional-impulsada https://ast.aragon.es/sites/default/files/ast_memoriaactividad2016_resumen.pdf
A11: Agencias de administración digital y TIC | B11: Agencia Estatal de Administración Digital (AEAD) | C11: Propio (ente): Agencia Digital de Andalucía (ADA) | D11: Propio (ente): Aragonesa de Servicios Telemáticos (AST) | E11: Sin verificar | F11: Propio (ente): Agencia Balear de Digitalización, Ciberseguridad y Telecomunicaciones (ABDigital) | G11: Sin verificar | H11: Sin verificar | I11: Propio (ente): Agencia de Transformación Digital de Castilla-La Mancha | J11: Sin verificar | K11: Propio (ente): Centre de Telecomunicacions i Tecnologies de la Informació (CTTI) | L11: Consejería | M11: Sin verificar | N11: Propio (ente): Agencia para la Modernización Tecnológica de Galicia (AMTEGA) | O11: Propio (ente): Agencia para la Administración Digital de la Comunidad de Madrid (Madrid Digital) | P11: Propio (ente): Agencia Digital de la Región de Murcia (organismo autónomo) | Q11: Sin verificar | R11: Propio (ente): EJIE, Sociedad Informática del Gobierno Vasco, S.A. | S11: Sin verificar | T11: =COUNTIF(C11:S11,"Propio*") -> 9 | U11: =COUNTIF(C11:S11,"Sin verificar") -> 7 | V11: =1+T11 -> 10 | W11: Parcial, por adhesión voluntaria a servicios comunes de la AGE; no sustituye a los servicios TIC autonómicos. | X11: Autoorganización: cada administración gestiona sus propios sistemas de información (art. 148.1.1ª CE y estatutos). La Ley 40/2015 obliga a la interoperabilidad y permite reutilizar y adherirse a soluciones de otras administraciones. | Y11: https://www.boe.es/buscar/doc.php?id=BOE-A-2024-22929 https://www.juntadeandalucia.es/boja/2021/65/43 https://ast.aragon.es/sites/default/files/ast_memoriaactividad2016_resumen.pdf https://www.caib.es/eboibfront/eli/es-ib/d/2025/12/19/63/dof/spa/pdf https://www.boe.es/eli/es-cm/l/2024/03/15/1 https://documents.dadesobertes.gencat.cat/convenis/docs/2021/2021_5_1536/2021_5_1536_0.pdf https://pdr-mediorural.xunta.gal/sites/default/files/inline-files/D.252.11.castellano.pdf https://www.bocm.es/boletin/CM_Orden_BOCM/2026/07/14/BOCM-20260714-12.PDF https://www.boe.es/buscar/act.php?id=BORM-s-2022-90316 https://www.ejie.euskadi.eus/who-we-are/-/legal-and-corporate-framework/ https://laadministracionaldia.inap.es/noticia.asp?id=1515740
A12: Agencias de investigación e innovación | B12: Agencia Estatal de Investigación (AEI) y Centro para el Desarrollo Tecnológico y la Innovación (CDTI, E.P.E.) | C12: Consejería | D12: Propio (ente): Fundación Agencia Aragonesa para la Investigación y el Desarrollo (ARAID) | E12: Propio (ente): Agencia de Ciencia, Competitividad Empresarial e Innovación del Principado de Asturias (SEKUENS) | F12: Sin verificar | G12: Propio (órgano): Agencia Canaria de Investigación, Innovación y Sociedad de la Información (ACIISI) | H12: Sin verificar | I12: Propio (ente): Agencia de Investigación e Innovación de Castilla-La Mancha (organismo autónomo) | J12: Sin verificar | K12: Propio (ente): Agència de Gestió d'Ajuts Universitaris i de Recerca (AGAUR) | L12: Propio (ente): Agència Valenciana de la Innovació (AVI), integrada operativamente en IVACE+i | M12: Sin verificar | N12: Propio (ente): Axencia Galega de Innovación (GAIN) | O12: Sin verificar | P12: Propio (ente): Fundación Séneca, Agencia de Ciencia y Tecnología de la Región de Murcia | Q12: Sin verificar | R12: Sin verificar | S12: Sin verificar | T12: =COUNTIF(C12:S12,"Propio*") -> 8 | U12: =COUNTIF(C12:S12,"Sin verificar") -> 8 | V12: =2+T12 -> 10 | W12: Sí, en concurrencia: AEI y CDTI financian a entidades de todas las CCAA mediante convocatorias estatales; los organismos autonómicos añaden fondos propios y no cubren huecos territoriales. | X12: Fomento y coordinación general de la investigación científica y técnica: competencia estatal (art. 149.1.15ª CE). Las CCAA pueden fomentar la investigación en su territorio (art. 148.1.17ª CE y estatutos), coordinadas por la Ley 14/2011 de la Ciencia y el Consejo de Política Científica, Tecnológica y de Innovación. | Y12: https://www.boe.es/eli/es/rd/2015/11/27/1067 https://www.boe.es/eli/es/rd/2026/04/01/263 https://laadministracionaldia.inap.es/noticia.asp?id=1264632 https://www.juntadeandalucia.es/export/presup2026/memoria/memoria2-e-2.pdf https://www.boe.es/boe/dias/2019/01/28/pdfs/BOE-A-2019-994.pdf https://boe.es/buscar/doc.php?id=BOE-A-2023-1605 https://www.gobiernodecanarias.org/conocimiento/la_agencia/ https://castillalamancha.es/sites/default/files/documentos/pdf/20220629/08_decreto_54_2022_estatutos_agencia_investigacion.pdf https://laadministracionaldia.inap.es/noticia.asp?id=1266605 https://www.uv.es/serinves/convocatories/2026/Avi%202026/instruccions_internes.pdf https://www.xunta.gal/dog/Publicados/2012/20120127/AnuncioCA04-230112-11332_es.html https://www.borm.es/services/anuncio/ano/2026/numero/2481/pdf?id=843163
A13: Agencias de la energía | B13: Instituto para la Diversificación y Ahorro de la Energía (IDAE) | C13: Propio (ente): Agencia Andaluza de la Energía | D13: Consejería | E13: Propio (ente): Fundación Asturiana de la Energía (FAEN) | F13: Propio (ente): Instituto Balear de la Energía (IBE) | G13: Consejería | H13: Sin verificar | I13: Sin verificar | J13: Propio (ente): Ente Regional de la Energía de Castilla y León (EREN) | K13: Propio (ente): Institut Català d'Energia (ICAEN) | L13: Propio (ente): IVACE+i (Instituto Valenciano de Competitividad e Innovación), área de Energía | M13: Propio (ente): Agencia Extremeña de la Energía (AGENEX), entidad pública empresarial | N13: Propio (ente): Instituto Enerxético de Galicia (INEGA) | O13: Propio (ente): Fundación de la Energía de la Comunidad de Madrid (FENERCOM) | P13: Consejería | Q13: Consejería | R13: Propio (ente): Ente Vasco de la Energía (EVE) | S13: Consejería | T13: =COUNTIF(C13:S13,"Propio*") -> 10 | U13: =COUNTIF(C13:S13,"Sin verificar") -> 2 | V13: =1+T13 -> 11 | W13: Parcial: el IDAE actúa en todo el territorio, pero buena parte de sus líneas se ejecutan a través de las CCAA (consejería o agencia regional). Donde no hay agencia, la gestiona la consejería. | X13: Bases del régimen energético y planificación económica general: competencias estatales (art. 149.1.13ª y 25ª CE). A las CCAA corresponden el desarrollo normativo y la ejecución, incluida la gestión de ayudas de ahorro, eficiencia y renovables en su territorio. | Y13: https://www.cnmc.es/sites/default/files/energia/consumidores/201610_Enlaces%2520eficiencia%2520energ%C3%A9tica%5B1%5D.pdf https://juntadeandalucia.es/boja/2003/189/1 https://www.boe.es/buscar/pdf/2019/BOE-A-2019-5579-consolidado.pdf https://www.gobiernodecanarias.org/boc/2022/257/001.html https://derecholocal.es/?p=13612 https://laadministracionaldia.inap.es/noticia.asp?id=1241987 https://www.boe.es/diario_boe/txt.php?id=BOE-A-2026-15131 https://laadministracionaldia.inap.es/noticia.asp?id=1111574 https://transparencia.carm.es/wres/transparencia/doc/Consejo_Gobierno/2018-06-14/punto_25_ENERAGEN.pdf https://www.boe.es/buscar/act.php?id=BOE-A-2024-1778 https://www.boe.es/eli/es-ri/l/2022/11/02/13
A14: Seguridad ferroviaria | B14: Agencia Estatal de Seguridad Ferroviaria (AESF) | C14: Sin verificar | D14: Lo cubre el Estado | E14: Lo cubre el Estado | F14: Sin verificar | G14: No existe | H14: Lo cubre el Estado | I14: Lo cubre el Estado | J14: Lo cubre el Estado | K14: Consejería | L14: Propio (ente): Agència Valenciana de Seguretat Ferroviària (AVSF) | M14: Lo cubre el Estado | N14: Lo cubre el Estado | O14: Sin verificar | P14: Lo cubre el Estado | Q14: Lo cubre el Estado | R14: No existe | S14: Lo cubre el Estado | T14: =COUNTIF(C14:S14,"Propio*") -> 1 | U14: =COUNTIF(C14:S14,"Sin verificar") -> 3 | V14: =1+T14 -> 2 | W14: Parcial. La AESF cubre por ley toda la RFIG en las 17 CCAA. No cubre las redes autonómicas (FGC, FGV, Euskotren, SFM) ni metros y tranvías: su informe 2025 los excluye y en Madrid la propia AESF declara que no tiene competencia sobre Metro. No se ha encontrado ninguna encomienda o convenio por el que la AESF supervise una red autonómica. Extenderla requeriría un convenio o una encomienda con cada comunidad, o un cambio legal. | X14: Los ferrocarriles que discurren íntegramente por el territorio de una comunidad son de competencia autonómica (art. 148.1.5ª CE y estatutos). La RFIG y su seguridad son estatales (art. 149.1.21ª CE; Ley 38/2015, del Sector Ferroviario, con la AESF como autoridad de seguridad). | Y14: https://www.boe.es/eli/es/rd/2014/12/19/1072 https://www.era.europa.eu/sites/default/files/reports/ias%20nsa%20espa%C3%B1a%202025.pdf https://www.boe.es/eli/es-vc/l/2018/03/26/7/con https://www.boe.es/ccaa/dogv/2026/10425/r00001-00351.pdf https://www.boe.es/ccaa/dogc/2026/9680/f00001-00004.pdf https://www.euskadi.eus/contenidos/anuncio_tablon/con_3917055/es_def/adjuntos/Orden-consulta-publica-previa-LSF.pdf
A15: Agencias de salud pública | B15: Agencia Estatal de Salud Pública (AESAP) | C15: Consejería | D15: Consejería | E15: Consejería | F15: Propio (ente): Agencia de Salud Pública de las Illes Balears (ASPIB) | G15: Consejería | H15: Consejería | I15: Consejería | J15: Consejería | K15: Propio (órgano): Agència de Salut Pública de Catalunya (ASPCAT), sin personalidad jurídica | L15: Consejería | M15: Consejería | N15: Consejería | O15: Consejería | P15: Consejería | Q15: Propio (ente): Instituto de Salud Pública y Laboral de Navarra (ISPLN) | R15: Propio (ente): Instituto Vasco de Salud Pública (Osasungintza) | S15: Consejería | T15: =COUNTIF(C15:S15,"Propio*") -> 4 | U15: =COUNTIF(C15:S15,"Sin verificar") -> 0 | V15: =1+T15 -> 5 | W15: No. La AESAP no sustituye a las direcciones generales ni a las agencias autonómicas: la vigilancia y la intervención de salud pública siguen siendo autonómicas. Solo coordina e integra la información. | X15: Sanidad: bases y coordinación general son estatales (art. 149.1.16ª CE); la gestión de la salud pública es autonómica (estatutos; Ley 33/2011, General de Salud Pública). La AESAP es un órgano estatal de vigilancia, preparación y coordinación y no asume la ejecución autonómica. | Y15: https://www.boe.es/eli/es/l/2025/07/28/7 https://www.sanidad.gob.es/en/profesionales/saludPublica/saludAmbLaboral/calidadAguas/piscinas/pdf/CCAA_SILOE_R_ene21.pdf https://www.boe.es/buscar/act.php?id=BOE-A-2011-2108 https://www.euskadi.eus/web01-bopv/es/bopv2/datos/2023/12/2305490a.shtml https://govern.cat/govern/docs/2017/10/24/16/16/6bc122b4-de02-4974-9a53-0974dfdc3a37.pdf https://aplicacions.economia.gencat.cat/wpres/2023/pdf/MP_SA14.pdf
A16: Agencias de cooperación al desarrollo | B16: Agencia Española de Cooperación Internacional para el Desarrollo (AECID) | C16: Propio (ente): Agencia Andaluza de Cooperación Internacional para el Desarrollo (AACID) | D16: Sin verificar | E16: Propio (órgano): Agencia Asturiana de Cooperación al Desarrollo | F16: Sin verificar | G16: Sin verificar | H16: Sin verificar | I16: Sin verificar | J16: Sin verificar | K16: Propio (ente): Agència Catalana de Cooperació al Desenvolupament (ACCD) | L16: Sin verificar | M16: Propio (ente): Agencia Extremeña de Cooperación Internacional para el Desarrollo (AEXCID) | N16: Sin verificar | O16: Sin verificar | P16: Sin verificar | Q16: Sin verificar | R16: Propio (ente): Agencia Vasca de Cooperación para el Desarrollo (eLankidetza) | S16: Sin verificar | T16: =COUNTIF(C16:S16,"Propio*") -> 5 | U16: =COUNTIF(C16:S16,"Sin verificar") -> 12 | V16: =1+T16 -> 6 | W16: No por defecto. Las CCAA gestionan su propia AOD. La AECID podría canalizar fondos autonómicos mediante convenio (hay convenios puntuales, p. ej. Murcia-AECID 2017 según el Consejo de Gobierno de la CARM), pero no hay cobertura general. | X16: La política de cooperación internacional del Estado deriva del art. 149.1.3ª CE. La Ley 1/2023, de Cooperación para el Desarrollo Sostenible y la Solidaridad Global, reconoce la cooperación descentralizada de CCAA y entes locales (cap. IV, sección 2ª), que estas financian y gestionan con fondos propios. | Y16: https://www.boe.es/eli/es/rd/2007/10/26/1403/con https://www.juntadeandalucia.es/boja/2006/98/d2.pdf https://euskadi.eus:443/bopv2/datos/2008/07/0804175a.pdf https://doe.juntaex.es/pdfs/doe/2024/1420o/24062490.pdf https://www.asturias.es/bopa/2026/06/15/2026-04797.pdf
A17: Institutos de seguridad y salud laboral | B17: Instituto Nacional de Seguridad y Salud en el Trabajo (INSST, O.A., M.P.) | C17: Propio (ente): Instituto Andaluz de Prevención de Riesgos Laborales (IAPRL) | D17: Propio (órgano): Instituto Aragonés de Seguridad y Salud Laboral (ISSLA) | E17: Propio (ente): Instituto Asturiano de Prevención de Riesgos Laborales (IAPRL) | F17: Propio (ente): Instituto Balear de Seguridad y Salud Laboral (IBASSAL) | G17: Propio (ente): Instituto Canario de Seguridad Laboral (ICASEL) | H17: Propio (ente): Instituto Cántabro de Seguridad y Salud en el Trabajo (ICASST) | I17: Consejería | J17: Consejería | K17: Consejería | L17: Propio (ente): Instituto Valenciano de Seguridad y Salud en el Trabajo (INVASSAT) | M17: Consejería | N17: Propio (ente): Instituto de Seguridad y Salud Laboral de Galicia (ISSGA) | O17: Propio (ente): Instituto Regional de Seguridad y Salud en el Trabajo (IRSST) | P17: Propio (ente): Instituto de Seguridad y Salud Laboral de la Región de Murcia (ISSL) | Q17: Propio (ente): Instituto de Salud Pública y Laboral de Navarra (ISPLN) | R17: Propio (ente): Instituto Vasco de Seguridad y Salud Laborales (OSALAN) | S17: Consejería | T17: =COUNTIF(C17:S17,"Propio*") -> 12 | U17: =COUNTIF(C17:S17,"Sin verificar") -> 0 | V17: =1+T17 -> 13 | W17: No. La ejecución está transferida a las 17 CCAA, que la ejercen con institutos propios o desde la consejería. El INSST no presta esos servicios en territorio autonómico; solo hace investigación, normalización y estudios estatales y coordina. | X17: Legislación laboral estatal; su ejecución corresponde a las CCAA (art. 149.1.7ª CE). La Ley 31/1995, de PRL, encarga al INSST el apoyo técnico y la colaboración con los órganos técnicos autonómicos, que ejercen el asesoramiento, la investigación de accidentes y el apoyo técnico a la ITSS en su territorio. | Y17: https://www.insst.es/el-instituto/conoce-el-instituto/mision-y-funciones https://www.insst.es/relaciones-institucionales/ambito-autonomico/enlaces-organismos-ccaa-en-prl-con-estrategias-sst https://juntadeandalucia.es/boja/2006/251/2 https://cdn.juntadeandalucia.es/boja/2020/4/BOJA20-004-00002-31-01_00167569.pdf https://intranet.caib.es/eboibfront/pdf/es/2024/89/1166156 https://laadministracionaldia.inap.es/noticia.asp?id=1225149
A18: Entes de emergencias 112 | B18: Dirección General de Protección Civil y Emergencias (Ministerio del Interior) | C18: Propio (ente): Agencia de Emergencias de Andalucía (antes Agencia de Seguridad y Gestión Integral de Emergencias, ASGIE) | D18: Sin verificar | E18: Propio (ente): Servicio de Emergencias del Principado de Asturias (SEPA) | F18: Propio (ente): Gestió d'Emergències de les Illes Balears (GEIB), entidad pública empresarial | G18: Propio (ente): Gestión de Servicios para la Salud y Seguridad en Canarias (GSC), sociedad pública | H18: Propio (ente): Servicio de Emergencias de Cantabria (SEMCA), organismo autónomo | I18: Sin verificar | J18: Consejería | K18: Propio (ente): Centre d'Atenció i Gestió de Trucades d'Urgència 112 Catalunya (CAT112), entidad de derecho público | L18: Propio (ente): Agència Valenciana de Seguretat i Resposta a les Emergències (AVSRE), organismo autónomo | M18: Sin verificar | N18: Propio (ente): Axencia Galega de Emerxencias (AXEGA), agencia pública autonómica | O18: Propio (ente): Agencia de Seguridad y Emergencias Madrid 112 (ASEM112), ente de derecho público de régimen especial | P18: Sin verificar | Q18: Consejería | R18: Sin verificar | S18: Sin verificar | T18: =COUNTIF(C18:S18,"Propio*") -> 9 | U18: =COUNTIF(C18:S18,"Sin verificar") -> 6 | V18: =0+T18 -> 9 | W18: No. El Estado no presta el 112 en ninguna comunidad: los 17 centros 112 son autonómicos. La duplicación es entre comunidades, en la forma de gestionar (ente o servicio), no con el Estado. | X18: Protección civil: competencia concurrente. Las CCAA prestan el servicio 112 y gestionan las emergencias de su ámbito (RD 903/1997; estatutos); el Estado gestiona las emergencias de interés nacional y coordina el sistema (Ley 17/2015, del Sistema Nacional de Protección Civil). | Y18: https://www.boe.es/eli/es/l/2015/07/09/17 https://laadministracionaldia.inap.es/noticia.asp?id=1246471 https://laadministracionaldia.inap.es/noticia.asp?id=1265294 https://laadministracionaldia.inap.es/noticia.asp?id=1250448 https://ficheiros-web.xunta.gal/cartas_de_servizo/aprobadas/emerxencias/Carta_Servizos_gal.pdf https://intranet.caib.es/eboibfront/pdf/ca/2026/30/1214222 https://parcan.es/files/pub/bop/11l/2024/417/bo417.pdf https://laadministracionaldia.inap.es/noticia.asp?id=1267282 https://laadministracionaldia.inap.es/noticia.asp?id=1267294
A19: Observatorios de convivencia escolar | B19: Observatorio Estatal de la Convivencia Escolar | C19: Propio (órgano): Observatorio para la Convivencia Escolar en Andalucía | D19: Propio (órgano): Observatorio autonómico de convivencia escolar de Aragón (el informe no da el nombre exacto) | E19: Propio (órgano): Observatorio autonómico de convivencia escolar del Principado de Asturias (el informe no da el nombre exacto) | F19: Propio (órgano): Institut per a la Convivència i l'Èxit Escolar (Convivèxit) | G19: Sin verificar | H19: Propio (órgano): Observatorio autonómico de convivencia escolar de Cantabria (el informe no da el nombre exacto) | I19: Propio (órgano): Observatorio autonómico de convivencia escolar de Castilla-La Mancha (el informe no da el nombre exacto) | J19: Propio (órgano): Observatorio de la Comunidad de Castilla y León, sección de convivencia escolar | K19: Sin verificar | L19: Propio (órgano): Observatorio para la Convivencia Escolar (desde 2023, pleno conjunto «Observatorio Igualdad y Convivencia») | M19: Propio (órgano): Observatorio para la Convivencia Escolar en Extremadura | N19: Propio (órgano): Consejo para la Convivencia Escolar de la Comunidad Autónoma de Galicia | O19: Propio (órgano): Observatorio autonómico de convivencia escolar de la Comunidad de Madrid (el informe no da el nombre exacto) | P19: Propio (órgano): Observatorio autonómico de convivencia escolar de la Región de Murcia (el informe no da el nombre exacto) | Q19: Sin verificar | R19: Propio (órgano): Observatorio autonómico de convivencia escolar del País Vasco (el informe no da el nombre exacto) | S19: Propio (órgano): Observatorio autonómico de convivencia escolar de La Rioja (el informe no da el nombre exacto) | T19: =COUNTIF(C19:S19,"Propio*") -> 14 | U19: =COUNTIF(C19:S19,"Sin verificar") -> 3 | V19: =1+T19 -> 15 | W19: Parcial. El Observatorio Estatal (RD 275/2007, modificado por RD 3/2018) es un órgano colegiado consultivo de ámbito estatal: estudia, informa y propone. No gestiona la convivencia en los centros, que corresponde a las CCAA, y no hay convenios para que cubra a una CCAA sin observatorio propio. | X19: Educación: el Estado dicta las normas básicas (art. 149.1.30 CE, LOE/LOMLOE) y las CCAA las desarrollan, ejecutan y gestionan los centros. Cada administración educativa puede crear sus propios órganos de convivencia; ninguna ley lo obliga. | Y19: https://educacionfpydeportes.gob.es/dam/jcr:9b630aa5-b767-4739-848b-65a46bcebbf9/informe-convivencia-ccaa-v-mayo--2024.pdf https://educacionfpydeportes.gob.es/ca/dam/jcr:6e1130b2-96f3-4008-b2ab-c6dbb76d473f/rd-observatorio-estatal-convivencia-escolar.pdf https://vlex.es/vid/real-decreto-3-2018-700920453 https://sirdoc.ccyl.es/Biblioteca/Dosieres/DL203AtencionViolenciaGenero/pdfs/CyL-Decreto-52-2014-Observatorio.pdf https://doe.juntaex.es/pdfs/doe/2026/1040o/26050065.pdf https://www.caib.es/sites/convivexit/ca/normativa_autonamica/
A20: Consejos de la juventud | B20: Consejo de la Juventud de España (CJE) | C20: Propio (órgano): Consejo de la Juventud de Andalucía | D20: Propio (ente): Consejo de la Juventud de Aragón | E20: Propio (ente): Consejo de la Juventud del Principado de Asturias (Conseyu de la Mocedá) | F20: Sin verificar | G20: Sin verificar | H20: Propio (ente): Consejo de la Juventud de Cantabria | I20: Propio (ente): Consejo de la Juventud de Castilla-La Mancha | J20: Propio (ente): Consejo de la Juventud de Castilla y León | K20: Sin verificar | L20: Sin verificar | M20: Propio (ente): Consejo de la Juventud de Extremadura | N20: Propio (órgano): Consejo Asesor y Consultivo de Juventud de Galicia | O20: Propio (órgano): Mesa de Políticas de Juventud de la Comunidad de Madrid (sustituye al Consejo de la Juventud, suprimido) | P20: Sin verificar | Q20: Propio (ente): Consejo de la Juventud de Navarra / Nafarroako Gazteriaren Kontseilua | R20: Sin verificar | S20: Propio (ente): Consejo de la Juventud de La Rioja | T20: =COUNTIF(C20:S20,"Propio*") -> 11 | U20: =COUNTIF(C20:S20,"Sin verificar") -> 6 | V20: =1+T20 -> 12 | W20: No sustitutiva. El CJE es una plataforma estatal; tras la Ley 15/2014 (reforma CORA) dejó de ser organismo autónomo y es una entidad corporativa de base privada. Los consejos autonómicos forman parte de él o se coordinan con él, pero no representa a la juventud ante cada gobierno autonómico. No hay convenios de cobertura. | X20: Juventud: es una competencia exclusiva autonómica según los Estatutos. El art. 48 CE obliga a todos los poderes públicos a promover la participación de la juventud. Cada CCAA regula su consejo por ley propia; el CJE actúa en el ámbito estatal. | Y20: https://www.cje.org/en/entidades/ https://www.cje.org/en/faq/ https://www.boe.es/eli/es-cb/l/2019/02/14/1/con/20190225 https://www.boe.es/boe/dias/2005/05/20/pdfs/A16971-16975.pdf https://boe.es/boe/dias/2025/03/20/pdfs/BOE-A-2025-5523.pdf https://laadministracionaldia.inap.es/noticia.asp?id=1127756 https://laadministracionaldia.inap.es/noticia.asp?id=1235364 https://www.boe.es/boe/dias/1985/05/22/pdfs/A14960-14961.pdf https://www.parcan.es/files/documentacion/dosieres/DOSS0102/DOSS0102DOC1424.PDF https://tematico.asturias.es/hacienda/cuen2005/doc/5/4_1.pdf https://www.juntadeandalucia.es/sites/default/files/2020-03/Proyecto%20de%20Ley%20de%20Juventud%20de%20Andaluc%C3%ADa.pdf https://www.cje.org/download/295/consejos-de-juventud/23033/res-2016-autonomiacjandalucia.pdf
A21: Observatorios de igualdad y violencia de género | B21: Observatorio Estatal de Violencia sobre la Mujer | C21: Propio (órgano): Observatorio Andaluz de la Violencia de Género | D21: Propio (órgano): Observatorio Aragonés de Violencia sobre la Mujer | E21: Sin verificar | F21: Propio (órgano): Observatori per a la Igualtat de les Illes Balears | G21: Propio (órgano): Observatorio de la Igualdad de Género (Instituto Canario de Igualdad) | H21: Propio (órgano): Observatorio de Igualdad de Género de Cantabria | I21: Sin verificar | J21: Propio (órgano): Observatorio de la Comunidad de Castilla y León, sección de género | K21: Propio (órgano): Observatori de la Igualtat de Gènere (OIG) | L21: Sin verificar | M21: Sin verificar | N21: Propio (órgano): Observatorio Galego da Violencia de Xénero | O21: Propio (órgano): Observatorio Regional de la Violencia de Género | P21: Propio (órgano): Observatorio de Igualdad de la Región de Murcia | Q21: Sin verificar | R21: Sin verificar | S21: Sin verificar | T21: =COUNTIF(C21:S21,"Propio*") -> 10 | U21: =COUNTIF(C21:S21,"Sin verificar") -> 7 | V21: =1+T21 -> 11 | W21: Parcial. El OEVM (LO 1/2004, art. 30; RD 253/2006) es un órgano colegiado adscrito al Ministerio de Igualdad que elabora informes de ámbito estatal. No hay convenios para que sustituya a los observatorios autonómicos. Sin presupuesto propio: el gasto lo asume la DG contra la Violencia de Género (lote previo B1). | X21: Igualdad y violencia de género: el Estado fija el marco básico (LO 1/2004 y LO 3/2007; art. 149.1.1 CE) y las CCAA tienen competencias propias en políticas de mujer y asistencia social según sus Estatutos y leyes autonómicas. Cada CCAA puede crear sus órganos de seguimiento. | Y21: https://www.boe.es/eli/es/lo/2004/12/28/1 https://www.boe.es/eli/es/rd/2006/03/03/253/con/20220928 https://cdn.juntadeandalucia.es/boja/2010/116/d2.pdf https://www.parcan.es/files/documentacion/dosieres/DOSS0244/DOSS0244DOC5684.PDF https://www.caib.es/sites/participacio/es/n/observatori_per_a_la_igualtat/ https://vlex.es/vid/decreto-38-2015-27-563806338 https://sirdoc.ccyl.es/Biblioteca/Dosieres/DL203AtencionViolenciaGenero/pdfs/CyL-Decreto-52-2014-Observatorio.pdf https://dones.gencat.cat/content/dam/dones/03_ambits/observatori/01_coneix_nos/activitats/Memoria-OIG-2025_edicio.pdf https://www.lex.gal/es/normativa/detalle/3166/pdf/ https://www.bocm.es/boletin/CM_Orden_BOCM/2022/12/21/BOCM-20221221-47.PDF https://borm.es/services/anuncio/782935/pdf https://transparencia.carm.es/documents/184026/11587769/MAIN+Decreto+Observatorio+Igualdad.pdf/fb2f0a04-7b0e-47f6-a68f-6948b430238a https://www.boe.es/eli/es-nc/lf/2019/04/04/17/con
A22: Consejos audiovisuales (reguladores) | B22: Comisión Nacional de los Mercados y la Competencia (CNMC) | C22: Propio (ente): Consejo Audiovisual de Andalucía (CAA) | D22: Sin verificar | E22: Sin verificar | F22: Sin verificar | G22: Sin verificar | H22: Sin verificar | I22: Sin verificar | J22: Sin verificar | K22: Propio (ente): Consell de l'Audiovisual de Catalunya (CAC) | L22: Propio (ente): Consell de l'Audiovisual de la Comunitat Valenciana | M22: Sin verificar | N22: Sin verificar | O22: Consejería | P22: Sin verificar | Q22: Consejería | R22: Sin verificar | S22: Sin verificar | T22: =COUNTIF(C22:S22,"Propio*") -> 3 | U22: =COUNTIF(C22:S22,"Sin verificar") -> 12 | V22: =1+T22 -> 4 | W22: No. La CNMC asumió la regulación audiovisual estatal en 2013 (Ley 3/2013) y supervisa a los prestadores de ámbito estatal. Los prestadores autonómicos y locales los supervisa la autoridad de cada CCAA, sea un consejo independiente o la propia consejería. No hay convenios para que la CNMC cubra a una CCAA. | X22: Audiovisual: el Estado fija las bases del régimen de radio y televisión (art. 149.1.27 CE; Ley 13/2022, General de Comunicación Audiovisual) y las CCAA las desarrollan y ejecutan. La supervisión se reparte según el ámbito de cobertura del prestador. | Y22: https://www.cnmc.es/en/ambitos-de-actuacion/audiovisual/actividad-internacional https://www.rirm.org/en/caa-audiovisual-council-of-andalusia/ https://vlex.es/vid/decreto-121-2022-16-910713792 https://redopositor.com/oposiciones/convocatoria/resolucio-de-14-de-juliol-de-2026-de-la-presidencia-per-la-qual-es-pro--00d7ce64/ https://www.boe.es/eli/es-md/l/2001/04/18/2/con/20231229 https://parlamentodenavarra.es/sites/default/files/boletines/B2011821.pdf https://www.boe.es/eli/es-ib/l/2010/12/22/15/con
A24: Rojo: la comunidad tiene organismo propio sobre el tema. Verde: no lo tiene (lo cubre el Estado, lo hace la consejería o no existe). Gris: sin verificar. "Organismos en total" suma el estatal y los autonómicos verificados; el máximo posible es 18. Fuentes oficiales por celda en el dashboard y en los JSON de trabajo.

Sheet Hoja 1
A1: ID | B1: Ámbito | C1: Comunidad autónoma | D1: Periodo presidencial | E1: Nombre | F1: Tipo de creación / transformación | G1: Fecha legal | H1: Norma fundacional | I1: Mandato en teoría | J1: Poder real: juicio basado en evidencia | K1: Presupuesto propio (EUR millones) | L1: Año del presupuesto | M1: Base del presupuesto numérico | N1: Corte del presupuesto numérico | O1: Estado de cuantificación | P1: Crédito inicial (EUR millones) | Q1: Modificación neta (EUR millones) | R1: Presupuesto: texto completo | S1: Corte: texto completo | T1: Estado legal y operativo | U1: Límites del juicio | V1: Duplicidades: clasificación (juicio) | W1: IDs relacionados | X1: Duplicidades: explicación y límite | Y1: Fuentes de duplicidad | Z1: Fuentes de la ficha | AA1: Importe contextual (EUR millones; NO sumar) | AB1: Año / periodo contextual | AC1: Base contextual | AD1: Nombre del titular del importe | AE1: URL del documento | AF1: Fecha de revisión | AG1: Personal: personas (ocupadas) | AH1: Año del personal | AI1: Base del personal | AJ1: Estado de verificación del personal | AK1: Fuente del personal | AL1: Crédito de personal (EUR millones) | AM1: Año del coste de personal | AN1: Base del coste de personal | AO1: Estado de verificación del coste | AP1: Fuente del coste | AQ1: Gasto de personal ejecutado (EUR millones) | AR1: Año del gasto de personal | AS1: Corte de ejecución de personal | AT1: Base de ejecución de personal | AU1: Fuente de ejecución de personal | AV1: Estado de verificación de ejecución | AW1: Cobertura presupuesto / personal / salarios | AX1: Puestos aprobados / presupuestados | AY1: Fecha puestos aprobados | AZ1: Base de puestos aprobados | BA1: Fuente puestos aprobados | BB1: Notas de personal y apoyo ministerial | BC1: Papel en leyes / reglamentos: verificación | BD1: Informe obligatorio (preceptivo): ámbito | BE1: Informe vinculante / consentimiento requerido | BF1: Bloqueo o demora: alcance y límite | BG1: Norma / artículo sobre consulta | BH1: Fuente legal de consulta normativa | BI1: Pagos de personal 2026 hasta 31/08 (EUR millones) | BJ1: Crédito personal comparativo2025, edición08.2026 (EUR millones) | BK1: Obligaciones personal comparativo2025, edición08.2026 (EUR millones) | BL1: Crédito personal inicial / otra base (EUR millones; NO sumar) | BM1: Base / fecha del crédito alternativo | BN1: Notas de conciliación de crédito y ejecución | BO1: Crédito personal 2025 cierre (EUR millones) | BP1: Gasto personal 2025 reconocido anual (EUR millones) | BQ1: Pagos personal 2025 anual (EUR millones) | BR1: Año y corte anual personal | BS1: Base anual de personal | BT1: Fuente anual de personal | BU1: Verificación anual / conciliación | BV1: Clasificación: útil / no útil | BW1: Clasificación: veredicto | BX1: Clasificación: función | BY1: Clasificación: duplicidad | BZ1: Clasificación: exigida por la UE | CA1: Clasificación: actividad reciente | CB1: Clasificación: motivo | CC1: Clasificación: base en el P100 | CD1: Clasificación: destino de sus funciones | CE1: Tema funcional | CF1: Organismos del mismo tema (Estado + CCAA, verificados) | CG1: Coste de apoyo (sin presupuesto propio): unidad, vocales y dietas | CH1: Coste de personal por persona 2025 (EUR, calculado) | CI1: Desglose: personal técnico/científico/inspector | CJ1: Desglose: personal de administración y apoyo | CK1: Desglose: otro / no clasificable | CL1: Desglose: total de referencia | CM1: Puestos de libre designación | CN1: Altos cargos | CO1: Personal eventual (confianza) | CP1: Desglose: unidad y fecha | CQ1: Desglose: criterio de clasificación | CR1: Desglose: fuente | CS1: Desglose: verificación
A2: 1 | B2: Estatal | C2: Estado | D2: Zapatero | E2: Agencia Estatal de Evaluación de las Políticas Públicas y la Calidad de los Servicios (AEVAL) | F2: Nueva agencia con absorción de unidades ministeriales | G2: 2006-12-01 | H2: RD 1418/2006 | I2: Evaluar políticas públicas y mejorar la calidad de servicios; informes, evaluaciones y certificación de calidad. | J2: Juicio: función técnica real, no regulador con poder de sanción. Memoria 2009 acredita evaluaciones, plantilla técnica y ejecución de 5.601.938,42 EUR (93,98% del presupuesto definitivo). | O2: Sin presupuesto propio actual: supresión/extinción; no cuantificar sustituto | R2: Sin presupuesto propio actual por supresión. El importe de 2009 es evidencia histórica de actividad, no presupuesto actual. | S2: 31/08/2026, salvo indicación distinta | T2: Norma derogada y agencia suprimida con efectos 29/07/2017 por RD 769/2017; funciones reubicadas. | U2: El informe histórico no mide toda su vida ni la eficacia final de sus recomendaciones. | V2: Sucesión funcional histórica | W2: 45 | X2: AEVAL fue suprimida en 2017 y sus funciones reubicadas; la agencia de 2026 sucede al Instituto intermedio. No son dos presupuestos actuales de la misma agencia. | Y2: https://www.boe.es/buscar/act.php?id=BOE-A-2006-21902 https://www.boe.es/diario_boe/txt.php?id=BOE-A-2010-15779 https://www.boe.es/diario_boe/txt.php?id=BOE-A-2026-2553 https://www.boe.es/boe/dias/2026/05/12/pdfs/BOE-A-2026-10246.pdf | Z2: https://www.boe.es/buscar/act.php?id=BOE-A-2006-21902 https://www.boe.es/diario_boe/txt.php?id=BOE-A-2010-15779 | AE2: https://files.instinct.com/q91pr53q4umo-entidades-publicas-poder-y-presupuesto | AF2: 12/10/2026 | AI2: Personas realmente ocupadas; no equiparar vocales, puestos RPT o apoyo ministerial con plantilla | AJ2: Pendiente: sin cifra de personal ocupado verificada en el conjunto actual | AO2: Pendiente: sin coste de personal individual verificado en el conjunto actual | AV2: Pendiente: no se ha verificado gasto salarial ejecutado individual en esta versión | AW2: SIN CIFRA INDIVIDUAL VERIFICADA de presupuesto, personal ocupado y salarios ejecutados; investigación pendiente, no prueba de falta de publicación | BC2: Revisado: AEVAL histórica | BD2: Evaluación de políticas, informes solicitados y contratos gestión. No informe previo general de leyes identificado. | BE2: No consentimiento favorable para leyes establecido en funciones revisadas. | BF2: No veto legislativo identificado en estas cláusulas; no pretende descartar obligaciones sectoriales en otras normas. | BG2: RD1418/2006 art6 | BH2: https://www.boe.es/buscar/act.php?id=BOE-A-2006-21902 | BV2: Extinguida | BW2: Extinguida | BX2: Extinguida o no constituida | BY2: 3 organismos sobre este tema entre el Estado y las CCAA (verificados) | BZ2: No | CA2: No aplica (no vigente) | CB2: Suprimida en 2017 (RD 769/2017); funciones reubicadas y hoy en la Agencia Estatal de Evaluación (ID 45). | CE2: Evaluación de políticas públicas | CF2: 3 | CH2: =IF(AND(ISNUMBER(BP2),ISNUMBER(AG2),AG2>0),BP2*1000000/AG2,"")
A3: 2 | B3: Estatal | C3: Estado | D3: Zapatero | E3: Agencia Estatal de Seguridad Aérea (AESA) | F3: Nueva entidad; hereda tareas de la Dirección General de Aviación Civil | G3: 2008-02-08 | H3: RD 184/2008 | I3: Supervisión de seguridad de aviación civil; inspección, autorizaciones y potestades administrativas. | J3: Juicio: poder ejecutivo real, no observatorio decorativo. Las autorizaciones e inspecciones producen efectos sobre operadores. | K3: 89.455 | L3: 2026 | M3: Crédito total actualizado | N3: 31/08/2026 | O3: Cifra propia verificada | P3: 83.717 | Q3: 5.738 | R3: Presupuesto propio, crédito inicial 2026 83,717 M EUR; modificaciones netas +5,738 M; crédito total 89,455 M al 31/08/2026. IGAE p.99, cifras publicadas en miles de euros, no gasto ejecutado ni dotación solo administrativa. | S3: 31/08/2026, salvo indicación distinta | T3: Vigente; estado operativo no exhaustivamente auditado | U3: Plantilla ocupada: ver columna de personal (EPSAP enero 2026 o fuente indicada); no se ha verificado la independencia práctica de su dirección. | V3: No se ha identificado relación en esta revisión (no certifica ausencia) | X3: Revisión cualitativa del mandato y estado de las 95 fichas; no auditoría exhaustiva de funciones ni proyectos. | Z3: https://www.boe.es/eli/es/rd/2008/02/08/184/con https://www.igae.pap.hacienda.gob.es/sitios/igae/es-ES/Contabilidad/ContabilidadPublica/CPE/EjecucionPresupuestaria/Documents/ORGANISMOS%2008.%202026.pdf https://digital.gob.es/content/dam/portal-mtdfp/funcion-publica/rcp/boletin/2026_01/revision-agosto-2026/EPSAP_Enero_2026%20.pdf https://digital.gob.es/content/dam/portal-mtdfp/funcion-publica/rcp/notaepsap/Noticia_EPSAP_Enero_26.pdf | AE3: https://files.instinct.com/q91pr53q4umo-entidades-publicas-poder-y-presupuesto | AF3: 12/10/2026 | AG3: 346 | AH3: 2026-01 | AI3: Efectivos (personas) según Estadística del Personal al Servicio de las AA.PP. (EPSAP) enero 2026, Tabla 4.1 p.37: 340 funcionarios de carrera + 6 personal laboral + 0 otro personal ('-' en la tabla) = 346. Datos a enero de 2026 (la publicación no indica día). Estadística oficial de la DGFP; no son puestos RPT ni número medio anual. | AJ3: Cifra de personal publicada en fuente primaria; fecha indicada, no inferir vigencia posterior | AK3: https://digital.gob.es/content/dam/portal-mtdfp/funcion-publica/rcp/boletin/2026_01/revision-agosto-2026/EPSAP_Enero_2026%20.pdf | AL3: 23.308 | AM3: 2026 | AN3: Capítulo 1: crédito TOTAL actualizado IGAE, corte 31/08/2026 | AO3: Crédito autorizado, no gasto realizado ni solo salarios | AP3: https://www.igae.pap.hacienda.gob.es/sitios/igae/es-ES/Contabilidad/ContabilidadPublica/CPE/EjecucionPresupuestaria/Documents/ORGANISMOS%2008.%202026.pdf | AQ3: 13.226 | AR3: 2026 | AS3: Hasta 31/08/2026:8 meses, NO año completo | AT3: Capítulo 1: obligaciones reconocidas; incluye costes de personal, no desglose salarial puro | AU3: https://www.igae.pap.hacienda.gob.es/sitios/igae/es-ES/Contabilidad/ContabilidadPublica/CPE/EjecucionPresupuestaria/Documents/ORGANISMOS%2008.%202026.pdf | AV3: Fuente primaria cotejada contra fila y unidad milesEUR; no estimación | AW3: Crédito y gasto de personal individual verificados; plantilla ocupada verificada a enero de 2026 (EPSAP, efectivos); puestos RPT no verificados | BC3: Revisado: AESA: iniciativa normativa y asistencia técnica | BD3: Propone normas en su ámbito. Los informes urbanísticos vinculantes que aparecen en la modificación de estructura ministerial son de DGAC, no atribución propia de AESA. | BE3: No consentimiento favorable ni veto legislativo establecido en las cláusulas revisadas. | BF3: Revisión limitada a las atribuciones citadas: no descarta trámites sectoriales en otras normas. | BG3: RD184/2008 art9.1k y9.2; modificaciónDGAC | BH3: https://www.boe.es/buscar/act.php?id=BOE-A-2008-2595 | BI3: 13.226 | BJ3: 23.308 | BK3: 12.718 | BN3: IGAE: columnas 2026 crédito / obligaciones / pagos;2025 crédito y obligaciones al mismo 31/08. No comparar 8 meses con año completo. Capítulo 1 no equivale solo a sueldos. PlantillaRPT del lote no incorporada sin verificación adicional. | BO3: 23.308 | BP3: 20.143 | BQ3: 20.143 | BR3: 2025: hasta31/12/2025, año completo | BS3: Capítulo1: gastos de personal; obligaciones reconocidas, no solo salarios | BT3: https://www.igae.pap.hacienda.gob.es/sitios/igae/es-ES/Contabilidad/ContabilidadPublica/CPE/EjecucionPresupuestaria/Documents/ORGANISMOS%2012.%202025.pdf | BU3: Fuente primaria cotejada: IGAE edición12.2025, tabla y unidad milesEUR. No confundir con comparativa2025 de edición08.2026. | BV3: Útil | BW3: Mantener | BX3: Regulación o inspección de terceros | BZ3: Sí: el Reglamento (UE) 2018/1139 exige una autoridad nacional de aviación civil | CA3: Acreditada | CB3: Certifica e inspecciona la aviación civil; nadie más lo hace. | CC3: Aplicando el criterio del P100: Costes del Estado 9 (función técnica; exigida por la UE) | CE3: Seguridad aérea | CH3: =IF(AND(ISNUMBER(BP3),ISNUMBER(AG3),AG3>0),BP3*1000000/AG3,"") -> 58216.763
A4: 3 | B4: Estatal | C4: Estado | D4: Zapatero | E4: Agencia Estatal Antidopaje (AEA), hoy CELAD | F4: Nueva agencia; posterior ampliación/renombramiento | G4: 2008-02-08 | H4: RD 185/2008; antecedente habilitante LO 7/2006 | I4: Controles antidopaje, prevención e investigación; competencias actuales de control y sanción sujetas a legislación antidopaje posterior. | J4: Juicio: poder administrativo real; no contar AEPSAD (2013) y CELAD como creaciones independientes desde cero. | K4: 8.213 | L4: 2026 | M4: Crédito total actualizado | N4: 31/08/2026 | O4: Cifra propia verificada | P4: 6.644 | Q4: 1.569 | R4: Presupuesto propio, crédito inicial 2026 6,644 M EUR; modificaciones netas +1,569 M; crédito total 8,213 M al 31/08/2026. IGAE p.99, cifras publicadas en miles de euros, no gasto ejecutado ni dotación solo administrativa. | S4: 31/08/2026, salvo indicación distinta | T4: Continuidad institucional bajo denominaciones AEA, AEPSAD y CELAD. | U4: El estatuto de 2008 no basta para atribuir todas las potestades sancionadoras actuales; no se audita aquí su ejercicio. | V4: No se ha identificado relación en esta revisión (no certifica ausencia) | X4: Revisión cualitativa del mandato y estado de las 95 fichas; no auditoría exhaustiva de funciones ni proyectos. | Z4: https://www.boe.es/eli/es/rd/2008/02/08/185 https://www.igae.pap.hacienda.gob.es/sitios/igae/es-ES/Contabilidad/ContabilidadPublica/CPE/EjecucionPresupuestaria/Documents/ORGANISMOS%2008.%202026.pdf https://www.boe.es/diario_boe/txt.php?id=BOE-A-2013-6732 https://digital.gob.es/content/dam/portal-mtdfp/funcion-publica/rcp/boletin/2026_01/revision-agosto-2026/EPSAP_Enero_2026%20.pdf https://digital.gob.es/content/dam/portal-mtdfp/funcion-publica/rcp/notaepsap/Noticia_EPSAP_Enero_26.pdf | AE4: https://files.instinct.com/q91pr53q4umo-entidades-publicas-poder-y-presupuesto | AF4: 12/10/2026 | AG4: 24 | AH4: 2026-01 | AI4: Efectivos (personas) según Estadística del Personal al Servicio de las AA.PP. (EPSAP) enero 2026, Tabla 4.1 p.37: 17 funcionarios de carrera + 7 personal laboral + 0 otro personal ('-' en la tabla) = 24. Datos a enero de 2026 (la publicación no indica día). Estadística oficial de la DGFP; no son puestos RPT ni número medio anual. | AJ4: Cifra de personal publicada en fuente primaria; fecha indicada, no inferir vigencia posterior | AK4: https://digital.gob.es/content/dam/portal-mtdfp/funcion-publica/rcp/boletin/2026_01/revision-agosto-2026/EPSAP_Enero_2026%20.pdf | AL4: 1.889 | AM4: 2026 | AN4: Capítulo 1: crédito TOTAL actualizado IGAE, corte 31/08/2026 | AO4: Crédito autorizado, no gasto realizado ni solo salarios | AP4: https://www.igae.pap.hacienda.gob.es/sitios/igae/es-ES/Contabilidad/ContabilidadPublica/CPE/EjecucionPresupuestaria/Documents/ORGANISMOS%2008.%202026.pdf | AQ4: 1.12 | AR4: 2026 | AS4: Hasta 31/08/2026:8 meses, NO año completo | AT4: Capítulo 1: obligaciones reconocidas; incluye costes de personal, no desglose salarial puro | AU4: https://www.igae.pap.hacienda.gob.es/sitios/igae/es-ES/Contabilidad/ContabilidadPublica/CPE/EjecucionPresupuestaria/Documents/ORGANISMOS%2008.%202026.pdf | AV4: Fuente primaria cotejada contra fila y unidad milesEUR; no estimación | AW4: Crédito y gasto de personal individual verificados; plantilla ocupada verificada a enero de 2026 (EPSAP, efectivos); puestos RPT no verificados | BC4: Revisado: CELAD actual + AEA histórica | BD4: Sí: proyectos normativos AGE sobre dopaje y convenios internacionales. CCAA: a solicitud. | BE4: No se exige consentimiento favorable ni carácter vinculante del informe en la cláusula citada; no es veto. | BF4: Trámite previo en ámbito específico. Omitirlo puede generar cuestión procedimental, no veto parlamentario automático; efecto exacto requiere analizar procedimiento. | BG4: RD908/2022 art7.1ñ; RD185/2008 art5e | BH4: https://www.boe.es/buscar/doc.php?id=BOE-A-2022-17477 | BI4: 1.12 | BJ4: 1.889 | BK4: 0.869 | BN4: IGAE: columnas 2026 crédito / obligaciones / pagos;2025 crédito y obligaciones al mismo 31/08. No comparar 8 meses con año completo. Capítulo 1 no equivale solo a sueldos. PlantillaRPT del lote no incorporada sin verificación adicional. | BO4: 1.889 | BP4: 1.475 | BQ4: 1.475 | BR4: 2025: hasta31/12/2025, año completo | BS4: Capítulo1: gastos de personal; obligaciones reconocidas, no solo salarios | BT4: https://www.igae.pap.hacienda.gob.es/sitios/igae/es-ES/Contabilidad/ContabilidadPublica/CPE/EjecucionPresupuestaria/Documents/ORGANISMOS%2012.%202025.pdf | BU4: Fuente primaria cotejada: IGAE edición12.2025, tabla y unidad milesEUR. No confundir con comparativa2025 de edición08.2026. | BV4: Útil | BW4: Mantener | BX4: Regulación o inspección de terceros | BZ4: No | CA4: Acreditada | CB4: Hace los controles antidopaje con la independencia que exige el código mundial. | CC4: Aplicando el criterio del P100: Costes del Estado 9 (independencia exigida por el Código Mundial Antidopaje) | CE4: Antidopaje | CH4: =IF(AND(ISNUMBER(BP4),ISNUMBER(AG4),AG4>0),BP4*1000000/AG4,"") -> 61458.333
A5: 4 | B5: Estatal | C5: Estado | D5: Rajoy | E5: Agencia Estatal de Investigación (AEI) | F5: Nueva entidad con integración de unidades y programas preexistentes | G5: 2015-11-27 | H5: RD 1067/2015 | I5: Financiar, evaluar, conceder y seguir ayudas de investigación científica y técnica. | J5: Juicio: poder de asignación de recursos real. Decide y tramita ayudas, no es únicamente un foro. Reducción neta de crédito en 2026 acreditada, sin prueba del destino. | K5: 1214.005 | L5: 2026 | M5: Crédito total actualizado | N5: 31/08/2026 | O5: Cifra propia verificada | P5: 1419.995 | Q5: -205.99 | R5: Presupuesto propio, crédito inicial 2026 1.419,995 M EUR; modificaciones netas -205,990 M; crédito total 1.214,005 M al 31/08/2026. IGAE p.100, cifras publicadas en miles de euros, no gasto ejecutado ni dotación solo administrativa. | S5: 31/08/2026, salvo indicación distinta | T5: Vigente. | U5: No se ha demostrado la causa ni el destino de los -205,990 M EUR. No equivalen por sí solos a vaciamiento ni a desaparición de funciones. Obligaciones no financieras agosto: 458,023 M EUR, frente a 455,808 M en agosto 2025 (IGAE p.102). | V5: Ámbito temático próximo; funciones distintas; Ámbito I+D+i próximo; funciones y territorios distintos | W5: 33, 89, 112, 117 | X5: Investigación/innovación: AEI financia y sigue ayudas, CSIC realiza investigación, GAIN promueve innovación autonómica. No hay doble financiación demostrada. | Financiación, investigación o innovación en ámbitos estatales y autonómicos distintos; no equivalencia de programas ni doble financiación demostrada. | Y5: https://www.boe.es/eli/es/rd/2015/11/27/1067 https://www.igae.pap.hacienda.gob.es/sitios/igae/es-ES/Contabilidad/ContabilidadPublica/CPE/EjecucionPresupuestaria/Documents/ORGANISMOS%2008.%202026.pdf https://www.aei.gob.es/en/about-aei/plans-aei/Budget https://www.boe.es/eli/es/rd/2007/12/21/1730/con https://www.xunta.gal/dog/Publicados/2012/20120127/AnuncioCA04-230112-11332_es.html https://www.xunta.gal/dog/Publicados/2025/20251231/AnuncioC3B0-231225-0001_es.html https://boe.es/buscar/doc.php?id=BOE-A-2023-1605 https://www.boe.es/eli/es-cm/l/2020/07/10/4 | Z5: https://www.boe.es/eli/es/rd/2015/11/27/1067 https://www.igae.pap.hacienda.gob.es/sitios/igae/es-ES/Contabilidad/ContabilidadPublica/CPE/EjecucionPresupuestaria/Documents/ORGANISMOS%2008.%202026.pdf https://www.aei.gob.es/en/about-aei/plans-aei/Budget https://digital.gob.es/content/dam/portal-mtdfp/funcion-publica/rcp/boletin/2026_01/revision-agosto-2026/EPSAP_Enero_2026%20.pdf https://digital.gob.es/content/dam/portal-mtdfp/funcion-publica/rcp/notaepsap/Noticia_EPSAP_Enero_26.pdf https://www.aei.gob.es/sites/default/files/page/field_file/2025-01/PLAN%20DE%20ACTUACION%20ANUAL%202025%20APROBADO.pdf | AE5: https://files.instinct.com/q91pr53q4umo-entidades-publicas-poder-y-presupuesto | AF5: 12/10/2026 | AG5: 220 | AH5: 2026-01 | AI5: Efectivos (personas) según Estadística del Personal al Servicio de las AA.PP. (EPSAP) enero 2026, Tabla 4.1 p.37: 200 funcionarios de carrera + 20 personal laboral + 0 otro personal ('-' en la tabla) = 220. Datos a enero de 2026 (la publicación no indica día). Estadística oficial de la DGFP; no son puestos RPT ni número medio anual. | AJ5: Cifra de personal publicada en fuente primaria; fecha indicada, no inferir vigencia posterior | AK5: https://digital.gob.es/content/dam/portal-mtdfp/funcion-publica/rcp/boletin/2026_01/revision-agosto-2026/EPSAP_Enero_2026%20.pdf | AL5: 13.568 | AM5: 2026 | AN5: Capítulo 1: crédito TOTAL actualizado IGAE, corte 31/08/2026 | AO5: Crédito autorizado, no gasto realizado ni solo salarios | AP5: https://www.igae.pap.hacienda.gob.es/sitios/igae/es-ES/Contabilidad/ContabilidadPublica/CPE/EjecucionPresupuestaria/Documents/ORGANISMOS%2008.%202026.pdf | AQ5: 8.325 | AR5: 2026 | AS5: Hasta 31/08/2026:8 meses, NO año completo | AT5: Capítulo 1: obligaciones reconocidas; incluye costes de personal, no desglose salarial puro | AU5: https://www.igae.pap.hacienda.gob.es/sitios/igae/es-ES/Contabilidad/ContabilidadPublica/CPE/EjecucionPresupuestaria/Documents/ORGANISMOS%2008.%202026.pdf | AV5: Fuente primaria cotejada contra fila y unidad milesEUR; no estimación | AW5: Crédito y gasto de personal individual verificados; plantilla ocupada verificada a enero de 2026 (EPSAP, efectivos); puestos RPT no verificados | BB5: Plan de Actuación Anual 2025 de la AEI (aprobado 26/12/2024) alude a la 'baja cobertura de la RPT' (p.12) y a puestos RPT que 'permanecen vacantes' (p.20), sin cifras legibles; RPT no verificada. | BC5: Revisado: AEI | BD5: Evaluación científica de ayudas/proyectos; no trámite general de consentimiento legislativo en art5. | BE5: No consentimiento favorable para leyes establecido en funciones revisadas. | BF5: No veto legislativo identificado en estas cláusulas; no pretende descartar obligaciones sectoriales en otras normas. | BG5: RD1067/2015 art5 | BH5: https://www.boe.es/eli/es/rd/2015/11/27/1067 | BI5: 8.325 | BJ5: 12.346 | BK5: 7.946 | BN5: IGAE: columnas 2026 crédito / obligaciones / pagos;2025 crédito y obligaciones al mismo 31/08. No comparar 8 meses con año completo. Capítulo 1 no equivale solo a sueldos. PlantillaRPT del lote no incorporada sin verificación adicional. | BO5: 12.789 | BP5: 12.649 | BQ5: 12.649 | BR5: 2025: hasta31/12/2025, año completo | BS5: Capítulo1: gastos de personal; obligaciones reconocidas, no solo salarios | BT5: https://www.igae.pap.hacienda.gob.es/sitios/igae/es-ES/Contabilidad/ContabilidadPublica/CPE/EjecucionPresupuestaria/Documents/ORGANISMOS%2012.%202025.pdf | BU5: Fuente primaria cotejada: IGAE edición12.2025, tabla y unidad milesEUR. No confundir con comparativa2025 de edición08.2026. Crédito comparativo edición08.2026: 12.346M; crédito cierre12.2025: 12.789M. La diferencia no prueba por sí sola origen/cause de transferencia. | BV5: Útil | BW5: Mantener | BX5: Financiación y ayudas | BY5: Organismo estatal de referencia. 8 comunidades tienen el suyo propio; 10 organismos sobre este tema entre el Estado y las CCAA (verificados). | BZ5: No | CA5: Acreditada | CB5: Evalúa por pares y concede las ayudas estatales de investigación. | CC5: Aplicando el criterio del P100: Costes del Estado 9 (función técnica) | CE5: Agencias de investigación e innovación | CF5: 10 | CH5: =IF(AND(ISNUMBER(BP5),ISNUMBER(AG5),AG5>0),BP5*1000000/AG5,"") -> 57495.455
A6: 5 | B6: Estatal | C6: Estado | D6: Rajoy | E6: Autoridad Independiente de Responsabilidad Fiscal (AIReF) | F6: Nueva autoridad | G6: 2013-11-14 | H6: LO 6/2013 | I6: Supervisar estabilidad presupuestaria y sostenibilidad; informes, opiniones y evaluaciones; recomendaciones bajo cumplir o explicar. | J6: Juicio: influencia técnica y control fiscal real, pero no puede vetar presupuestos ni imponer sanciones. Publica Spending Reviews y evaluaciones verificadas. | K6: 12.341 | L6: 2026 | M6: Crédito total actualizado | N6: 31/08/2026 | O6: Cifra propia verificada | P6: 10.579 | Q6: 1.762 | R6: Presupuesto propio, crédito inicial 2026 10,579 M EUR; modificaciones netas +1,762 M; crédito total 12,341 M al 31/08/2026. IGAE p.99, cifras publicadas en miles de euros, no gasto ejecutado ni dotación solo administrativa. | S6: 31/08/2026, salvo indicación distinta | T6: Vigente; estado operativo no exhaustivamente auditado | U6: No se ha verificado el número actual de puestos ocupados ni la independencia práctica de su dirección. | V6: No se ha identificado relación en esta revisión (no certifica ausencia) | X6: Revisión cualitativa del mandato y estado de las 95 fichas; no auditoría exhaustiva de funciones ni proyectos. | Z6: https://www.boe.es/eli/es/lo/2013/11/14/6/con https://www.igae.pap.hacienda.gob.es/sitios/igae/es-ES/Contabilidad/ContabilidadPublica/CPE/EjecucionPresupuestaria/Documents/ORGANISMOS%2008.%202026.pdf https://www.airef.es/es/spending-review/ | AE6: https://files.instinct.com/q91pr53q4umo-entidades-publicas-poder-y-presupuesto | AF6: 12/10/2026 | AI6: Personas realmente ocupadas; no equiparar vocales, puestos RPT o apoyo ministerial con plantilla | AJ6: Pendiente: sin cifra de personal ocupado verificada en el conjunto actual | AL6: 8.493 | AM6: 2026 | AN6: Capítulo 1: crédito TOTAL actualizado IGAE, corte 31/08/2026 | AO6: Crédito autorizado, no gasto realizado ni solo salarios | AP6: https://www.igae.pap.hacienda.gob.es/sitios/igae/es-ES/Contabilidad/ContabilidadPublica/CPE/EjecucionPresupuestaria/Documents/ORGANISMOS%2008.%202026.pdf | AQ6: 5.115 | AR6: 2026 | AS6: Hasta 31/08/2026:8 meses, NO año completo | AT6: Capítulo 1: obligaciones reconocidas; incluye costes de personal, no desglose salarial puro | AU6: https://www.igae.pap.hacienda.gob.es/sitios/igae/es-ES/Contabilidad/ContabilidadPublica/CPE/EjecucionPresupuestaria/Documents/ORGANISMOS%2008.%202026.pdf | AV6: Fuente primaria cotejada contra fila y unidad milesEUR; no estimación | AW6: Crédito y gasto de personal individual verificados; plantilla ocupada y puestos RPT no verificados (fuente propia no legible automáticamente) | BB6: Sin cifra verificada en esta revisión: airef.es bloquea la lectura automática (robots). Documentos oficiales localizados para comprobación manual: Memoria anual de actividades 2025 (https://www.airef.es/wp-content/uploads/2026/03/Memoria/AIReF_Memoria-anual-de-actividades_2025.pdf) y RPT de funcionarios a 03/04/2025 (https://www.airef.es/wp-content/uploads/2025/04/Sobre_nosotros/RPT_funcionarios_03_04_2025.pdf). La EPSAP enero 2026 solo publica el agregado de Autoridades Administrativas Independientes (1.926 efectivos, Tabla 1.5 p.8), sin desglose por entidad. | BC6: Revisado: AIReF, informes presupuestarios y orden metodológica | BD6: Sí: previsiones de proyectos de presupuestos y modificación de orden metodológica; NO todas las leyes. | BE6: Recomendaciones: apartarse exige motivación e incorporar informe (art5.1). Aval de previsiones debe indicarse; no consentimiento para aprobar ley. | BF6: Trámite previo en ámbito específico. Omitirlo puede generar cuestión procedimental, no veto parlamentario automático; efecto exacto requiere analizar procedimiento. | BG6: LO6/2013 arts5.1,14,15 | BH6: https://www.boe.es/eli/es/lo/2013/11/14/6/con | BI6: 5.115 | BJ6: 8.376 | BK6: 4.511 | BN6: IGAE: columnas 2026 crédito / obligaciones / pagos;2025 crédito y obligaciones al mismo 31/08. No comparar 8 meses con año completo. Capítulo 1 no equivale solo a sueldos. PlantillaRPT del lote no incorporada sin verificación adicional. | BO6: 8.376 | BP6: 7.338 | BQ6: 7.338 | BR6: 2025: hasta31/12/2025, año completo | BS6: Capítulo1: gastos de personal; obligaciones reconocidas, no solo salarios | BT6: https://www.igae.pap.hacienda.gob.es/sitios/igae/es-ES/Contabilidad/ContabilidadPublica/CPE/EjecucionPresupuestaria/Documents/ORGANISMOS%2012.%202025.pdf | BU6: Fuente primaria cotejada: IGAE edición12.2025, tabla y unidad milesEUR. No confundir con comparativa2025 de edición08.2026. | BV6: Útil | BW6: Mantener | BX6: Control interno y cumplimiento | BZ6: Sí: la Directiva 2011/85/UE exige un organismo fiscal independiente | CA6: Acreditada | CB6: Evalúa el gasto y los beneficios fiscales: el P100 le encarga revisar todo el gasto y conserva su informe obligatorio. Exigida por la UE. | CC6: Explícito en el P100: Costes del Estado 1, 9 y 12; Organización del Estado 11 | CE6: Supervisión fiscal | CH6: =IF(AND(ISNUMBER(BP6),ISNUMBER(AG6),AG6>0),BP6*1000000/AG6,"")
A7: 6 | B7: Estatal | C7: Estado | D7: Rajoy | E7: Consejo de Transparencia y Buen Gobierno (CTBG) | F7: Nueva entidad | G7: 2013-12-09 | H7: Ley 19/2013, art.33; RD 919/2014 | I7: Resolver reclamaciones de acceso a información y controlar publicidad activa. | J7: Juicio: poder jurídico real al resolver reclamaciones; no tiene una capacidad general de imponer multas. Ejecución y estructura presupuestaria evidencian operación. | K7: 3.37938 | L7: 2026 | M7: Crédito total actualizado | N7: 31/08/2026 | O7: Cifra propia verificada | P7: 3.37938 | Q7: 0 | R7: Presupuesto propio 2026: 3.379.380 EUR exactos (programa 921X). IGAE agosto: 3,380 M EUR redondeados, modificación neta cero. Obligaciones no financieras: 1,671 M EUR (p.102). No confundir con el presupuesto total del ministerio. | S7: 31/08/2026, salvo indicación distinta | T7: Vigente; estatuto reemplazado en 2024. | U7: Modificación neta cero no descarta transferencias compensadas entre partidas. | V7: No se ha identificado relación en esta revisión (no certifica ausencia) | X7: Revisión cualitativa del mandato y estado de las 95 fichas; no auditoría exhaustiva de funciones ni proyectos. | Z7: https://www.boe.es/eli/es/l/2013/12/09/19 https://www.igae.pap.hacienda.gob.es/sitios/igae/es-ES/Contabilidad/ContabilidadPublica/CPE/EjecucionPresupuestaria/Documents/ORGANISMOS%2008.%202026.pdf https://consejodetransparencia.es/content/dam/ctransparencia/portal-ctbg/transparencia/informacion-economica-presupuestaria-y-estadistica/presupuestos-y-ejecuci%C3%B3n/2026/presupuesto-gastos-2026(prorrogado).pdf https://consejodetransparencia.es/content/dam/ctransparencia/portal-ctbg/nosotros/memorias-y-plan-estrategico/memoria-2025/Memoria_2025_CTBG.pdf https://consejodetransparencia.es/content/dam/ctransparencia/portal-ctbg/transparencia/informacion-institucional-organizativa-y-de-planificacion/RPT_30-06-2026.pdf https://consejodetransparencia.es/ct_Home/transparencia/portal-transparencia/informacion-institucional/mas-transparencia/documentos-personal.html | AE7: https://files.instinct.com/q91pr53q4umo-entidades-publicas-poder-y-presupuesto | AF7: 12/10/2026 | AG7: 31 | AH7: 2025-12-31 | AI7: 31 efectivos a 31/12/2025, incluido el Presidente; los otros 30 son funcionarios de carrera (por disposición estatutaria); sin personal laboral ni eventual. Memoria CTBG 2025, ap. 1.3.2, p.19, Tabla 1 'Efectivos del CTBG a 31 de diciembre de 2025'. | AJ7: Cifra de personal publicada en fuente primaria; fecha indicada, no inferir vigencia posterior | AK7: https://consejodetransparencia.es/content/dam/ctransparencia/portal-ctbg/nosotros/memorias-y-plan-estrategico/memoria-2025/Memoria_2025_CTBG.pdf | AL7: 2.464 | AM7: 2026 | AN7: Capítulo 1: crédito TOTAL actualizado IGAE, corte 31/08/2026 | AO7: Crédito autorizado, no gasto realizado ni solo salarios | AP7: https://www.igae.pap.hacienda.gob.es/sitios/igae/es-ES/Contabilidad/ContabilidadPublica/CPE/EjecucionPresupuestaria/Documents/ORGANISMOS%2008.%202026.pdf | AQ7: 1.398 | AR7: 2026 | AS7: Hasta 31/08/2026:8 meses, NO año completo | AT7: Capítulo 1: obligaciones reconocidas; incluye costes de personal, no desglose salarial puro | AU7: https://www.igae.pap.hacienda.gob.es/sitios/igae/es-ES/Contabilidad/ContabilidadPublica/CPE/EjecucionPresupuestaria/Documents/ORGANISMOS%2008.%202026.pdf | AV7: Fuente primaria cotejada contra fila y unidad milesEUR; no estimación | AW7: Crédito y gasto de personal individual verificados; plantilla ocupada verificada a 31/12/2025 (Memoria CTBG) y puestos RPT a 30/06/2026 (fechas distintas, sin cobertura calculada) | AX7: 39 | AY7: 2026-06-30 | AZ7: Puestos de la RPT del CTBG (personal funcionario), 'Total Puestos: 39', fecha de vigencia 30-06-2026; el documento no indica ocupación ni vacantes. | BA7: https://consejodetransparencia.es/content/dam/ctransparencia/portal-ctbg/transparencia/informacion-institucional-organizativa-y-de-planificacion/RPT_30-06-2026.pdf | BB7: Ocupados (31 a 31/12/2025, Memoria; incluye al Presidente, alto cargo fuera de RPT) y RPT (39 puestos a 30/06/2026) son de fechas y fuentes distintas: no se calcula cobertura. Portal de transparencia CTBG: 'Toda la plantilla ... está formada por funcionarios/as de carrera' y no hay personal eventual. Memoria 2025: cap. 1 presupuestado 2.463,70 miles EUR; obligaciones 2.201.447,49 EUR (89,36%), coherente con IGAE (2,201 M). | BC7: Informe obligatorio sobre determinados proyectos normativos estatales | BD7: Sí: proyectos normativos estatales que desarrollen Ley 19/2013 o estén relacionados con su objeto | BE7: El art 38.1(c) exige informe, no dictamen favorable ni consentimiento; no declara vinculación | BF7: Puede exigir el trámite de informe en su ámbito. No se atribuye veto a la aprobación parlamentaria; efecto de omisión o demora requiere revisar expediente y procedimiento concreto. | BG7: Ley 19/2013 art 38.1(c) | BH7: https://www.boe.es/eli/es/l/2013/12/09/19 | BI7: 1.398 | BJ7: 2.464 | BK7: 1.409 | BN7: IGAE: columnas 2026 crédito / obligaciones / pagos;2025 crédito y obligaciones al mismo 31/08. No comparar 8 meses con año completo. Capítulo 1 no equivale solo a sueldos. PlantillaRPT del lote no incorporada sin verificación adicional. | BO7: 2.464 | BP7: 2.201 | BQ7: 2.201 | BR7: 2025: hasta31/12/2025, año completo | BS7: Capítulo1: gastos de personal; obligaciones reconocidas, no solo salarios | BT7: https://www.igae.pap.hacienda.gob.es/sitios/igae/es-ES/Contabilidad/ContabilidadPublica/CPE/EjecucionPresupuestaria/Documents/ORGANISMOS%2012.%202025.pdf | BU7: Fuente primaria cotejada: IGAE edición12.2025, tabla y unidad milesEUR. No confundir con comparativa2025 de edición08.2026. | BV7: Útil | BW7: Reformar | BX7: Control interno y cumplimiento | BY7: Organismo estatal de referencia. 12 comunidades tienen el suyo propio; 13 organismos sobre este tema entre el Estado y las CCAA (verificados). | BZ7: No | CA7: Acreditada | CB7: Resuelve las reclamaciones de acceso a la información; el P100 lo mantiene pero lo saca del alcance del Gobierno (terna por mérito, mandato único). Absorbería a los consejos autonómicos. | CC7: Explícito en el P100: Organización del Estado 11 | CE7: Consejos de transparencia | CF7: 13 | CH7: =IF(AND(ISNUMBER(BP7),ISNUMBER(AG7),AG7>0),BP7*1000000/AG7,"") -> 71000 | CI7: 17 | CJ7: 13 | CK7: 1 | CL7: 31 | CM7: 10 | CN7: 1 | CO7: 0 | CP7: Personas (efectivos) a 31/12/2025 (Memoria CTBG 2025, Tabla 1). Libre designación: puestos de la RPT de funcionarios vigente a 30/06/2026 (39 puestos), otra fuente y fecha. | CQ7: Proxy por subgrupo, no por función. A1 (11) + A2 (6) van al núcleo técnico; C1 (12) + C2 (1) van a administración y apoyo; el Presidente (alto cargo, sin grupo) va a 'otro'. Parte de los A1 hacen gestión (Secretario/a General, Director/a de Gabinete) y parte de los C1 hacen tareas técnicas (3 Analistas de Sistemas, 4 Jefes/as de Sección de nivel 22). | CR7: https://consejodetransparencia.es/content/dam/ctransparencia/portal-ctbg/nosotros/memorias-y-plan-estrategico/memoria-2025/Memoria_2025_CTBG.pdf | CS7: Memoria CTBG 2025, ap. 1.3.2, p.19, Tabla 1 'Efectivos del CTBG a 31 de diciembre de 2025'. Presidente: 1 (sin grupo). A1: Subdirector/a General 3 + Secretario/a General 1 + Director/a de Gabinete 1 + Puesto de trabajo N30 1 + Subdirector/a Adjunto/a 2 + Jefe/a de Área 2 + Consejero/a Técnico/a 1 = 11. A2: Jefe/a de Servicio N26 5 + Jefe/a de Sección N20 1 = 6. C1: Jefe/a de Sección N22 4 + Analista de Sistemas 3 + Secretario/a N18 2 + Secretario/a de Subdirector General 1 + Jefe/a de Negociado 2 = 12. C2: Secretario/a de Subdirector General 1. Total de efectivos: 31. Texto: 'todos ellos funcionarios de carrera por expresa disposición estatutaria, con excepción del Presidente'. Libre designación: RPT_30-06-2026.pdf (https://consejodetransparencia.es/content/dam/ctransparencia/portal-ctbg/transparencia/informacion-institucional-organizativa-y-de-planificacion/RPT_30-06-2026.pdf), 'Total Puestos: 39'; leyenda: L = 'LIBRE DESIGNACION', C = 'CONCURSO DE MERITOS'. Hay 10 L y 27 C. En la p.1 se leen 12 letras (L L C L L C L C C C C C, 5 L) para 14 puestos. En la p.2 hay 4 L (Subdirector/a General x2 y Subdirector/a Adjunto/a x2) y en la p.3 hay 1 L (Subdirector/a General). Dos puestos de la p.1 no tienen tipo de provisión legible en la lectura automática (probablemente los dos 'Puesto de trabajo' de nivel 30): si ambos fueran LD, el total sería 12. Altos cargos: el Presidente, con fila propia en la Tabla 1 y la partida 'Retribuciones altos cargos' en la Tabla 2 (ap. 1.3.3). Personal eventual: portal de transparencia del CTBG, 'Documentos de personal': 'No hay personal eventual ni hay ni habrá indemnizaciones por cese.' Contexto de la RPT, sin mezclar con lo anterior (39 puestos a 30/06/2026): A1 14, A1/A2 5, A2 2, A2/C1 7, C1/C2 6, C1 5.
A8: 7 | B8: Estatal | C8: Estado | D8: Rajoy | E8: Agencia Estatal de Seguridad Ferroviaria (AESF) | F8: Nueva agencia que integra funciones ministeriales | G8: 2014-12-19 | H8: RD 1072/2014 | I8: Autoridad nacional de seguridad ferroviaria: supervisión, certificados y autorizaciones de seguridad. | J8: Juicio: poder ejecutivo real, aunque no es una autoridad judicial ni un simple observatorio. | K8: 17.523 | L8: 2026 | M8: Crédito total actualizado | N8: 31/08/2026 | O8: Cifra propia verificada | P8: 16.463 | Q8: 1.06 | R8: Presupuesto propio, crédito inicial 2026 16,463 M EUR; modificaciones netas +1,060 M; crédito total 17,523 M al 31/08/2026. IGAE p.99, cifras publicadas en miles de euros, no gasto ejecutado ni dotación solo administrativa. | S8: 31/08/2026, salvo indicación distinta | T8: Vigente; estado operativo no exhaustivamente auditado | U8: Plantilla ocupada: ver columna de personal (EPSAP enero 2026 o fuente indicada); no se ha verificado la independencia práctica de su dirección. | V8: No se ha identificado relación en esta revisión (no certifica ausencia) | X8: Revisión cualitativa del mandato y estado de las 95 fichas; no auditoría exhaustiva de funciones ni proyectos. | Z8: https://www.boe.es/eli/es/rd/2014/12/19/1072 https://www.igae.pap.hacienda.gob.es/sitios/igae/es-ES/Contabilidad/ContabilidadPublica/CPE/EjecucionPresupuestaria/Documents/ORGANISMOS%2008.%202026.pdf https://digital.gob.es/content/dam/portal-mtdfp/funcion-publica/rcp/boletin/2026_01/revision-agosto-2026/EPSAP_Enero_2026%20.pdf https://digital.gob.es/content/dam/portal-mtdfp/funcion-publica/rcp/notaepsap/Noticia_EPSAP_Enero_26.pdf | AE8: https://files.instinct.com/q91pr53q4umo-entidades-publicas-poder-y-presupuesto | AF8: 12/10/2026 | AG8: 126 | AH8: 2026-01 | AI8: Efectivos (personas) según Estadística del Personal al Servicio de las AA.PP. (EPSAP) enero 2026, Tabla 4.1 p.37: 115 funcionarios de carrera + 11 personal laboral + 0 otro personal ('-' en la tabla) = 126. Datos a enero de 2026 (la publicación no indica día). Estadística oficial de la DGFP; no son puestos RPT ni número medio anual. | AJ8: Cifra de personal publicada en fuente primaria; fecha indicada, no inferir vigencia posterior | AK8: https://digital.gob.es/content/dam/portal-mtdfp/funcion-publica/rcp/boletin/2026_01/revision-agosto-2026/EPSAP_Enero_2026%20.pdf | AL8: 7.972 | AM8: 2026 | AN8: Capítulo 1: crédito TOTAL actualizado IGAE, corte 31/08/2026 | AO8: Crédito autorizado, no gasto realizado ni solo salarios | AP8: https://www.igae.pap.hacienda.gob.es/sitios/igae/es-ES/Contabilidad/ContabilidadPublica/CPE/EjecucionPresupuestaria/Documents/ORGANISMOS%2008.%202026.pdf | AQ8: 4.836 | AR8: 2026 | AS8: Hasta 31/08/2026:8 meses, NO año completo | AT8: Capítulo 1: obligaciones reconocidas; incluye costes de personal, no desglose salarial puro | AU8: https://www.igae.pap.hacienda.gob.es/sitios/igae/es-ES/Contabilidad/ContabilidadPublica/CPE/EjecucionPresupuestaria/Documents/ORGANISMOS%2008.%202026.pdf | AV8: Fuente primaria cotejada contra fila y unidad milesEUR; no estimación | AW8: Crédito y gasto de personal individual verificados; plantilla ocupada verificada a enero de 2026 (EPSAP, efectivos); puestos RPT no verificados | BC8: Revisado: AESF participación normativa | BD8: Proponer/elaborar marco normativo seguridad e interoperabilidad; no literal informepreceptivo general en art9h. | BE8: No se exige consentimiento favorable ni carácter vinculante del informe en la cláusula citada; no es veto. | BF8: Preparación normativa y autorizaciones técnicas distintas de consentimiento para aprobar leyes. | BG8: RD1072/2014 art9.1h y9.2 | BH8: https://www.boe.es/eli/es/rd/2014/12/19/1072/con | BI8: 4.836 | BJ8: 6.896 | BK8: 4.24 | BN8: IGAE: columnas 2026 crédito / obligaciones / pagos;2025 crédito y obligaciones al mismo 31/08. No comparar 8 meses con año completo. Capítulo 1 no equivale solo a sueldos. PlantillaRPT del lote no incorporada sin verificación adicional. AESF: cifra previa del lote 6,896050M etiquetada 2022 no validada; IGAE2025 muestra 6,896M. No corregir año por parecido de importes. | BO8: 6.896 | BP8: 6.746 | BQ8: 6.746 | BR8: 2025: hasta31/12/2025, año completo | BS8: Capítulo1: gastos de personal; obligaciones reconocidas, no solo salarios | BT8: https://www.igae.pap.hacienda.gob.es/sitios/igae/es-ES/Contabilidad/ContabilidadPublica/CPE/EjecucionPresupuestaria/Documents/ORGANISMOS%2012.%202025.pdf | BU8: Fuente primaria cotejada: IGAE edición12.2025, tabla y unidad milesEUR. No confundir con comparativa2025 de edición08.2026. | BV8: Útil | BW8: Mantener | BX8: Regulación o inspección de terceros | BY8: Organismo estatal de referencia. 1 comunidades tienen el suyo propio; 2 organismos sobre este tema entre el Estado y las CCAA (verificados). | BZ8: Sí: la Directiva (UE) 2016/798 exige una autoridad nacional de seguridad ferroviaria | CA8: Acreditada | CB8: Certifica e inspecciona la seguridad de la red ferroviaria estatal. | CC8: Aplicando el criterio del P100: Costes del Estado 9 (función técnica; exigida por la UE) | CE8: Seguridad ferroviaria | CF8: 2 | CH8: =IF(AND(ISNUMBER(BP8),ISNUMBER(AG8),AG8>0),BP8*1000000/AG8,"") -> 53539.683
A9: 8 | B9: Estatal | C9: Estado | D9: Zapatero | E9: Observatorio Estatal de la Convivencia Escolar | F9: Órgano colegiado nuevo sin personalidad propia | G9: 2007-02-23 | H9: RD 275/2007 | I9: Recoger información, estudiar convivencia escolar, asesorar y recomendar políticas educativas. | J9: Juicio: poder consultivo, sin sanción, veto ni mando sobre centros. Función verificable; el ministerio mantiene página institucional y nombró vocales en 2025. | O9: Sin presupuesto propio: órgano sin dotación diferenciada (verificado en norma) | R9: Sin presupuesto propio (verificado en norma). Real Decreto 3/2018, de 12 de enero (BOE-A-2018-432, BOE 13/01/2018), disposición adicional segunda «Gastos de funcionamiento»: «El Ministerio de Educación, Cultura y Deporte atenderá con cargo a su presupuesto ordinario los gastos de funcionamiento personales y materiales de este órgano colegiado» y «La dotación de personal al Observatorio se realizará a través de la correspondiente redistribución de efectivos del Ministerio, sin que ello pueda suponer incremento de puestos ni de retribuciones». La secretaría corresponde a la persona titular de la SG del Centro Nacional de Innovación e Investigación Educativa (art. 3.1.d del RD 275/2007, en la redacción del RD 3/2018). El coste lo absorbe el presupuesto ordinario del ministerio competente en educación (hoy Educación, FP y Deportes). No se prorratea y tampoco equivale a cero EUR. No se ha identificado ningún convenio, encargo, contrato ni subvención a su nombre. La norma no regula retribuciones ni indemnizaciones de los vocales. | S9: 31/08/2026, salvo indicación distinta | T9: Vigente; modificado en 2018. | U9: La ausencia de línea propia no prueba inactividad; falta verificar todas las reuniones y resultados 2026. | V9: Mandato paralelo en distinto nivel territorial | W9: 85, 88 | X9: Convivencia escolar: órgano estatal y dos autonómicos. Diferentes jurisdicciones; no prueba de gasto duplicado. Ficha 85 reubicada desde 2014. | Y9: https://www.boe.es/eli/es/rd/2007/02/23/275 https://www.educacionfpydeportes.gob.es/mc/sgctie/convivencia-escolar/observatorio.html https://boe.es/boe/dias/2025/11/15/pdfs/BOE-A-2025-23138.pdf https://www.educa.jcyl.es/convivenciaescolar/es/observatorio-convivencia-escolar/antecedentes-observatorio-convivencia-escolar-castilla-leon https://recursos.educarex.es/pdf/normativa-sg/Decreto_28-2007.pdf | Z9: https://www.boe.es/eli/es/rd/2007/02/23/275 https://www.educacionfpydeportes.gob.es/mc/sgctie/convivencia-escolar/observatorio.html https://boe.es/boe/dias/2025/11/15/pdfs/BOE-A-2025-23138.pdf https://www.boe.es/eli/es/rd/2007/02/23/275/con https://www.boe.es/boe/dias/2018/01/13/pdfs/BOE-A-2018-432.pdf | AE9: https://files.instinct.com/q91pr53q4umo-entidades-publicas-poder-y-presupuesto | AF9: 12/10/2026 | AI9: Personas realmente ocupadas; no equiparar vocales, puestos RPT o apoyo ministerial con plantilla | AJ9: Sin plantilla propia (verificado en norma: RD 3/2018, DA 2.ª, redistribución de efectivos del Ministerio). No se publica el n.º de efectivos de apoyo; los vocales no son plantilla | AO9: Sin crédito de personal propio: el coste lo absorbe el presupuesto ordinario del Ministerio de Educación (unidad de apoyo: SG del CNIIE según RD 3/2018); no se prorratea | AV9: Sin ejecución de personal propia: el gasto está incluido en la unidad ministerial de apoyo; no se prorratea | AW9: No tiene presupuesto, plantilla ni capítulo 1 propios (RD 3/2018, DA 2.ª, verificado). El gasto va a cargo del presupuesto ordinario del Ministerio, sin prorrateo. No se ha identificado importe contextual | BB9: Órgano colegiado sin plantilla propia. RD 3/2018, DA 2.ª: el personal procede de la redistribución de efectivos del Ministerio, sin incremento de puestos ni de retribuciones. Secretaría: titular de la SG del CNIIE (art. 3.1.d RD 275/2007, redacción 2018). Los vocales, nombrados por ejemplo en 2025, no son plantilla. No se ha publicado el número de efectivos de apoyo. No repartir el gasto total del ministerio. | BC9: Funciones consultivas revisadas: Estudios, asesoramiento e informes sobre convivencia escolar | BD9: No trámite obligatorio general de aprobación de leyes identificado en las funciones revisadas | BE9: No consentimiento favorable obligatorio o vinculación identificado en dichas funciones | BF9: No veto legal a aprobación de leyes atribuido por las funciones revisadas. Alcance limitado a norma revisada, no certificación de ausencia de cualquier norma sectorial posterior. | BG9: RD 275/2007 arts 1.2,2 | BH9: https://www.boe.es/eli/es/rd/2007/02/23/275 | BV9: No útil | BW9: Suprimir | BX9: Consultivo o participación | BY9: Organismo estatal de referencia. 14 comunidades tienen el suyo propio; 15 organismos sobre este tema entre el Estado y las CCAA (verificados). | BZ9: No | CA9: Parcial | CB9: Observatorio, consejo o comisión: el P100 los cierra salvo que su ministerio demuestre que su trabajo cambia decisiones o mejora un servicio; publicar informes no cuenta. | CC9: Explícito en el P100: Costes del Estado 2 | CD9: Estructura ordinaria del ministerio, si alguna función resultara imprescindible | CE9: Observatorios de convivencia escolar | CF9: 15 | CG9: Apoyo: Secretaría: titular de la SG del Centro Nacional de Innovación e Investigación Educativa (art. 3.1.d RD 275/2007, redacción RD 3/2018); personal por redistribución de efectivos del Ministerio de Educación. vocales: 27. | CH9: =IF(AND(ISNUMBER(BP9),ISNUMBER(AG9),AG9>0),BP9*1000000/AG9,"")
A10: 9 | B10: Estatal | C10: Estado | D10: Zapatero | E10: Observatorio de la Vida Militar | F10: Órgano nuevo; constitución efectiva 14/01/2014 bajo Rajoy | G10: 2011-07-27 | H10: LO 9/2011 | I10: Analizar vida militar, derechos y condiciones de los miembros de Fuerzas Armadas; presentar memorias a las Cortes. | J10: Juicio: supervisión y asesoramiento real, no poder de mando militar ni sanción. Adscripción parlamentaria y memorias previstas por ley. | O10: Sin presupuesto propio: órgano sin dotación diferenciada (verificado en norma) | R10: Sin presupuesto propio (verificado en norma). LO 9/2011, art. 53.1: es un «órgano colegiado, de carácter asesor y consultivo, adscrito a las Cortes Generales». Art. 53.2: el Ministerio de Defensa «proporcionará la sede y el apoyo administrativo necesario para el funcionamiento del Observatorio», que «contará con un órgano de trabajo permanente». Art. 55.1: «La pertenencia al Observatorio no será retribuida». El art. 56.2 remite a un reglamento el estatuto de los miembros y la composición del órgano de trabajo; su presidente lo presentaba aún como reto pendiente en la Revista Española de Defensa (mayo de 2024). El coste de sede y apoyo administrativo lo absorbe el Ministerio de Defensa. No se prorratea y tampoco equivale a cero. Una búsqueda general no ha identificado ninguna partida, convenio ni contrato a su nombre. Actividad acreditada: el 26/06/2025 la Comisión de Defensa del Congreso debatió el dictamen sobre su Memoria-Informe 2023 (DSCD-15-CO-376). | S10: 31/08/2026, salvo indicación distinta | T10: Creado 2011, constituido 2014. | U10: Distinguir creación legal de puesta en funcionamiento; no se ha cuantificado personal propio. | V10: No se ha identificado relación en esta revisión (no certifica ausencia) | X10: Revisión cualitativa del mandato y estado de las 95 fichas; no auditoría exhaustiva de funciones ni proyectos. | Z10: https://www.boe.es/diario_boe/txt.php?id=BOE-A-2011-12961 https://www.defensa.gob.es/gabinete/notasPrensa/2014/01/DGC-140114-constitucion-observatorio-01.html https://www.boe.es/eli/es/lo/2011/07/27/9/con https://boe.es/boe/dias/2011/07/28/pdfs/BOE-A-2011-12961.pdf https://www.boe.es/eli/es/lo/2011/07/27/9 https://www.congreso.es/public_oficiales/L15/CONG/DS/CO/DSCD-15-CO-376.PDF https://working.mde.es/Galerias/gabinete/red/2024/05/p-30-31-red-416-observatorio.pdf | AE10: https://files.instinct.com/q91pr53q4umo-entidades-publicas-poder-y-presupuesto | AF10: 12/10/2026 | AI10: Personas realmente ocupadas; no equiparar vocales, puestos RPT o apoyo ministerial con plantilla | AJ10: Sin plantilla propia (verificado en norma: arts. 53.2 y 55.1 LO 9/2011). Órgano de trabajo permanente sin composición reglamentada ni efectivos publicados; los miembros no son plantilla | AO10: Sin crédito de personal propio: el coste del apoyo administrativo y la sede lo absorbe el Ministerio de Defensa (art. 53.2 LO 9/2011); no se prorratea | AV10: Sin ejecución de personal propia: el gasto está incluido en el Ministerio de Defensa; no se prorratea | AW10: No tiene presupuesto, plantilla ni capítulo 1 propios (LO 9/2011, arts. 53.2 y 55.1, verificado). Defensa aporta la sede y el apoyo administrativo, sin prorrateo. No se ha identificado importe contextual | BB10: Sin plantilla propia publicada. Los 9 miembros (5 elegidos por el Congreso y 4 por el Senado) no son plantilla y su pertenencia no es retribuida (art. 55.1 LO 9/2011). Sede y apoyo administrativo: Ministerio de Defensa (art. 53.2). La ley prevé un «órgano de trabajo permanente», pero su composición depende de un reglamento que, según el presidente del Observatorio (RED, mayo de 2024), seguía pendiente. No repartir el gasto de Defensa. | BC10: Asesoramiento, análisis e informes sobre vida militar; memoria a Cortes | BD10: No informe preceptivo general sobre aprobación de leyes identificado en las funciones revisadas | BE10: No consentimiento favorable o vinculación normativa establecido en funciones revisadas | BF10: No poder de veto legislativo atribuido en funciones revisadas. Proponer cambios, informar a Cortes o participar no equivale a aprobar leyes; no certifica ausencia de reglas sectoriales posteriores. | BG10: LO9/2011 arts 53,54 | BH10: https://www.boe.es/diario_boe/txt.php?id=BOE-A-2011-12961 | BV10: No útil | BW10: Suprimir | BX10: Consultivo o participación | BZ10: No | CA10: Acreditada | CB10: Observatorio, consejo o comisión: el P100 los cierra salvo que su ministerio demuestre que su trabajo cambia decisiones o mejora un servicio; publicar informes no cuenta. | CC10: Explícito en el P100: Costes del Estado 2 | CD10: Estructura ordinaria del ministerio, si alguna función resultara imprescindible | CE10: Vida militar | CG10: Apoyo: Ministerio de Defensa: sede, apoyo administrativo y «órgano de trabajo permanente» (art. 53.2 LO 9/2011). puestos asignados según fuente oficial: 7. vocales: 9. miembros: no retribuidos (art. 55.1 LO 9/2011: «La pertenencia al Observatorio no será retribuida»). gasto con nombre propio: 2014: 5.212 EUR abonados por la Subsecretaría de Defensa (RED n.º 319, 2015, https://working.mde.es/Galerias/gabinete/red/2015/red-319-observatorio-vida-militar.pdf) | 2015: autorización de gasto de 55.000 EUR para dietas en la Sección 14-Defensa (Ley 36/2014 de PGE) y presupuesto 2016 del OVM de 55.979,10 EUR sin partida en la Ley 48/2015 (Memoria-Informe 2015 del OVM, https://www.prevencionintegral.com/sites/default/files/noticia/36030/field_adjuntos/pdft076-16observatoriovidamilitar20151.pdf). | CH10: =IF(AND(ISNUMBER(BP10),ISNUMBER(AG10),AG10>0),BP10*1000000/AG10,"")
A11: 10 | B11: Estatal | C11: Estado | D11: Zapatero | E11: Observatorio Universitario de Becas, Ayudas al Estudio y Rendimiento Académico | F11: Órgano colegiado nuevo | G11: 2010-10-01 | H11: RD 1220/2010 | I11: Estudiar impacto de becas en equidad y rendimiento, informar y proponer mejoras. | J11: Juicio: consultivo, sin facultad de otorgar becas ni obligar al Gobierno. La norma prueba función, no actividad actual. | O11: Sin presupuesto propio: órgano sin dotación diferenciada (verificado en norma) | R11: Sin presupuesto propio (verificado en norma). RD 1220/2010, disposición adicional única «Gastos de funcionamiento»: «El Ministerio de Educación atenderá, con cargo a su presupuesto ordinario, los gastos de funcionamiento, personales y materiales de este órgano». La dotación de personal de la Unidad Técnica y de la Secretaría Permanente «será realizada desde la Subdirección General de Análisis, Estudios y Prospectiva Universitaria», y «No se solicitará para su funcionamiento ni incremento de puestos de trabajo ni de retribuciones». El art. 7.2 añade que la unidad técnica está integrada por personal de esa SG. El coste lo absorbe el departamento competente en universidades y no se prorratea. El importe de las becas NO es su presupuesto. Actividad: el ministerio informó el 19/12/2018 de que «Por primera vez en siete años» se reunía el Observatorio. No se ha encontrado evidencia oficial de reuniones posteriores, lo que no prueba inactividad. | S11: 31/08/2026, salvo indicación distinta | T11: Norma consultada; actividad 2026 no verificada. | U11: No hay evidencia suficiente para denominarlo vacío o para afirmar que sigue reunido en 2026. | V11: No se ha identificado relación en esta revisión (no certifica ausencia) | X11: Revisión cualitativa del mandato y estado de las 95 fichas; no auditoría exhaustiva de funciones ni proyectos. | Z11: https://www.boe.es/buscar/act.php?id=BOE-A-2010-15786 https://www.ull.es/portal/normativa/normativa/real-decreto-1220-2010-de-1-de-octubre-por-el-que-se-crea-el-observatorio-universitario-de-becas-ayudas-al-estudio-y-rendimiento-academico/ https://www.boe.es/eli/es/rd/2010/10/01/1220/con https://www.ciencia.gob.es/Noticias/2018/Diciembre/El-Observatorio-de-Becas-se-reune-para-abordar-la-reforma-del-sistema.html | AE11: https://files.instinct.com/q91pr53q4umo-entidades-publicas-poder-y-presupuesto | AF11: 12/10/2026 | AI11: Personas realmente ocupadas; no equiparar vocales, puestos RPT o apoyo ministerial con plantilla | AJ11: Sin plantilla propia (verificado en norma: DA única y art. 7.2 del RD 1220/2010, personal de la SG de Análisis, Estudios y Prospectiva Universitaria). No se publica el n.º de efectivos | AO11: Sin crédito de personal propio: el coste lo absorbe la SG de Análisis, Estudios y Prospectiva Universitaria / el presupuesto ordinario del departamento de universidades; no se prorratea | AV11: Sin ejecución de personal propia: el gasto está incluido en la SG de apoyo; no se prorratea | AW11: No tiene presupuesto, plantilla ni capítulo 1 propios (RD 1220/2010, DA única, verificado), sin prorrateo. Sin importe contextual. Última reunión acreditada: 19/12/2018 | BB11: Sin plantilla propia. Unidad Técnica y Secretaría Permanente atendidas con personal de la SG de Análisis, Estudios y Prospectiva Universitaria (art. 7.2 y DA única del RD 1220/2010), sin incremento de puestos ni de retribuciones. Los vocales no son plantilla. No se ha publicado el n.º de efectivos de apoyo. No repartir el gasto ministerial. | BC11: Estadísticas e informes sobre becas; ayuda técnica a decisiones de Congreso/Senado, no autorización de leyes | BD11: No informe obligatorio general de aprobación de leyes identificado en funciones revisadas | BE11: No consentimiento favorable obligatorio establecido en funciones revisadas | BF11: Sin veto normativo atribuido por las funciones revisadas; informar a las Cortes o asesorar no equivale a aprobar una ley. Alcance limitado a disposición revisada, no auditoría de todas las normas sectoriales posteriores. | BG11: RD 1220/2010 arts.1.3,2 | BH11: https://www.boe.es/buscar/act.php?id=BOE-A-2010-15786 | BV11: No útil | BW11: Suprimir | BX11: Consultivo o participación | BZ11: No | CA11: No acreditada | CB11: Observatorio, consejo o comisión: el P100 los cierra salvo que su ministerio demuestre que su trabajo cambia decisiones o mejora un servicio; publicar informes no cuenta. | CC11: Explícito en el P100: Costes del Estado 2 | CD11: Estructura ordinaria del ministerio, si alguna función resultara imprescindible | CE11: Becas universitarias | CG11: Apoyo: Unidad Técnica y Secretaría Permanente atendidas por personal de la SG de Análisis, Estudios y Prospectiva Universitaria (art. 7.2 y DA única RD 1220/2010). vocales: 18. | CH11: =IF(AND(ISNUMBER(BP11),ISNUMBER(AG11),AG11>0),BP11*1000000/AG11,"")
A12: 11 | B12: Estatal | C12: Estado | D12: Zapatero | E12: Observatorio del Empleo Público | F12: Órgano nuevo | G12: 2010-07-02 | H12: RD 868/2010 | I12: Estudiar empleo público y recursos humanos; información y propuestas. | J12: Juicio: técnico/consultivo; no gestiona plantillas ni decide ofertas públicas. Actividad reciente no acreditada. | O12: Sin presupuesto propio: órgano sin dotación diferenciada (verificado en norma) | R12: Sin presupuesto propio (verificado en norma). RD 868/2010, disposición adicional segunda «Gastos de funcionamiento». Ap. 1: la Secretaría de Estado para la Función Pública, a través de la Dirección General de la Función Pública, «prestará al Secretariado los medios técnicos, personales y materiales que sean necesarios para el funcionamiento del Observatorio del Empleo Público». Ap. 2: «En ningún caso el funcionamiento del Observatorio del Empleo Público implicará directa o indirectamente incremento de gasto público». Secretariado: la persona titular de una SG de la DG de la Función Pública (art. 4.1.e). El coste lo absorbe la DG de la Función Pública y no se prorratea. No se ha identificado importe contextual. Las fuentes oficiales localizadas no acreditan actividad reciente, y la página del BOE no muestra derogación. | S12: 31/08/2026, salvo indicación distinta | T12: Creación acreditada; continuidad operativa no verificada. | U12: Sin auditoría de reuniones, dotación y productos actuales, no cabe llamarlo entidad vacía. | V12: No se ha identificado relación en esta revisión (no certifica ausencia) | X12: Revisión cualitativa del mandato y estado de las 95 fichas; no auditoría exhaustiva de funciones ni proyectos. | Z12: https://www.boe.es/eli/es/rd/2010/07/02/868 https://www.lamoncloa.gob.es/consejodeministros/referencias/paginas/2010/02072010referenciaconsejoministros.aspx | AE12: https://files.instinct.com/q91pr53q4umo-entidades-publicas-poder-y-presupuesto | AF12: 12/10/2026 | AI12: Personas realmente ocupadas; no equiparar vocales, puestos RPT o apoyo ministerial con plantilla | AJ12: Sin plantilla propia (verificado en norma: RD 868/2010, DA 2.ª, medios de la DG de la Función Pública). No se publica el n.º de efectivos de apoyo; los vocales no son plantilla | AO12: Sin crédito de personal propio: el coste lo absorbe la DG de la Función Pública (SE de Función Pública); no se prorratea | AV12: Sin ejecución de personal propia: el gasto está incluido en la DG de la Función Pública; no se prorratea | AW12: No tiene presupuesto, plantilla ni capítulo 1 propios (RD 868/2010, DA 2.ª, verificado), sin prorrateo. Sin importe contextual; actividad reciente no acreditada | BB12: Sin plantilla propia. Medios técnicos, personales y materiales a cargo de la SE de Función Pública a través de la DG de la Función Pública (RD 868/2010, DA 2.ª.1). Secretario: titular de una SG de esa DG (art. 4.1.e). Los vocales no son plantilla. No repartir el gasto ministerial. | BC12: Estudios, propuestas e informe anual sobre empleo público; no autorización de leyes | BD12: No informe obligatorio general de aprobación de leyes identificado en funciones revisadas | BE12: No consentimiento favorable obligatorio establecido en funciones revisadas | BF12: Sin veto normativo atribuido por las funciones revisadas; informar a las Cortes o asesorar no equivale a aprobar una ley. Alcance limitado a disposición revisada, no auditoría de todas las normas sectoriales posteriores. | BG12: RD 868/2010 art.3 | BH12: https://www.boe.es/eli/es/rd/2010/07/02/868 | BV12: No útil | BW12: Suprimir | BX12: Consultivo o participación | BZ12: No | CA12: No acreditada | CB12: Observatorio, consejo o comisión: el P100 los cierra salvo que su ministerio demuestre que su trabajo cambia decisiones o mejora un servicio; publicar informes no cuenta. | CC12: Explícito en el P100: Costes del Estado 2 | CD12: Estructura ordinaria del ministerio, si alguna función resultara imprescindible | CE12: Empleo público | CG12: Apoyo: Secretariado: titular de una SG de la DG de la Función Pública (art. 4.1.e); medios técnicos, personales y materiales de la SE de Función Pública a través de la DG de la Función Pública (DA 2.ª.1 RD 868/2010). vocales: 21. | CH12: =IF(AND(ISNUMBER(BP12),ISNUMBER(AG12),AG12>0),BP12*1000000/AG12,"")
A13: 12 | B13: Estatal | C13: Estado | D13: Zapatero | E13: Observatorio de la Internacionalización | F13: Órgano nuevo | G13: 2009-03-27 | H13: RD 430/2009 | I13: Analizar comercio y desarrollo empresarial internacional; informe anual al Congreso. | J13: Juicio: consultivo/técnico, no poder de concesión ni regulación. El informe anual es una obligación legal, no prueba de que se haya cumplido hoy. | O13: Sin presupuesto propio: órgano sin dotación diferenciada (verificado en norma) | R13: Sin presupuesto propio (verificado en norma). RD 430/2009, disposición adicional única: «La Secretaría de Estado de Comercio prestará los medios técnicos, personales y materiales que sean necesarios para el cumplimiento de la adecuada celebración de las reuniones y sesiones de trabajo» y «El funcionamiento de Observatorio no supondrá incremento de gasto, ya sea por indemnizaciones, asistencias o, en general, por cualesquiera otros conceptos». Secretaría General Permanente: titular de la SG de Análisis, Estrategia y Evaluación de la SE de Comercio (art. 4.3). El coste lo absorbe la SE de Comercio y no se prorratea. No se ha identificado importe contextual. El BOE no registra derogación ni modificación. No se ha verificado el cumplimiento del informe anual al Congreso (art. 3.2). | S13: 31/08/2026, salvo indicación distinta | T13: Creación acreditada; actividad 2026 no verificada. | U13: No confundir con estudios de Cámara de España u observatorios de empresas multinacionales de otras entidades. | V13: No se ha identificado relación en esta revisión (no certifica ausencia) | X13: Revisión cualitativa del mandato y estado de las 95 fichas; no auditoría exhaustiva de funciones ni proyectos. | Z13: https://www.boe.es/buscar/doc.php?id=BOE-A-2009-6645 https://www.boe.es/eli/es/rd/2009/03/27/430 | AE13: https://files.instinct.com/q91pr53q4umo-entidades-publicas-poder-y-presupuesto | AF13: 12/10/2026 | AI13: Personas realmente ocupadas; no equiparar vocales, puestos RPT o apoyo ministerial con plantilla | AJ13: Sin plantilla propia (verificado en norma: RD 430/2009, DA única, medios de la SE de Comercio). No se publica el n.º de efectivos; los vocales no son plantilla | AO13: Sin crédito de personal propio: el coste lo absorbe la SE de Comercio (SG de Análisis, Estrategia y Evaluación); no se prorratea | AV13: Sin ejecución de personal propia: el gasto está incluido en la SE de Comercio; tampoco hay indemnizaciones ni asistencias (DA única); no se prorratea | AW13: No tiene presupuesto, plantilla ni capítulo 1 propios (RD 430/2009, DA única, verificado). Sin indemnizaciones ni asistencias; sin prorrateo; sin importe contextual | BB13: Sin plantilla propia. Medios técnicos, personales y materiales de la SE de Comercio (RD 430/2009, DA única). La Secretaría General Permanente (titular de la SG de Análisis, Estrategia y Evaluación, art. 4.3) elabora los estudios encargados por el Pleno (art. 5). La norma excluye cualquier gasto por indemnizaciones o asistencias. Los vocales no son plantilla. | BC13: Análisis, propuestas e informe anual al Congreso sobre comercio internacional; no autorización de leyes | BD13: No informe obligatorio general de aprobación de leyes identificado en funciones revisadas | BE13: No consentimiento favorable obligatorio establecido en funciones revisadas | BF13: Sin veto normativo atribuido por las funciones revisadas; informar a las Cortes o asesorar no equivale a aprobar una ley. Alcance limitado a disposición revisada, no auditoría de todas las normas sectoriales posteriores. | BG13: RD 430/2009 art.3 | BH13: https://www.boe.es/buscar/doc.php?id=BOE-A-2009-6645 | BV13: No útil | BW13: Suprimir | BX13: Consultivo o participación | BZ13: No | CA13: No acreditada | CB13: Observatorio, consejo o comisión: el P100 los cierra salvo que su ministerio demuestre que su trabajo cambia decisiones o mejora un servicio; publicar informes no cuenta. | CC13: Explícito en el P100: Costes del Estado 2 | CD13: Estructura ordinaria del ministerio, si alguna función resultara imprescindible | CE13: Internacionalización empresarial | CG13: Apoyo: Secretaría General Permanente: titular de la SG de Análisis, Estrategia y Evaluación de la SE de Comercio (art. 4.3); medios técnicos, personales y materiales de la SE de Comercio (DA única RD 430/2009). vocales: 24. miembros: no retribuidos (DA única RD 430/2009: el funcionamiento «no supondrá incremento de gasto, ya sea por indemnizaciones, asistencias»). | CH13: =IF(AND(ISNUMBER(BP13),ISNUMBER(AG13),AG13>0),BP13*1000000/AG13,"")
A14: 13 | B14: Estatal | C14: Estado | D14: Zapatero | E14: Observatorio Estatal de Violencia sobre la Mujer | F14: Órgano colegiado nuevo | G14: 2004-12-28 | H14: LO 1/2004, art.30; RD 253/2006 | I14: Asesorar, evaluar y elaborar informes sobre violencia de género, con informe anual al Gobierno y CCAA. | J14: Juicio: función técnica y de seguimiento real, sin sanciones, ni capacidad de ordenar a jueces o policía. XVIII informe anual 2024 publicado acredita actividad. | O14: Sin presupuesto propio: órgano sin dotación diferenciada (verificado en norma) | R14: Sin presupuesto propio (verificado en la norma vigente). El RD 253/2006 quedó derogado por el RD 752/2022, de 13 de septiembre (BOE 28/09/2022, en vigor desde el 29/09/2022), que regula hoy funciones, funcionamiento y composición del Observatorio. Disposición adicional única del RD 752/2022 «Gastos de funcionamiento»: el departamento del que dependa orgánicamente la Delegación del Gobierno contra la Violencia de Género «atenderá los gastos de funcionamiento personales y materiales del Observatorio, con cargo al presupuesto ordinario de dicho ministerio». Secretaría: titular de la SG de Sensibilización, Prevención y Estudios de la Violencia de Género (art. 4.4). El coste lo absorbe la DGVG (Ministerio de Igualdad) y no se prorratea. No se ha identificado ningún contrato, encargo ni convenio a nombre del Observatorio. La norma no regula retribuciones ni indemnizaciones de los vocales. | S14: 31/08/2026, salvo indicación distinta | T14: Vigente; estado operativo no exhaustivamente auditado | U14: No se ha verificado el número actual de puestos ocupados ni la independencia práctica de su dirección. | V14: Ámbito compartido; funciones distintas; Ámbito temático compartido; jurisdicción y facultades distintas | W14: 14, 123 | X14: Violencia de género: el Observatorio asesora y evalúa; la Delegación formula y coordina políticas y tiene legitimación judicial. | Violencia de género e igualdad: observatorio consultivo cántabro, observatorio estatal y delegación ejecutiva estatal. No se demuestra gasto duplicado. | Y14: https://www.boe.es/eli/es/lo/2004/12/28/1 https://violenciagenero.igualdad.gob.es/violenciaencifras/observatorio/informesanuales/xviii-informe-anual-del-observatorio-estatal-de-violencia-sobre-la-mujer-2024/ https://boc.cantabria.es/boces/verAnuncioAction.do?idAnuBlob=352798 | Z14: https://www.boe.es/eli/es/lo/2004/12/28/1 https://violenciagenero.igualdad.gob.es/violenciaencifras/observatorio/informesanuales/xviii-informe-anual-del-observatorio-estatal-de-violencia-sobre-la-mujer-2024/ https://www.boe.es/eli/es/rd/2022/09/13/752/con https://www.boe.es/eli/es/rd/2006/03/03/253/con | AE14: https://files.instinct.com/q91pr53q4umo-entidades-publicas-poder-y-presupuesto | AF14: 12/10/2026 | AI14: Personas realmente ocupadas; no equiparar vocales, puestos RPT o apoyo ministerial con plantilla | AJ14: Sin plantilla propia (verificado en norma: RD 752/2022, DA única y art. 4.4, apoyo de la SG de Sensibilización, Prevención y Estudios de la DGVG). No se publica el n.º de efectivos | AO14: Sin crédito de personal propio: el coste lo absorbe la Delegación del Gobierno contra la Violencia de Género (presupuesto ordinario del Ministerio de Igualdad); no se prorratea | AV14: Sin ejecución de personal propia: el gasto está incluido en la DGVG; no se prorratea | AW14: No tiene presupuesto, plantilla ni capítulo 1 propios (RD 752/2022, DA única, verificado). El RD 253/2006 está derogado. Sin prorrateo; sin importe contextual | BB14: Sin plantilla propia. Gastos personales y materiales con cargo al presupuesto ordinario del ministerio del que depende la DGVG (RD 752/2022, DA única). Secretaría: SG de Sensibilización, Prevención y Estudios de la Violencia de Género de la DGVG (art. 4.4). La anterior previsión de dotar una «División de Estudios e Informes» mediante modificación de la RPT sin incremento de gasto (RD 253/2006, DF 2.ª) quedó derogada en 2022. Los vocales no son plantilla. | BC14: Informes y propuestas sobre violencia de género; informe anual sobre necesidades de reforma legal | BD14: No informe preceptivo general sobre aprobación de leyes identificado en las funciones revisadas | BE14: No consentimiento favorable o vinculación normativa establecido en funciones revisadas | BF14: No poder de veto legislativo atribuido en funciones revisadas. Proponer cambios, informar a Cortes o participar no equivale a aprobar leyes; no certifica ausencia de reglas sectoriales posteriores. | BG14: LO1/2004 art 30 | BH14: https://www.boe.es/eli/es/lo/2004/12/28/1 | BV14: No útil | BW14: Suprimir | BX14: Consultivo o participación | BY14: Organismo estatal de referencia. 10 comunidades tienen el suyo propio; 11 organismos sobre este tema entre el Estado y las CCAA (verificados). | BZ14: No | CA14: Acreditada | CB14: Observatorio, consejo o comisión: el P100 los cierra salvo que su ministerio demuestre que su trabajo cambia decisiones o mejora un servicio; publicar informes no cuenta. | CC14: Explícito en el P100: Costes del Estado 2 | CD14: Estructura ordinaria del ministerio, si alguna función resultara imprescindible | CE14: Observatorios de igualdad y violencia de género | CF14: 11 | CG14: Apoyo: Secretaría: titular de la SG de Sensibilización, Prevención y Estudios de la Violencia contra las Mujeres, en la DGVG (art. 4.4 RD 752/2022); gastos personales y materiales con cargo al ministerio del que depende la DGVG (DA única). Esa SG elabora el informe anual. vocales: 45. gasto con nombre propio: Becas de formación en el Observatorio: 6 becas en 2022-2023, de 1.050 EUR brutos/mes más 600 EUR/año cada una (extracto BOE 22/03/2022) (https://violenciagenero.igualdad.gob.es/wp-content/uploads/DGVGInforma_becas.pdf) | Borrador de bases de 2026: entre 14.400 y 22.200 EUR brutos anuales por beca, sin número fijado (https://www.igualdad.gob.es/wp-content/uploads/2026/06/Orden-de-Bases-becas_BORRADOR.pdf). | CH14: =IF(AND(ISNUMBER(BP14),ISNUMBER(AG14),AG14>0),BP14*1000000/AG14,"")
A15: 14 | B15: Estatal | C15: Estado | D15: Zapatero | E15: Delegación Especial del Gobierno contra la Violencia sobre la Mujer, hoy Delegación del Gobierno contra la Violencia de Género | F15: Órgano administrativo nuevo | G15: 2004-12-28 | H15: LO 1/2004, art.29 | I15: Formular, coordinar e impulsar políticas estatales contra violencia de género y legitimación judicial para defender derechos tutelados. | J15: Juicio: poder de coordinación administrativa y legitimación judicial real; no es solo un observatorio. No sustituye competencias de jueces, policía ni autonomías. | O15: Sin cifra propia actual verificada | R15: Sin presupuesto propio de entidad: centro directivo del Ministerio de Igualdad sin personalidad. Crédito identificable (columnas contextuales): servicio 30.03 'Delegación del Gobierno contra la Violencia de Género', PGE 2023 (Ley 31/2022), tomo Sección 30, pp.16-17, miles EUR: cap.1 2.556,06; cap.2 6.742,27; cap.4 53.618,00 (a CCAA 19.800; a familias e ISFL 33.768; al exterior 50); cap.6 16.623,54; total 79.539,87 = 79,53987 M EUR, todo en el programa 232C. El programa 232C suma 259.741,89 miles (259,74189 M), de los que 180.202,02 miles corresponden al servicio 30.02 Secretaría de Estado de Igualdad y contra la Violencia de Género (p.18): no imputables a la Delegación. 2026: presupuesto 2023 prorrogado (Ministerio de Hacienda, nota de 19/05/2026: crédito del cap.6 del programa 'dotada en el presupuesto para el año 2023, prorrogado para el año 2026', crédito inicial 16.623.540 EUR, idéntico al PGE 2023). El tomo de la prórroga 2026 no se ha podido cotejar, y la ejecución 2026 del servicio/programa no se ha localizado. No equivale al coste de la Delegación como organización: incluye transferencias e inversiones. | S15: 31/08/2026, salvo indicación distinta | T15: Continúa bajo denominación posterior. | U15: El programa 232C está compartido con la Secretaría de Estado (servicio 30.02); solo el servicio 30.03 es de la Delegación. Falta la ejecución 2026 del servicio y el tomo de prórroga 2026; personal ocupado no publicado. | V15: Ámbito compartido; funciones distintas; Ámbito temático compartido; jurisdicción y facultades distintas | W15: 13, 123 | X15: Violencia de género: el Observatorio asesora y evalúa; la Delegación formula y coordina políticas y tiene legitimación judicial. | Violencia de género e igualdad: observatorio consultivo cántabro, observatorio estatal y delegación ejecutiva estatal. No se demuestra gasto duplicado. | Y15: https://www.boe.es/eli/es/lo/2004/12/28/1 https://violenciagenero.igualdad.gob.es/violenciaencifras/observatorio/informesanuales/xviii-informe-anual-del-observatorio-estatal-de-violencia-sobre-la-mujer-2024/ https://boc.cantabria.es/boces/verAnuncioAction.do?idAnuBlob=352798 | Z15: https://www.boe.es/eli/es/lo/2004/12/28/1 https://www.sepg.pap.hacienda.gob.es/Presup/PGE2023Ley/MaestroTomos/PGE-ROM/doc/L_23_E_G30.PDF https://www.hacienda.gob.es/es-ES/Prensa/Noticias/Paginas/2026/20260519-NP-CM-INVERSIONES-IGUALDAD.aspx | AA15: 79.53987 | AB15: 2026 (prórroga del presupuesto 2023; importe del PGE 2023 Ley) | AC15: Crédito inicial del servicio 30.03 Delegación del Gobierno contra la Violencia de Género (programa 232C), PGE 2023 prorrogado a 2026; centro directivo sin personalidad, NO presupuesto propio de entidad; incluye transferencias (cap.4 53,618 M) e inversiones (cap.6 16,624 M) | AD15: Delegación del Gobierno contra la Violencia de Género (servicio 30.03, Ministerio de Igualdad) | AE15: https://files.instinct.com/q91pr53q4umo-entidades-publicas-poder-y-presupuesto | AF15: 12/10/2026 | AI15: Personas realmente ocupadas; no equiparar vocales, puestos RPT o apoyo ministerial con plantilla | AJ15: Pendiente: sin cifra de personal ocupado verificada en el conjunto actual | AL15: 2.55606 | AM15: 2026 | AN15: Capítulo 1: crédito inicial del servicio 30.03 Delegación (programa 232C), PGE 2023 (Ley 31/2022) prorrogado a 2026: altos cargos 61,04 + funcionarios 2.138,89 + cuotas, prestaciones y gastos sociales 356,13 = 2.556,06 miles EUR. Importe del tomo PGE 2023; tomo de prórroga 2026 no cotejado | AO15: Crédito autorizado, no gasto realizado ni solo salarios | AP15: https://www.sepg.pap.hacienda.gob.es/Presup/PGE2023Ley/MaestroTomos/PGE-ROM/doc/L_23_E_G30.PDF | AV15: Pendiente: no se ha verificado gasto salarial ejecutado individual en esta versión | AW15: Crédito del servicio 30.03 (PGE 2023 prorrogado a 2026) en columnas contextuales y su capítulo 1 verificados; personal ocupado y ejecución 2026 no verificados | BB15: Apoyo ministerial/departamental indicado en el lote y norma de la ficha; gasto individual no desglosado verificado. No repartir gasto total del ministerio. Centro directivo del Ministerio de Igualdad con puestos en la RPT del ministerio - personal MINISTERIAL, no de entidad independiente | BC15: Revisado: Delegación Violencia Género: impulso y asesoramiento | BD15: Coordina, asesora y realiza estudios; no informe previo general de leyes en funciones art3. | BE15: No consentimiento favorable ni veto legislativo establecido en las cláusulas revisadas. | BF15: Revisión limitada a las atribuciones citadas: no descarta trámites sectoriales en otras normas. | BG15: RD246/2024 art3 | BH15: https://boe.es/buscar/doc.php?id=BOE-A-2024-4616 | BN15: Prórroga: nota del Ministerio de Hacienda de 19/05/2026 (Consejo de Ministros, límites de compromisos del cap.6 del programa 'Actuaciones para la prevención integral de la violencia de género', solicitados por la Delegación): presupuesto 2023 'prorrogado para el año 2026'. El cap.6 de 2026 (16.623.540 EUR) coincide con el PGE 2023 (16.623,54 miles), lo que es coherente con la prórroga automática de los créditos iniciales; los demás capítulos de 2026 no se han cotejado en el tomo de prórroga. Ejecución (obligaciones) 2025 y 2026 del servicio 30.03: no localizada. | BV15: Sin decisión en el P100 | BW15: Pendiente de decisión | BX15: Servicio público directo | BZ15: No | CA15: Acreditada | CB15: Dirección general del Ministerio de Igualdad (no es un organismo): coordina la política contra la violencia de género y gestiona 79,5 M. | CC15: El P100 no trata la violencia de género ni el futuro del Ministerio de Igualdad | CE15: Violencia de género (política estatal) | CH15: =IF(AND(ISNUMBER(BP15),ISNUMBER(AG15),AG15>0),BP15*1000000/AG15,"") | CI15: 44 | CJ15: 16 | CK15: 3 | CL15: 63 | CP15: Puestos de la RPT de personal funcionario del Ministerio de Igualdad vigente a 01/09/2025, en las unidades de la Delegación del Gobierno contra la Violencia de Género (47975): Unidad de Apoyo 47976 (20), S.G. de Coordinación Interinstitucional en Violencia contra las Mujeres 48214 (21) y S.G. de Sensibilización, Prevención y Estudios de la Violencia contra las Mujeres 48215 (22). Excluye el personal laboral y al titular de la Delegación, que es alto cargo sin puesto en la RPT. | CQ15: Proxy por subgrupo, no por función; parte de los A1/A2 hacen gestión. Núcleo: puestos A1, A1A2 y A2. Administración y apoyo: C1, C1C2 y C2, que corresponden a secretarías (6), jefaturas de negociado (7), auxiliares de oficina (2) y técnico auxiliar de informática (1). Otro: puestos A2C1, compartidos entre grupos (3 jefaturas de sección, una por unidad). | CR15: https://transparencia.gob.es/content/dam/transparencia_home/publicidadactiva/organizacionyempleo/rpt/actual-junio-2025/migd/250901-RPT-IGU-50716-PF.pdf | CS15: RPT de funcionarios del Ministerio de Igualdad (vigencia 01-09-2025, 24 pp., 'Total Puestos: 445'). En la p. 11, bajo la cabecera '47975 DELEGACION DEL GOBIERNO CONTRA LA VIOLENCIA DE GENERO', está la Unidad de Apoyo 47976 con 20 puestos: A1 8, A1A2 3, A2 2, A2C1 1, C1C2 4, C1 2. En la p. 12, la SG 48214 tiene 21 puestos: A1 7, A1A2 5, A2 3, A2C1 1, C1 2, C1C2 2, C2 1. En la p. 13, la SG 48215 tiene 22 puestos: A1 9, A1A2 5, A2 2, A2C1 1, C1 2, C1C2 2, C2 1. Núcleo 13+15+16 = 44; apoyo 6+5+5 = 16; A2C1 3; total 63. Aviso: los subgrupos salen de una lectura asistida (WebFetch) de un texto extraído con las columnas separadas. Cuatro filas tienen subgrupo dudoso (UA filas 9 y 20; SG 48215 filas 13 y 14), pero ninguna cambia de columna: son Jefes de servicio (A en cualquier lectura) o un Jefe de negociado (C). Hay versión de la RPT a 01/01/2026 (260101-RPT-IGU-50716-PF.pdf) que no se pudo abrir.
A16: 15 | B16: Estatal | C16: Estado | D16: Zapatero | E16: Consejo Estatal de Familias y Observatorio Estatal de Familias | F16: Consejo nuevo; observatorio como órgano/comisión permanente del Consejo, con previsión legal anterior | G16: 2007-05-11 | H16: RD 613/2007; antecedente de previsión del observatorio en Ley 40/2003 | I16: Representar movimiento asociativo familiar, estudiar situación y políticas de familias y recomendar actuaciones. | J16: Juicio: consultivo, no decide prestaciones ni subvenciones. Consejo y observatorio no deben contarse como dos agencias presupuestarias autónomas. | O16: Sin presupuesto propio: órgano sin dotación diferenciada (verificado en norma) | R16: Sin presupuesto propio (verificado en norma). RD 613/2007, disposición adicional única «Medios de funcionamiento»: «El Ministerio de Trabajo y Asuntos Sociales atenderá con sus medios personales y materiales a la constitución y funcionamiento del Consejo Estatal y, en su seno, del Observatorio, sin que ello suponga incremento de gasto». El Observatorio es un órgano del Consejo y opera también como su Comisión Permanente (art. 1.2). Secretario: un funcionario del ministerio designado por la SE de Servicios Sociales, Familias y Discapacidad (art. 7.1). El coste lo absorbe el departamento hoy competente en familias (Derechos Sociales) y no se prorratea. Consejo y Observatorio no son dos presupuestos. El RD 904/2025 (subvenciones directas de Derechos Sociales) no contiene ningún importe para el Consejo ni para el Observatorio. No consta modificación ni derogación en la página del BOE. No se ha verificado la reunión anual ordinaria (art. 12.1). | S16: 31/08/2026, salvo indicación distinta | T16: Creación acreditada; actividad actual no verificada. | U16: No se ha verificado composición vigente ni cumplimiento de la reunión anual; sin base para llamarlo vacío. | V16: No se ha identificado relación en esta revisión (no certifica ausencia) | X16: Revisión cualitativa del mandato y estado de las 95 fichas; no auditoría exhaustiva de funciones ni proyectos. | Z16: https://www.boe.es/boe/dias/2007/05/12/pdfs/A20598-20600.pdf https://www.boe.es/eli/es/rd/2007/05/11/613 | AE16: https://files.instinct.com/q91pr53q4umo-entidades-publicas-poder-y-presupuesto | AF16: 12/10/2026 | AI16: Personas realmente ocupadas; no equiparar vocales, puestos RPT o apoyo ministerial con plantilla | AJ16: Sin plantilla propia (verificado en norma: RD 613/2007, DA única). Secretaría ejercida por un funcionario ministerial; no se publica el n.º de efectivos | AO16: Sin crédito de personal propio: el coste lo absorbe el ministerio competente en familias (Derechos Sociales); no se prorratea | AV16: Sin ejecución de personal propia: el gasto está incluido en la unidad ministerial de familias; no se prorratea | AW16: No tiene presupuesto, plantilla ni capítulo 1 propios (RD 613/2007, DA única, verificado). El Observatorio no tiene un presupuesto separado del Consejo. Sin prorrateo; sin importe contextual | BB16: Sin plantilla propia. Medios personales y materiales del ministerio competente (RD 613/2007, DA única), sin incremento de gasto. Secretario del Consejo y del Observatorio: un funcionario designado por la SE (art. 7.1). Los vocales no son plantilla. No repartir el gasto ministerial. | BC16: Consejo informa proyectos sometidos a su consideración; Observatorio es órgano del Consejo | BD16: Art 2.1(d),(e): proyectos y consultas sometidos a consideración; no obligación general de informe favorable | BE16: No vinculación o consentimiento favorable establecido en la función revisada | BF16: Sin veto normativo atribuido por los artículos revisados. Consejo y Observatorio no equivalen a dos autorizaciones independientes. | BG16: RD 613/2007 arts 1.2,2.1(d),(e) | BH16: https://www.boe.es/boe/dias/2007/05/12/pdfs/A20598-20600.pdf | BV16: No útil | BW16: Suprimir | BX16: Consultivo o participación | BZ16: No | CA16: No acreditada | CB16: Observatorio, consejo o comisión: el P100 los cierra salvo que su ministerio demuestre que su trabajo cambia decisiones o mejora un servicio; publicar informes no cuenta. | CC16: Explícito en el P100: Costes del Estado 2 | CD16: Estructura ordinaria del ministerio, si alguna función resultara imprescindible | CE16: Familias | CG16: Apoyo: Secretario del Consejo y del Observatorio: un funcionario del ministerio designado por la SE competente en familias (arts. 7.1 y 11); medios personales y materiales del ministerio (DA única RD 613/2007). vocales: 36. | CH16: =IF(AND(ISNUMBER(BP16),ISNUMBER(AG16),AG16>0),BP16*1000000/AG16,"")
A17: 16 | B17: Estatal | C17: Estado | D17: Zapatero | E17: Observatorio Estatal de la Discapacidad | F17: Instrumento técnico por convenio, sin personalidad jurídica | G17: 2006-12-04 | H17: Convenio marco publicado por Resolución 14/12/2006 | I17: Recopilar, sistematizar, generar y difundir información sobre discapacidad; dirección del Real Patronato y gestión técnica encargada a entidad colaboradora. | J17: Juicio: función de conocimiento real, no autoridad sancionadora. Informe Olivenza 2025 acredita resultados recientes. | O17: Sin presupuesto propio: órgano sin dotación diferenciada (verificado en norma) | R17: Sin presupuesto propio (verificado en norma). RDLeg 1/2013, art. 73.4: «El cumplimiento de las funciones dirigidas al desarrollo de los objetivos generales del Observatorio Estatal de la Discapacidad no supondrá incremento del gasto público». Según el art. 73.1 es un instrumento técnico de la AGE que actúa a través de la DG competente en discapacidad. Financiación específica identificable (contextual, NO presupuesto propio): subvención de concesión directa de 100.000 EUR (0,1 M) al CERMI «para el Observatorio Estatal de la Discapacidad» (RD 904/2025, art. 3.3.e). La concede el Real Patronato sobre Discapacidad, con ejecución de hasta 12 meses entre el 01/01/2025 y el 31/12/2026. Antecedente: el convenio RPD–CERMI de 2023 (BOE-A-2023-11877) canalizó una subvención nominativa de 80.000 EUR (0,08 M) para su gestión y funcionamiento en 2023, con cargo a la aplicación 29.102.231F.485 de los PGE 2023. Estos importes no se suman ni se tratan como presupuesto del órgano, y el presupuesto del Real Patronato no se le atribuye. | S17: 31/08/2026, salvo indicación distinta | T17: Actividad recente verificada. | U17: La financiación del convenio de 2006 no debe repetirse como presupuesto actual; convenio firmado el 4/12/2006. | V17: No se ha identificado relación en esta revisión (no certifica ausencia) | X17: Revisión cualitativa del mandato y estado de las 95 fichas; no auditoría exhaustiva de funciones ni proyectos. | Z17: https://www.boe.es/diario_boe/txt.php?id=BOE-A-2006-22673 https://observatoriodeladiscapacidad.info/olivenza/2025/informe https://www.boe.es/diario_boe/txt.php?id=BOE-A-2025-20078 https://www.boe.es/eli/es/rdlg/2013/11/29/1 https://www.boe.es/diario_boe/txt.php?id=BOE-A-2023-11877 | AA17: 0.1 | AB17: 2025 (ejecución de hasta 12 meses consecutivos entre 01/01/2025 y 31/12/2026) | AC17: Subvención de concesión directa, RD 904/2025, art. 3.3.e (concedente: Real Patronato sobre Discapacidad; presupuesto 2023 prorrogado para 2025); NO presupuesto del órgano | AD17: Comité Español de Representantes de Personas con Discapacidad (CERMI), para el Observatorio Estatal de la Discapacidad | AE17: https://files.instinct.com/q91pr53q4umo-entidades-publicas-poder-y-presupuesto | AF17: 12/10/2026 | AI17: Personas realmente ocupadas; no equiparar vocales, puestos RPT o apoyo ministerial con plantilla | AJ17: Sin plantilla pública propia (verificado: RDLeg 1/2013, art. 73, y convenio/subvención al CERMI). El personal técnico es de la entidad gestora (CERMI) y no se cuenta | AO17: Sin crédito de personal propio: la dirección la absorbe la DG competente en discapacidad y la gestión técnica se financia con una subvención al CERMI (contextual, 0,1 M en 2025); no se prorratea | AV17: Sin ejecución de personal propia: el gasto del CERMI se justifica con la cuenta justificativa de la subvención, no como capítulo 1 público; no se prorratea | AW17: No tiene presupuesto, plantilla ni capítulo 1 propios (art. 73.4 RDLeg 1/2013, verificado). Importe contextual verificado: 0,1 M EUR de subvención directa al CERMI en 2025 (RD 904/2025); 0,08 M EUR en 2023 (convenio BOE-A-2023-11877) | BB17: Instrumento técnico sin personalidad jurídica ni plantilla pública. La gestión técnica la hace el CERMI con la subvención (RD 904/2025, art. 3.3.e; antes, convenio BOE-A-2023-11877, cuyo anexo 2 incluía 15.000 EUR para la secretaría técnica y exigía que el 100 % del personal técnico de la entidad fueran personas con discapacidad). Ese personal lo emplea el CERMI y NO es plantilla pública. Dirección pública: DG competente en discapacidad (RDLeg 1/2013, art. 73.1). No repartir el presupuesto del Real Patronato ni el del ministerio. | BC17: Instrumento técnico de información sobre discapacidad, no órgano de autorización normativa | BD17: No informe preceptivo general sobre aprobación de leyes identificado en las funciones revisadas | BE17: No consentimiento favorable o vinculación normativa establecido en funciones revisadas | BF17: No poder de veto legislativo atribuido en funciones revisadas. Proponer cambios, informar a Cortes o participar no equivale a aprobar leyes; no certifica ausencia de reglas sectoriales posteriores. | BG17: Convenio 2006 cláusulas Segunda, Tercera, Cuarta | BH17: https://www.boe.es/diario_boe/txt.php?id=BOE-A-2006-22673 | BV17: No útil | BW17: Suprimir | BX17: Consultivo o participación | BZ17: No | CA17: Acreditada | CB17: Observatorio, consejo o comisión: el P100 los cierra salvo que su ministerio demuestre que su trabajo cambia decisiones o mejora un servicio; publicar informes no cuenta. | CC17: Explícito en el P100: Costes del Estado 2 | CD17: Estructura ordinaria del ministerio, si alguna función resultara imprescindible | CE17: Discapacidad | CG17: Apoyo: Dirección pública: DG competente en discapacidad (art. 73.1 RDLeg 1/2013). La gestión técnica la presta el CERMI con la subvención, con personal propio que no es empleo público. gasto con nombre propio: 100.000 EUR: subvención directa al CERMI «para el Observatorio Estatal de la Discapacidad» (RD 904/2025, art. 3.3.e), ejecutable en 2025-2026 (https://www.boe.es/diario_boe/txt.php?id=BOE-A-2025-20078) | 2023: 80.000 EUR de subvención nominativa (aplicación 29.102.231F.485), de los que 15.000 EUR eran para «Secretaría técnica» según el anexo 2 del convenio RPD-CERMI (https://www.boe.es/diario_boe/txt.php?id=BOE-A-2023-11877). | CH17: =IF(AND(ISNUMBER(BP17),ISNUMBER(AG17),AG17>0),BP17*1000000/AG17,"")
A18: 17 | B18: Estatal | C18: Estado | D18: Zapatero | E18: Observatorio de la Lectura y el Libro | F18: Órgano colegiado nuevo | G18: 2007-06-22 | H18: Ley 10/2007, DA 2; RD 1574/2007, 30 de noviembre | I18: Analizar situación del libro, lectura y bibliotecas; asesorar y elaborar informe anual. | J18: Juicio: técnico/consultivo, sin poder vinculante sobre editoriales, bibliotecas ni políticas públicas. | O18: Sin presupuesto propio: órgano sin dotación diferenciada (verificado en norma) | R18: Sin presupuesto propio (verificado en norma). RD 1574/2007 (BOE 01/01/2008), disposición adicional segunda «Personal al servicio del Observatorio del Libro y de la Lectura»: «La dotación de personal del Observatorio del Libro y de la Lectura se realizará a través de la correspondiente modificación de la relación de puestos de trabajo del Ministerio de Cultura. Dicha modificación, en ningún caso, podrá suponer incremento del gasto público». Art. 1.3: órgano colegiado adscrito al Ministerio de Cultura a través de la DG del Libro, Archivos y Bibliotecas (denominación de 2007). Art. 5.2: la secretaría del Pleno la ejerce un funcionario de esa DG. El coste lo absorbe la DG competente en libro y lectura del Ministerio de Cultura y no se prorratea. No se ha identificado importe contextual. La norma no regula indemnizaciones de los miembros. | S18: 31/08/2026, salvo indicación distinta | T18: Creación acreditada; producción reciente no auditada. | U18: No confundir creación legal con cumplimiento anual del informe; falta revisión de productos 2026. | V18: No se ha identificado relación en esta revisión (no certifica ausencia) | X18: Revisión cualitativa del mandato y estado de las 95 fichas; no auditoría exhaustiva de funciones ni proyectos. | Z18: https://www.boe.es/eli/es/rd/2007/11/30/1574/con https://boe.es/boe/dias/2008/01/01/pdfs/A00012-00014.pdf | AE18: https://files.instinct.com/q91pr53q4umo-entidades-publicas-poder-y-presupuesto | AF18: 12/10/2026 | AI18: Personas realmente ocupadas; no equiparar vocales, puestos RPT o apoyo ministerial con plantilla | AJ18: Sin plantilla propia (verificado en norma: RD 1574/2007, DA 2.ª, puestos de la RPT del Ministerio de Cultura). No se publica el n.º de puestos ni de efectivos | AO18: Sin crédito de personal propio: el coste lo absorbe la DG del Libro del Ministerio de Cultura (RPT ministerial); no se prorratea | AV18: Sin ejecución de personal propia: el gasto está incluido en la DG del Libro; no se prorratea | AW18: No tiene presupuesto, plantilla ni capítulo 1 propios (RD 1574/2007, DA 2.ª, verificado). Personal de la RPT de Cultura sin incremento de gasto; sin prorrateo; sin importe contextual | BB18: Sin plantilla propia. Personal mediante modificación de la RPT del Ministerio de Cultura, sin incremento del gasto público (RD 1574/2007, DA 2.ª). Secretaría: un funcionario de la DG del Libro (art. 5.2), que también ejerce la secretaría del Comité Técnico (art. 6.f). No se publica cuántos puestos RPT tiene asignados. Los vocales no son plantilla. | BC18: Funciones consultivas revisadas: Asesoramiento, estudios e informe anual sobre lectura y libro | BD18: No trámite obligatorio general de aprobación de leyes identificado en las funciones revisadas | BE18: No consentimiento favorable obligatorio o vinculación identificado en dichas funciones | BF18: No veto legal a aprobación de leyes atribuido por las funciones revisadas. Alcance limitado a norma revisada, no certificación de ausencia de cualquier norma sectorial posterior. | BG18: RD 1574/2007 arts 1.2,2 | BH18: https://www.boe.es/eli/es/rd/2007/11/30/1574/con | BV18: No útil | BW18: Suprimir | BX18: Consultivo o participación | BZ18: No | CA18: No acreditada | CB18: Observatorio, consejo o comisión: el P100 los cierra salvo que su ministerio demuestre que su trabajo cambia decisiones o mejora un servicio; publicar informes no cuenta. | CC18: Explícito en el P100: Costes del Estado 2 | CD18: Estructura ordinaria del ministerio, si alguna función resultara imprescindible | CE18: Libro y lectura | CG18: Apoyo: Secretaría del Pleno y del Comité Técnico: un funcionario de la DG competente en libro (art. 5.2 y art. 6.f RD 1574/2007); dotación de personal mediante modificación de la RPT del Ministerio de Cultura (DA 2.ª). vocales: 32. | CH18: =IF(AND(ISNUMBER(BP18),ISNUMBER(AG18),AG18>0),BP18*1000000/AG18,"")
A19: 18 | B19: Estatal | C19: Estado | D19: Rajoy | E19: Observatorio de la Nutrición y de Estudio de la Obesidad | F19: Órgano colegiado nuevo | G19: 2013-01-18 | H19: Acuerdo Consejo de Ministros 18/01/2013, publicado Resolución AESAN 28/01/2013 | I19: Vigilar nutrición, actividad física y obesidad, analizar datos y apoyar evaluación de estrategia NAOS. | J19: Juicio: función técnica real, no regulador ni organismo que multa. AESAN vincula al observatorio estudios epidemiológicos como ALADINO. | O19: Sin presupuesto propio: órgano sin dotación diferenciada (verificado en norma) | R19: Sin presupuesto propio (verificado en norma). Acuerdo del Consejo de Ministros de 18/01/2013, publicado por Resolución AESAN de 28/01/2013 (BOE-A-2013-2074, BOE 23/02/2013). Apartado Cuarto.1: funciona con «los recursos humanos y materiales de la estructura permanente de la Unidad técnica de la Estrategia NAOS, dependiente de la AESAN». Apartado Quinto: «Los miembros del Observatorio no percibirán remuneración alguna en el ejercicio de sus funciones» y «La creación del Observatorio no supondrá aumento del gasto público». Secretaría: un representante de AESAN responsable del seguimiento epidemiológico y la evaluación de NAOS (apartado Tercero.1.D). El coste lo absorbe AESAN, organismo autónomo cuyo presupuesto NO es el del Observatorio, y no se prorratea. La web de AESAN no publica presupuesto, contratos ni fechas de reuniones; estudios como ALADINO no se le imputan como importe propio. | S19: 31/08/2026, salvo indicación distinta | T19: Vigente; estado operativo no exhaustivamente auditado | U19: No se ha verificado el número actual de puestos ocupados ni la independencia práctica de su dirección. | V19: No se ha identificado relación en esta revisión (no certifica ausencia) | X19: Revisión cualitativa del mandato y estado de las 95 fichas; no auditoría exhaustiva de funciones ni proyectos. | Z19: https://www.boe.es/diario_boe/txt.php?id=BOE-A-2013-2074 https://www.aesan.gob.es/nutricion/datos-sobrepeso-obesidad https://boe.es/boe/dias/2013/02/23/pdfs/BOE-A-2013-2074.pdf https://aesan.gob.es/nutricion/datos-sobrepeso-obesidad/observatorio-nutricion-y-estudio-obesidad | AE19: https://files.instinct.com/q91pr53q4umo-entidades-publicas-poder-y-presupuesto | AF19: 12/10/2026 | AI19: Personas realmente ocupadas; no equiparar vocales, puestos RPT o apoyo ministerial con plantilla | AJ19: Sin plantilla propia (verificado en norma: Acuerdo CM 18/01/2013, apartado Cuarto.1, Unidad técnica NAOS de AESAN). No se publica el n.º de efectivos; los miembros no son plantilla | AO19: Sin crédito de personal propio: el coste lo absorbe AESAN (Unidad técnica de la Estrategia NAOS); no se prorratea | AV19: Sin ejecución de personal propia: el gasto está incluido en AESAN; no se prorratea | AW19: No tiene presupuesto, plantilla ni capítulo 1 propios (Acuerdo CM 18/01/2013, apartados Cuarto y Quinto, verificado). Miembros no remunerados; sin prorrateo; sin importe contextual | BB19: Sin plantilla propia. Recursos humanos y materiales de la Unidad técnica de la Estrategia NAOS de AESAN (apartado Cuarto.1 del Acuerdo CM de 18/01/2013). Miembros sin remuneración (apartado Quinto); no son plantilla. No se publica el n.º de efectivos de la Unidad NAOS dedicados al Observatorio. No repartir el presupuesto de AESAN. | BC19: Funciones técnicas de nutrición; propuestas e informes expresamente no vinculantes | BD19: No informe obligatorio general de aprobación de leyes identificado en funciones revisadas | BE19: No vinculantes expresamente (Cuarto.3) | BF19: Sin veto normativo atribuido por las funciones revisadas; informar a las Cortes o asesorar no equivale a aprobar una ley. Alcance limitado a disposición revisada, no auditoría de todas las normas sectoriales posteriores. | BG19: Resolución de 28/01/2013, apartados Segundo y Cuarto.3 | BH19: https://www.boe.es/diario_boe/txt.php?id=BOE-A-2013-2074 | BV19: No útil | BW19: Suprimir | BX19: Consultivo o participación | BZ19: No | CA19: Acreditada | CB19: Observatorio, consejo o comisión: el P100 los cierra salvo que su ministerio demuestre que su trabajo cambia decisiones o mejora un servicio; publicar informes no cuenta. | CC19: Explícito en el P100: Costes del Estado 2 | CD19: Estructura ordinaria del ministerio, si alguna función resultara imprescindible | CE19: Nutrición y obesidad | CG19: Apoyo: Unidad técnica de la Estrategia NAOS (AESAN), con sus recursos humanos y materiales (apdo. Cuarto.1). Secretaría: un representante de AESAN responsable del seguimiento de NAOS (apdo. Tercero.1.D). vocales: 14. miembros: no retribuidos (apdo. Quinto del Acuerdo CM 18/01/2013: «no percibirán remuneración alguna en el ejercicio de sus funciones»). | CH19: =IF(AND(ISNUMBER(BP19),ISNUMBER(AG19),AG19>0),BP19*1000000/AG19,"")
A20: 19 | B20: Estatal | C20: Estado | D20: Zapatero | E20: Consejo Estatal de Responsabilidad Social de las Empresas (CERSE) | F20: Órgano colegiado nuevo | G20: 2008-02-15 | H20: RD 221/2008 | I20: Asesorar políticas de responsabilidad social empresarial; foro entre administración, empresas, sindicatos y otras organizaciones. | J20: Juicio: sin poder sancionador ni vinculante. Hay señal oficial de debilidad operativa: el ministerio habla en 2026 de reactivación y más de diez años desde último nombramiento de vocalías. | O20: Sin presupuesto propio: órgano sin dotación diferenciada (verificado en norma) | R20: Sin presupuesto propio (verificado en norma). El RD 221/2008 fue modificado por el RD 301/2026, de 8 de abril (BOE-A-2026-8072, BOE 11/04/2026), que añade la disposición adicional cuarta «Ausencia de incremento de gasto público»: «La creación y el funcionamiento del Consejo Estatal de Responsabilidad Social de las Empresas no supondrá incremento del gasto público, y será atendido con los medios personales, técnicos y presupuestarios existentes en la Secretaría de Estado de Economía Social del Departamento y por los órganos y organismos con representación en este». Según el nuevo art. 2.2, la DG competente en RSE «llevará a cabo las tareas de preparación, apoyo técnico y gestión del consejo»; según el art. 5.3, la secretaría la asume la persona titular de esa DG. El coste lo absorbe la DG de Economía Social y RSE (Ministerio de Trabajo y Economía Social) y no se prorratea. La reactivación de 2026 se apoya en el RD 301/2026 y en la Orden TES/693/2026 (BOE 10/07/2026), que regula la asignación de vocalías. No se ha identificado importe contextual. | S20: 31/08/2026, salvo indicación distinta | T20: Reactivación/renovación normativa en 2026, no creación de un segundo Consejo. | U20: La demora en renovar vocalías no prueba ausencia total de actividad ni presupuesto cero. | V20: No se ha identificado relación en esta revisión (no certifica ausencia) | X20: Revisión cualitativa del mandato y estado de las 95 fichas; no auditoría exhaustiva de funciones ni proyectos. | Z20: https://www.boe.es/diario_boe/txt.php?id=BOE-A-2008-3868 https://rse.mites.gob.es/organismos-y-redes/consejo-estatal-de-rse https://www.boe.es/eli/es/rd/2008/02/15/221/con https://www.boe.es/eli/es/rd/2026/04/08/301 https://www.boe.es/boe/dias/2026/07/10/pdfs/BOE-A-2026-15029.pdf | AE20: https://files.instinct.com/q91pr53q4umo-entidades-publicas-poder-y-presupuesto | AF20: 12/10/2026 | AI20: Personas realmente ocupadas; no equiparar vocales, puestos RPT o apoyo ministerial con plantilla | AJ20: Sin plantilla propia (verificado en norma: RD 221/2008, DA 4.ª y arts. 2.2 y 5.3 en la redacción del RD 301/2026). No se publica el n.º de efectivos de la DG dedicados al CERSE | AO20: Sin crédito de personal propio: el coste lo absorbe la DG de Economía Social y RSE / SE de Economía Social (Ministerio de Trabajo y Economía Social); no se prorratea | AV20: Sin ejecución de personal propia: el gasto está incluido en la DG de apoyo; no se prorratea | AW20: No tiene presupuesto, plantilla ni capítulo 1 propios (RD 221/2008, DA 4.ª introducida por el RD 301/2026, verificado). Sin prorrateo; sin importe contextual | BB20: Sin plantilla propia. Preparación, apoyo técnico y gestión a cargo de la DG competente en RSE (art. 2.2, redacción del RD 301/2026). Secretaría: titular de esa DG, que puede contar con personal de apoyo (art. 5.3). Medios personales, técnicos y presupuestarios de la SE de Economía Social (DA 4.ª). Los vocales no son plantilla. | BC20: Consulta y recomendaciones; no vinculantes expresamente | BD20: Informes a petición del Gobierno o iniciativa propia; no informe obligatorio general sobre leyes en artículos revisados | BE20: NO vinculantes, expresamente art 7.2 | BF20: No poder de veto normativo en los artículos revisados. El consenso interno del Consejo no convierte sus propuestas en obligatorias para el Gobierno. | BG20: RD 221/2008 arts 3(c),4.1(a),7.2 | BH20: https://www.boe.es/diario_boe/txt.php?id=BOE-A-2008-3868 | BV20: No útil | BW20: Suprimir | BX20: Consultivo o participación | BZ20: No | CA20: No acreditada | CB20: Observatorio, consejo o comisión: el P100 los cierra salvo que su ministerio demuestre que su trabajo cambia decisiones o mejora un servicio; publicar informes no cuenta. | CC20: Explícito en el P100: Costes del Estado 2 | CD20: Estructura ordinaria del ministerio, si alguna función resultara imprescindible | CE20: Responsabilidad social empresarial | CG20: Apoyo: DG competente en RSE (Economía Social y RSE): preparación, apoyo técnico y gestión (art. 2.2); su titular asume la secretaría y «podrá disponer de la asistencia de personal de apoyo» (art. 5.3, redacción RD 301/2026); medios de la SE de Economía Social (DA 4.ª). vocales: 56. | CH20: =IF(AND(ISNUMBER(BP20),ISNUMBER(AG20),AG20>0),BP20*1000000/AG20,"")
A21: 20 | B21: Estatal | C21: Estado | D21: Zapatero | E21: Consejo Estatal del Pueblo Gitano | F21: Órgano colegiado nuevo | G21: 2005-07-22 | H21: RD 891/2005 | I21: Participación de movimiento asociativo gitano y asesoramiento de políticas de inclusión. | J21: Juicio: representación/consulta, no potestad sancionadora ni poder de ejecución autónomo. | O21: Sin presupuesto propio: órgano sin dotación diferenciada (verificado en norma) | R21: Sin presupuesto propio (verificado en norma). RD 891/2005, disposición adicional segunda «Financiación»: «El coste de funcionamiento del Consejo Estatal del Pueblo Gitano será atendido con cargo a los créditos existentes en el Ministerio de Trabajo y Asuntos Sociales, sin que sea necesario el incremento de su dotación global». Art. 8.1: secretario, el titular de la SG de Programas Sociales, «que podrá ser asistido por el personal de apoyo necesario». La web del Ministerio de Derechos Sociales, Consumo y Agenda 2030 sitúa hoy la secretaría en la SG de Servicios Sociales. El coste lo absorbe esa SG y no se prorratea. En el Pleno de 20/02/2024 (acta publicada) se acordó poner en marcha una Oficina/Secretaría Técnica «con medios propios» antes de fin de año, pero no se ha localizado ningún contrato, subvención ni importe específico. Las cifras de esa acta (CODI, Plan de Desarrollo Gitano) son programas de política gitana y NO presupuesto del Consejo. Actividad: Pleno de 20/02/2024; la Orden DCA/935/2026 (BOE 05/09/2026) convoca la renovación de vocalías. | S21: 31/08/2026, salvo indicación distinta | T21: Creación acreditada; actividad reciente no auditada. | U21: No se ha verificado el número actual de puestos ocupados ni la independencia práctica de su dirección. | V21: No se ha identificado relación en esta revisión (no certifica ausencia) | X21: Revisión cualitativa del mandato y estado de las 95 fichas; no auditoría exhaustiva de funciones ni proyectos. | Z21: https://www.boe.es/boe/dias/2005/08/26/pdfs/A29622-29625.pdf https://www.boe.es/buscar/pdf/2005/BOE-A-2005-14549-consolidado.pdf https://www.dsca.gob.es/es/derechos-sociales/poblacion-gitana/consejo-estatal https://dsca.gob.es/sites/default/files/derechos-sociales/poblacion-gitana/docs/Acta_Pleno_200224__Censurado_0.pdf https://boe.es/boe/dias/2026/09/05/pdfs/BOE-A-2026-18697.pdf | AE21: https://files.instinct.com/q91pr53q4umo-entidades-publicas-poder-y-presupuesto | AF21: 12/10/2026 | AI21: Personas realmente ocupadas; no equiparar vocales, puestos RPT o apoyo ministerial con plantilla | AJ21: Sin plantilla propia (verificado en norma: RD 891/2005, DA 2.ª y art. 8.1, personal de apoyo de la SG ministerial). No se publica el n.º de efectivos; los vocales no son plantilla | AO21: Sin crédito de personal propio: el coste lo absorbe la SG de Servicios Sociales (Ministerio de Derechos Sociales, Consumo y Agenda 2030); no se prorratea | AV21: Sin ejecución de personal propia: el gasto está incluido en la SG de apoyo; no se prorratea | AW21: No tiene presupuesto, plantilla ni capítulo 1 propios (RD 891/2005, DA 2.ª, verificado). Sin prorrateo. Secretaría técnica acordada en 2024 sin importe localizado | BB21: Sin plantilla propia. Secretaría: SG de Servicios Sociales según la web ministerial; la norma de 2005 decía SG de Programas Sociales (art. 8.1), con personal de apoyo de esa unidad. La Oficina/Secretaría Técnica acordada en el Pleno de 20/02/2024 se pondría en marcha «con medios propios», sin importe ni n.º de personas localizados. Hay 40 vocalías en el Pleno; no son plantilla. | BC21: Dictámenes sobre proyectos normativos sometidos a su consideración | BD21: No informe obligatorio general de aprobación de leyes identificado en funciones revisadas | BE21: No consentimiento favorable obligatorio establecido en funciones revisadas | BF21: Sin veto normativo atribuido por las funciones revisadas; informar a las Cortes o asesorar no equivale a aprobar una ley. Alcance limitado a disposición revisada, no auditoría de todas las normas sectoriales posteriores. | BG21: RD 891/2005 art.3.1(d) | BH21: https://www.boe.es/boe/dias/2005/08/26/pdfs/A29622-29625.pdf | BV21: No útil | BW21: Suprimir | BX21: Consultivo o participación | BZ21: No | CA21: Acreditada | CB21: Observatorio, consejo o comisión: el P100 los cierra salvo que su ministerio demuestre que su trabajo cambia decisiones o mejora un servicio; publicar informes no cuenta. | CC21: Explícito en el P100: Costes del Estado 2 | CD21: Estructura ordinaria del ministerio, si alguna función resultara imprescindible | CE21: Participación: pueblo gitano | CG21: Apoyo: Secretaría: titular de la SG de Programas Sociales, que «podrá ser asistido por el personal de apoyo necesario» (art. 8.1 RD 891/2005); la web ministerial la sitúa hoy en la SG de Servicios Sociales. Coste con cargo a créditos del ministerio (DA 2.ª). vocales: 42. | CH21: =IF(AND(ISNUMBER(BP21),ISNUMBER(AG21),AG21>0),BP21*1000000/AG21,"")
A22: 21 | B22: Estatal | C22: Estado | D22: Zapatero | E22: Consejo de Participación de la Mujer | F22: Órgano colegiado nuevo creado por ley y regulado después | G22: 2007-03-22 | H22: LO 3/2007, art.78; RD 1791/2009, 20 de noviembre | I22: Canalizar participación de asociaciones y entidades de mujeres en igualdad; informes y propuestas. | J22: Juicio: consultivo, sin facultad general de imponer medidas o sanciones. | O22: Sin presupuesto propio: órgano sin dotación diferenciada (verificado en norma) | R22: Sin presupuesto propio (verificado en norma). RD 1791/2009, disposición adicional cuarta «Financiación»: «Para el desempeño de sus funciones, el Consejo de Participación de la Mujer contará con los créditos presupuestarios que asigne el Ministerio de Igualdad, sin que en ningún caso pueda originarse incremento del gasto público». Secretaría: tras la disposición final segunda del RD 634/2026 (Estatutos del Instituto de las Mujeres, O.A., BOE 30/07/2026), el art. 7.1 dice: «Ejercerá la secretaría la persona que ostente la Presidencia del Instituto de las Mujeres, O.A.». El coste lo absorbe el Ministerio de Igualdad / Instituto de las Mujeres, O.A. No se prorratea ni se le atribuye el presupuesto del Instituto. No se ha identificado ningún crédito con su nombre. La norma no regula retribuciones ni indemnizaciones de las vocalías. | S22: 31/08/2026, salvo indicación distinta | T22: Creación acreditada; actividad reciente no auditada. | U22: No se ha verificado el número actual de puestos ocupados ni la independencia práctica de su dirección. | V22: Ámbito compartido; sector especializado | W22: 48, 50 | X22: Igualdad y participación: consejo general de mujeres, observatorio I+D+i y observatorio cultural. Sectores y funciones no equivalentes. | Y22: https://www.boe.es/buscar/act.php?id=BOE-A-2009-20160 https://www.boe.es/boe/dias/2018/12/11/pdfs/BOE-A-2018-16905.pdf https://www.boe.es/buscar/act.php?id=BOE-A-2020-13026 https://www.cultura.gob.es/dam/jcr:85ee66d9-d300-4e8a-9903-07653ae01b27/report-orden-reguladora-observatorio-igualdad.pdf https://www.cultura.gob.es/cultura/mc/espacio-igualdad/observatorio.html | Z22: https://www.boe.es/buscar/act.php?id=BOE-A-2009-20160 https://www.boe.es/eli/es/rd/2009/11/20/1791/con https://www.boe.es/eli/es/rd/2009/11/20/1791/con/20260730 https://boe.es/buscar/pdf/2026/BOE-A-2026-16550-consolidado.pdf | AE22: https://files.instinct.com/q91pr53q4umo-entidades-publicas-poder-y-presupuesto | AF22: 12/10/2026 | AI22: Personas realmente ocupadas; no equiparar vocales, puestos RPT o apoyo ministerial con plantilla | AJ22: Sin plantilla propia (verificado en norma: RD 1791/2009, DA 4.ª y art. 7, apoyo del Instituto de las Mujeres, O.A.). No se publica el n.º de efectivos | AO22: Sin crédito de personal propio: el coste lo absorben el Ministerio de Igualdad y el Instituto de las Mujeres, O.A.; no se prorratea | AV22: Sin ejecución de personal propia: el gasto está incluido en el Instituto de las Mujeres / Ministerio de Igualdad; no se prorratea | AW22: No tiene presupuesto, plantilla ni capítulo 1 propios (RD 1791/2009, DA 4.ª, verificado). Secretaría en el Instituto de las Mujeres desde el RD 634/2026. Sin prorrateo; sin importe contextual | BB22: Sin plantilla propia. Créditos que asigne el Ministerio de Igualdad, sin incremento del gasto público (RD 1791/2009, DA 4.ª). La secretaría corresponde a la Presidencia del Instituto de las Mujeres, O.A. (art. 7.1 en la redacción del RD 634/2026). Los «servicios correspondientes» facilitan asistencia técnica a las vocalías (art. 7.2.d). Las vocalías no son plantilla. | BC22: Consulta sobre anteproyectos de ley y reales decretos cuando se solicita | BD22: No exigencia general sobre leyes en la disposición revisada; sí informe preceptivo sobre Plan Estratégico de Igualdad | BE22: No se exige dictamen favorable en el art 3.2 | BF22: Plazo mínimo para informe solicitado:30 días, urgencia 10. Es un trámite consultivo, no veto legislativo acreditado. No confundir el plan con una ley. | BG22: RD 1791/2009 art 3.2 | BH22: https://www.boe.es/buscar/act.php?id=BOE-A-2009-20160 | BV22: No útil | BW22: Suprimir | BX22: Consultivo o participación | BZ22: No | CA22: No acreditada | CB22: Observatorio, consejo o comisión: el P100 los cierra salvo que su ministerio demuestre que su trabajo cambia decisiones o mejora un servicio; publicar informes no cuenta. | CC22: Explícito en el P100: Costes del Estado 2 | CD22: Estructura ordinaria del ministerio, si alguna función resultara imprescindible | CE22: Participación: mujeres | CG22: Apoyo: Secretaría: Presidencia del Instituto de las Mujeres, O.A. (art. 7.1, redacción RD 634/2026); asistencia técnica a las vocalías «por medio de los servicios correspondientes» (art. 7.2.d); créditos del Ministerio de Igualdad (DA 4.ª). vocales: 40. | CH22: =IF(AND(ISNUMBER(BP22),ISNUMBER(AG22),AG22>0),BP22*1000000/AG22,"")
A23: 22 | B23: Estatal | C23: Estado | D23: Zapatero | E23: Fundación Pluralismo y Convivencia, F.S.P. | F23: Fundación estatal nueva | G23: 2004-10-15 | H23: Acuerdo Consejo Ministros 15/10/2004; origen reconocido en RD 45/2021 | I23: Promover libertad religiosa, conocimiento del pluralismo, convivencia y apoyo a confesiones minoritarias. | J23: Juicio: capacidad real de conceder ayudas y ejecutar programas, sin potestad reguladora o sancionadora. Convocatoria 2026 acredita ejecución. | K23: 2.027433 | L23: 2025 | M23: Presupuesto propio aprobado | N23: 2025, plan de actuación aprobado por el Patronato el 28/02/2025 | O23: Cifra propia2025 verificada; actual2026 pendiente | R23: Presupuesto 2025 del Plan de Actuación 2025 (apartado 5 'Presupuesto 2025', pp.17-18): total gastos 2.027.432,75 EUR = 2,027433 M EUR, igual al total de ingresos (transferencia a favor de la Fundación (PGE) 1.980.000; reintegro de ayudas 26.077,75; Comisión Europea, proyecto RE-TO, 21.355). Incluye ayudas monetarias (1.200.000 de concesión directa a federaciones + 146.077,75 de subvenciones contra la intolerancia) y gastos de personal 480.000. Plan aprobado el 28/02/2025 (cuentas anuales 2025, p.20). Ejecución 2025 (cuentas anuales 2025, documento fechado 24/06/2026): total gastos 2.084.510,21 EUR (Nota 3.1, p.7), de ellos ayudas monetarias 1.399.058,44 y gastos de personal 452.388,46 (cuenta de resultados, p.4); transferencia de la AGE 2025 por 1.980.000 EUR para gastos corrientes (aplicación 13.08.912O.441), imputada al ejercicio 1.860.000 (Nota 4.14 p.13; Nota 14.2 p.25). Plan de actuación o presupuesto 2026 no publicado en el portal (consulta 12/10/2026). La convocatoria 2026 de 130.000 EUR (columnas contextuales) es una línea parcial: no sumar. | S23: 31/08/2026, salvo indicación distinta | T23: Vigente, con estatutos posteriores. | U23: Falta obtener el presupuesto total vigente y su conciliación con transferencias PGE; no sumar convocatoria y transferencia. | V23: No se ha identificado relación en esta revisión (no certifica ausencia) | X23: Revisión cualitativa del mandato y estado de las 95 fichas; no auditoría exhaustiva de funciones ni proyectos. | Z23: https://www.pluralismoyconvivencia.es/wp-content/uploads/2021/02/Estatutos-FPyC-2021-1.pdf https://www.boe.es/diario_boe/txt.php?id=BOE-B-2026-29248 https://www.pluralismoyconvivencia.es/wp-content/uploads/2026/07/802EDU-PLURALISMO-Y-CONVIVENCIA-F.S.-CUENTAS-CA-2025.pdf https://www.pluralismoyconvivencia.es/wp-content/uploads/2025/03/Plan-Actuacion-2025.pdf https://www.pluralismoyconvivencia.es/informacion-economica-presupuestaria-y-estadistica/ https://www.pluralismoyconvivencia.es/fundacion/informacion-economica/ | AA23: 0.13 | AB23: 2026 | AC23: Convocatoria parcial; NO presupuesto total | AD23: Fundación Pluralismo y Convivencia, F.S.P. | AE23: https://files.instinct.com/q91pr53q4umo-entidades-publicas-poder-y-presupuesto | AF23: 12/10/2026 | AG23: 8 | AH23: 2025 | AI23: Personal de la Fundación en 2025 según Nota 13.3 de las cuentas anuales 2025 (p.21): 'en 2025 es de 8 personas a la espera de la incorporación de un nuevo efectivo aprobado por Tasa de reposición ordinaria'. La memoria no precisa si es media anual o plantilla a 31/12. Cumplimiento del plan: 5 asalariados en la actividad A1 y 3 en la A2 (pp.26-29) | AJ23: Cifra de personal publicada en fuente primaria; fecha indicada, no inferir vigencia posterior | AK23: https://www.pluralismoyconvivencia.es/wp-content/uploads/2026/07/802EDU-PLURALISMO-Y-CONVIVENCIA-F.S.-CUENTAS-CA-2025.pdf | AL23: 0.48 | AM23: 2025 | AN23: Gastos de personal presupuestados en el Plan de Actuación 2025 (apartado 5, pp.17-18): 480.000,00 EUR; base PyG de fundación, NO capítulo 1 | AO23: Presupuesto aprobado de la entidad; no gasto realizado ni solo salarios | AP23: https://www.pluralismoyconvivencia.es/wp-content/uploads/2025/03/Plan-Actuacion-2025.pdf | AQ23: 0.452388 | AR23: 2025 | AS23: 2025 año completo (cuentas anuales 2025) | AT23: Partida (64) 8. Gastos de personal de la cuenta de resultados 2025 (p.4): sueldos y salarios 345.249,20 + Seguridad Social a cargo de la entidad 105.326,86 + otros gastos sociales 1.812,40 (Nota 13.3, p.21) = 452.388,46 EUR; base PyG, no capítulo 1 | AU23: https://www.pluralismoyconvivencia.es/wp-content/uploads/2026/07/802EDU-PLURALISMO-Y-CONVIVENCIA-F.S.-CUENTAS-CA-2025.pdf | AV23: Fuente primaria cotejada contra fila y unidad EUR; no estimación | AW23: Presupuesto propio 2025 aprobado (plan de actuación), gasto de personal 2025 ejecutado (cuentas anuales) y personal 2025 (8 personas) verificados; presupuesto 2026 no publicado | BB23: Fundación del sector público estatal con personal propio (no ministerial). Retribución de la Dirección General publicada en el portal de transparencia: 'Retribución básica: 50.000,00 euros' y 'Retribución complementaria: 23.917,14 euros' (página 'Información económica, presupuestaria y estadística', consulta 12/10/2026). Gastos de personal 2024: 479.883,05 EUR (comparativo de la cuenta de resultados 2025, p.4). | BC23: Revisado: Pluralismo: asesoramiento y subvenciones | BD23: Fines de investigación, sensibilización y asesoramiento diversidad religiosa; no consulta normativa general en estatutos. | BE23: No consentimiento favorable ni veto legislativo establecido en las cláusulas revisadas. | BF23: Revisión limitada a las atribuciones citadas: no descarta trámites sectoriales en otras normas. | BG23: Estatutos2021 arts7,9 | BH23: https://www.boe.es/diario_boe/txt.php?id=BOE-A-2021-1193 | BP23: 0.452388 | BR23: 2025: hasta31/12/2025, año completo | BS23: Gastos de personal de la cuenta de resultados (cuentas anuales 2025): sueldos, Seguridad Social y otros gastos sociales; base PyG, no obligaciones reconocidas de capítulo 1 | BT23: https://www.pluralismoyconvivencia.es/wp-content/uploads/2026/07/802EDU-PLURALISMO-Y-CONVIVENCIA-F.S.-CUENTAS-CA-2025.pdf | BU23: Cuentas anuales 2025 (portal de transparencia; informe de auditoría 2025 publicado junto a ellas): fila '(64) 8. Gastos de personal' -452.388,46 EUR (2025) y -479.883,05 (2024), p.4. Fundación con contabilidad PGC-ESFL: no hay crédito de cierre ni pagos de capítulo 1 (BO y BQ vacías, NO cero). | BV23: No útil | BW23: Suprimir | BX23: Financiación y ayudas | BZ23: No | CA23: Acreditada | CB23: Fundación del sector público que reparte subvenciones a confesiones: el P100 cierra las fundaciones que no demuestren resultados y suprime las subvenciones por existir. | CC23: Explícito en el P100: Costes del Estado 2 y 3 | CE23: Libertad religiosa | CH23: =IF(AND(ISNUMBER(BP23),ISNUMBER(AG23),AG23>0),BP23*1000000/AG23,"") -> 56548.5 | CI23: 2 | CJ23: 4 | CK23: 1 | CL23: 7 | CP23: Personas del equipo publicado en la web de la Fundación (página 'Equipo', consulta 12/10/2026). Las cuentas anuales de 2025 (Nota 13.3, p. 21) hablan de 8 personas en 2025, entre ellas la trabajadora de limpieza, cuyo gasto (8.960,09 EUR) figura como no afecto a actividades. | CQ23: Por función, según el puesto publicado. Núcleo (programas): Subdirectora y responsable de Programas, Estudios e Incidencia; Técnico de Programas e Incidencia (2). Administración y apoyo: Responsable de Administración y gestión económica; Técnico de contratación y adecuación normativa; Técnico de Administración; Secretaria (4). Otro: Directora (1), cargo de dirección general que no se asigna a ninguna de las dos funciones. | CR23: https://www.pluralismoyconvivencia.es/fundacion/equipo/ | CS23: Página 'Equipo': 1 Inés Mazarrasa Steinkuhler, Directora; 2 Puerto García Ortiz, Subdirectora, responsable de Programas, Estudios e Incidencia; 3 Rita Gomes Faria, Técnico de Programas e Incidencia; 4 Aurora Fernández García, Responsable de Administración y gestión económica; 5 Lourdes Beltrán Latorre, Técnico de contratación y adecuación normativa; 6 Enrique Marín Serrano, Técnico de Administración; 7 Elena Moraleda Torres, Secretaria. 2+4+1 = 7. Las cuentas anuales de 2025 (https://www.pluralismoyconvivencia.es/wp-content/uploads/2026/07/802EDU-PLURALISMO-Y-CONVIVENCIA-F.S.-CUENTAS-CA-2025.pdf) no traen tabla de personal por categorías: la Nota 13.3 solo da el gasto (sueldos 345.249,20; SS 105.326,86; otros 1.812,40; total 452.388,46 EUR) y las '8 personas'.
A24: 23 | B24: Estatal | C24: Estado | D24: Rajoy | E24: Oficina Independiente de Regulación y Supervisión de la Contratación (OIReScon) | F24: Órgano colegiado nuevo con independencia funcional | G24: 2017-11-08 | H24: Ley 9/2017, art.332; RD 342/2023 | I24: Supervisar contratación pública, aprobar estrategia e instrucciones, emitir informes y remitir indicios a autoridades competentes. | J24: Juicio: poder supervisor real y ciertas instrucciones obligatorias en el ámbito legal, pero no tribunal de recursos ni fiscalía ni potestad general de anular contratos. | O24: Sin cifra propia actual verificada | R24: No se ha identificado dotación individual en las fuentes consultadas. Se financia con medios del órgano matriz; no equivale a cero EUR y no se le atribuye todo el presupuesto ministerial. | S24: 31/08/2026, salvo indicación distinta | T24: Creada por ley 2017; funcionamiento desarrollado después. | U24: No confundir con Junta Consultiva, Tribunal de Recursos Contractuales u Oficina Nacional de Evaluación; falta presupuesto individual actual. | V24: No se ha identificado relación en esta revisión (no certifica ausencia) | X24: Revisión cualitativa del mandato y estado de las 95 fichas; no auditoría exhaustiva de funciones ni proyectos. | Z24: https://www.boe.es/eli/es/l/2017/11/08/9 https://www.boe.es/eli/es/rd/2023/05/09/342/con https://www.hacienda.gob.es/rsc/oirescon/informe-anual-actuaciones/informe-anual-actuaciones-2025.pdf | AE24: https://files.instinct.com/q91pr53q4umo-entidades-publicas-poder-y-presupuesto | AF24: 12/10/2026 | AG24: 30 | AH24: 2025-01-01 | AI24: 63,83% ocupación; presidenta + 4 vocales + 25 funcionarios | AJ24: Cifra de personal publicada en fuente primaria; fecha indicada, no inferir vigencia posterior | AK24: https://www.hacienda.gob.es/rsc/oirescon/informe-anual-actuaciones/informe-anual-actuaciones-2025.pdf | AO24: Pendiente: sin coste de personal individual verificado en el conjunto actual | AV24: Pendiente: no se ha verificado gasto salarial ejecutado individual en esta versión | AW24: Hay dato individual de personal o crédito; ver año y fuente. Salarios ejecutados pendientes | AX24: 47 | AY24: 2025-01-01 | AZ24: RPT efectiva (estructura + nuevo ingreso) | BA24: https://www.hacienda.gob.es/rsc/oirescon/informe-anual-actuaciones/informe-anual-actuaciones-2025.pdf | BB24: Informe anual de actuaciones 2025 (aprobado el 06/03/2026): a efectos organizativos la Oficina está adscrita al MINHAC a través de su Subsecretaría (nota 7, p.21) y usa el Portal y la Sede Electrónica del MINHAC (pp.24 y 29). A 01/01/2025: RPT efectiva de 47 puestos y 30 ocupados (p.17), 63,83% (p.18); a 31/12/2025, ocupación de la RPT del 66,67% (p.18), sin número de puestos a esa fecha (no se infiere). El informe no da presupuesto, crédito ni coste de personal propio; el encargo a ISDEFE (3 años desde el 15/02/2026) figura sin importe. No se reparte crédito del Ministerio de Hacienda. | BC24: Revisado: OIReScon | BD24: Supervisión de contratación e instrucciones obligatorias AGE; estrategia contratación vinculante para sector público, no autorización legislativa. | BE24: No consentimiento favorable para leyes establecido en funciones revisadas. | BF24: No veto legislativo identificado en estas cláusulas; no pretende descartar obligaciones sectoriales en otras normas. | BG24: Ley9/2017 art332.6-7 | BH24: https://www.boe.es/eli/es/l/2017/11/08/9 | BN24: Sin crédito ni ejecución propios: el informe anual 2025 no los publica y la Oficina está adscrita a la Subsecretaría del MINHAC. Ocupación de la RPT: 63,83% a 01/01/2025 y 66,67% a 31/12/2025 (p.18). | BV24: Útil | BW24: Mantener | BX24: Control interno y cumplimiento | BZ24: No | CA24: Acreditada | CB24: Supervisa la contratación pública con independencia; encaja con las medidas de competencia en licitaciones del P100. | CC24: Aplicando el criterio del P100: Costes del Estado 9 (establecer hechos con independencia) | CE24: Supervisión de la contratación pública | CH24: =IF(AND(ISNUMBER(BP24),ISNUMBER(AG24),AG24>0),BP24*1000000/AG24,"") | CI24: 27 | CJ24: 3 | CK24: 0 | CL24: 30 | CP24: Personas (efectivos) a 31/12/2025, Tabla 3 de personal por grupo y sexo del Informe anual de actuaciones 2025 (pp. 20-21). Incluye a la Presidenta y a los 4 vocales. | CQ24: Proxy por subgrupo, no por función; parte de los A1/A2 hacen gestión. A1+A2 = núcleo; C1+C2 = administración y apoyo. La fuente no tiene subgrupo E ni otro personal ('otro' = 0 según la tabla, que no tiene más filas). | CR24: https://www.hacienda.gob.es/rsc/oirescon/informe-anual-actuaciones/informe-anual-actuaciones-2025.pdf | CS24: Tabla 3 (31/12/2025): A1 7 H + 5 M = 12; A2 5 H + 10 M = 15; C1 1 H + 2 M = 3; C2 0 + 0 = 0; Total 13 H + 17 M = 30. Núcleo 12+15 = 27; apoyo 3+0 = 3. La p. 18 confirma que la Oficina 'consolide el número de 30 efectivos' y una ocupación de la RPT del 66,67%. Que el total incluye a Presidenta y vocales se deduce de la Tabla 2 (31/12/2024: A1 13, A2 14, C1 3 = 30), que cuadra con 'presidenta + 4 vocales + otros 25 funcionarios' a 1/1/2025 (p. 17).
A25: 24 | B25: Estatal | C25: Estado | D25: Rajoy | E25: Comisión Nacional de los Mercados y la Competencia (CNMC) | F25: Fusión/reordenación de reguladores existentes, nueva persona jurídica | G25: 2013-06-04 | H25: Ley 3/2013 | I25: Defender competencia y supervisar mercados de energía, telecomunicaciones, audiovisuales, postal y transportes; sanciones, concentraciones y regulación. | J25: Juicio: poder vinculante muy alto, con inspección, multas y decisiones. No es un cascarón; su presupuesto bruto incorpora transferencias sectoriales. | K25: 4846.353 | L25: 2026 | M25: Crédito total actualizado | N25: 31/08/2026 | O25: Cifra propia verificada | P25: 3686.434 | Q25: 1159.919 | R25: Presupuesto propio, crédito inicial 2026 3.686,434 M EUR; modificaciones netas +1.159,919 M; crédito total 4.846,353 M al 31/08/2026. IGAE p.100, cifras publicadas en miles de euros, no gasto ejecutado ni dotación solo administrativa. Separación agosto: capítulo 1 personal 47,618 M; capítulo 2 bienes/servicios 25,567 M; transferencias capital 4.656,642 M. No llamar a todo ello coste de administración. | S25: 31/08/2026, salvo indicación distinta | T25: Vigente; absorción de organismos en 2013. | U25: Modificación positiva neta acreditada; no documentado el expediente causante completo. No comparar presupuesto bruto con organismos exclusivamente consultivos. | V25: Integración legal; Reordenación legal; constitución previa no confirmada; Reordenación legal; no equivalencia de mandato; Mandato paralelo en distinto nivel territorial | W25: 25, 26, 70, 71, 72, 74, 93 | X25: CNC y Comisión del Sector Postal se integraron en CNMC por Ley 3/2013; no son organismos actuales paralelos. No sumar un presupuesto sucesor a los antiguos. | Ley 3/2013 prevé extinción con CNMC; no se ha confirmado por completo la constitución operativa previa. CEMA conserva conflicto entre fuentes. | Ley 3/2013 prevé extinción de Comisión del Juego. No se atribuye su función de juego a CNMC por esa sola cláusula. | Competencia estatal y autonómica. Facultades territoriales distintas; no prueba de expedientes o gasto duplicados. | Y25: https://www.boe.es/diario_boe/txt.php?id=BOE-A-2013-5940 https://www.igae.pap.hacienda.gob.es/sitios/igae/es-ES/Contabilidad/ContabilidadPublica/CPE/EjecucionPresupuestaria/Documents/ORGANISMOS%2008.%202026.pdf https://www.cnmc.es/sites/default/files/editor_contenidos/CNMC/PortalTransparencia/2026_IT_%20y_IIT_ejecuci%C3%B3n%20presupuestaria.pdf https://www.boe.es/eli/es/l/2007/07/03/15 https://www.boe.es/eli/es/l/2007/10/08/23/con https://www.boe.es/eli/es/l/2010/03/31/7 https://www.boe.es/diario_boe/txt.php?id=BOE-A-2011-9735 https://www.cnmc.es/somos-cnmc/sobre-nosotros/que-es-la-cnmc https://www.boe.es/eli/es/l/2011/05/27/13 https://www.azarplus.com/comision-nacional-del-juego-r-i-p/ https://www.boe.es/eli/es/rdl/2011/08/26/11 https://www.boe.es/buscar/act.php?id=BOE-A-2007-14406 https://www.boe.es/buscar/act.php?id=BOE-A-2012-2313 https://www.euskadi.eus/web01-a3ogaoce/es/contenidos/informacion/ejec_pres_avc_2026/es_def/adjuntos/211_2026_7_DETALLESPORPARTIDAS-GASTOSEINGRESOS_es.pdf | Z25: https://www.boe.es/diario_boe/txt.php?id=BOE-A-2013-5940 https://www.igae.pap.hacienda.gob.es/sitios/igae/es-ES/Contabilidad/ContabilidadPublica/CPE/EjecucionPresupuestaria/Documents/ORGANISMOS%2008.%202026.pdf https://www.cnmc.es/sites/default/files/editor_contenidos/CNMC/PortalTransparencia/2026_IT_%20y_IIT_ejecuci%C3%B3n%20presupuestaria.pdf | AE25: https://files.instinct.com/q91pr53q4umo-entidades-publicas-poder-y-presupuesto | AF25: 12/10/2026 | AG25: 579 | AH25: 2025 | AI25: efectivos consolidados | AJ25: Cifra de personal publicada en fuente primaria; fecha indicada, no inferir vigencia posterior | AK25: https://www.cnmc.es/sites/default/files/editor_contenidos/CNMC/Memorias/Memoria%20Resumen%20ejecutivo%20CNMC%20web%20.pdf | AL25: 47.618 | AM25: 2026 | AN25: Capítulo 1: crédito TOTAL actualizado IGAE, corte 31/08/2026 | AO25: Crédito autorizado, no gasto realizado ni solo salarios | AP25: https://www.igae.pap.hacienda.gob.es/sitios/igae/es-ES/Contabilidad/ContabilidadPublica/CPE/EjecucionPresupuestaria/Documents/ORGANISMOS%2008.%202026.pdf | AQ25: 29.507 | AR25: 2026 | AS25: Hasta 31/08/2026:8 meses, NO año completo | AT25: Capítulo 1: obligaciones reconocidas; incluye costes de personal, no desglose salarial puro | AU25: https://www.igae.pap.hacienda.gob.es/sitios/igae/es-ES/Contabilidad/ContabilidadPublica/CPE/EjecucionPresupuestaria/Documents/ORGANISMOS%2008.%202026.pdf | AV25: Fuente primaria cotejada contra fila y unidad milesEUR; no estimación | AW25: Crédito y gasto de personal individual verificados; plantilla ocupada solo si hay cifra y fecha independiente | BB25: RPT/plantilla aprobada y cap.1: pendiente (cuentas anuales CNMC en portal transparencia) | BC25: Participa mediante informe en elaboración de normas y puede recurrir reglamentos | BD25: Participación prevista en art 5.2(a); obligatoriedad depende también de norma sectorial concreta, no resuelta en general | BE25: No veto legislativo general en art 5.2. Sus decisiones/circulares sectoriales pueden ser vinculantes y son una facultad distinta | BF25: Art 5.4: puede impugnar ante tribunales disposiciones de rango inferior a ley que obstaculicen competencia. Recurso no equivale a anulación o suspensión automática; no veto a leyes parlamentarias. | BG25: Ley 3/2013 arts 5.2(a),5.4 | BH25: https://www.boe.es/diario_boe/txt.php?id=BOE-A-2013-5940 | BI25: 29.507 | BJ25: 43.294 | BK25: 26.31 | BN25: IGAE: columnas 2026 crédito / obligaciones / pagos;2025 crédito y obligaciones al mismo 31/08. No comparar 8 meses con año completo. Capítulo 1 no equivale solo a sueldos. PlantillaRPT del lote no incorporada sin verificación adicional. | BO25: 43.294 | BP25: 42.084 | BQ25: 42.084 | BR25: 2025: hasta31/12/2025, año completo | BS25: Capítulo1: gastos de personal; obligaciones reconocidas, no solo salarios | BT25: https://www.igae.pap.hacienda.gob.es/sitios/igae/es-ES/Contabilidad/ContabilidadPublica/CPE/EjecucionPresupuestaria/Documents/ORGANISMOS%2012.%202025.pdf | BU25: Fuente primaria cotejada: IGAE edición12.2025, tabla y unidad milesEUR. No confundir con comparativa2025 de edición08.2026. | BV25: Útil | BW25: Mantener | BX25: Regulación o inspección de terceros | BY25: Organismo estatal de referencia. 9 comunidades tienen el suyo propio; 10 organismos sobre este tema entre el Estado y las CCAA (verificados). | BZ25: Sí: las directivas de energía y comunicaciones exigen un regulador nacional independiente | CA25: Acreditada | CB25: Regula mercados y sanciona conductas contra la competencia; el P100 conserva su informe obligatorio. Exigida por la UE. | CC25: Explícito en el P100: Costes del Estado 9; Organización del Estado 11 | CE25: Autoridades de defensa de la competencia | CF25: 10 | CH25: =IF(AND(ISNUMBER(BP25),ISNUMBER(AG25),AG25>0),BP25*1000000/AG25,"") -> 72683.938
A26: 25 | B26: Estatal | C26: Estado | D26: Zapatero | E26: Comisión Nacional de la Competencia (CNC) | F26: Fusión de Tribunal y Servicio de Defensa de la Competencia | G26: 2007-07-03 | H26: Ley 15/2007 | I26: Aplicar derecho de competencia, sancionar conductas y controlar concentraciones. | J26: Juicio: poder ejecutivo/regulador real mientras existió. | O26: Sin presupuesto propio actual: supresión/extinción; no cuantificar sustituto | R26: Sin presupuesto actual propio; extinguida e integrada en CNMC. No atribuir a la antigua CNC todo presupuesto CNMC. | S26: 31/08/2026, salvo indicación distinta | T26: Extinción prevista Ley 3/2013, ligada a puesta en funcionamiento de CNMC en 2013. | U26: Fecha exacta de comienzo operativo de CNMC no cerrada en este lote. | V26: Integración legal | W26: 24, 26 | X26: CNC y Comisión del Sector Postal se integraron en CNMC por Ley 3/2013; no son organismos actuales paralelos. No sumar un presupuesto sucesor a los antiguos. | Y26: https://www.boe.es/diario_boe/txt.php?id=BOE-A-2013-5940 https://www.igae.pap.hacienda.gob.es/sitios/igae/es-ES/Contabilidad/ContabilidadPublica/CPE/EjecucionPresupuestaria/Documents/ORGANISMOS%2008.%202026.pdf https://www.cnmc.es/sites/default/files/editor_contenidos/CNMC/PortalTransparencia/2026_IT_%20y_IIT_ejecuci%C3%B3n%20presupuestaria.pdf https://www.boe.es/eli/es/l/2007/07/03/15 https://www.boe.es/eli/es/l/2007/10/08/23/con | Z26: https://www.boe.es/eli/es/l/2007/07/03/15 https://www.boe.es/diario_boe/txt.php?id=BOE-A-2013-5940 | AE26: https://files.instinct.com/q91pr53q4umo-entidades-publicas-poder-y-presupuesto | AF26: 12/10/2026 | AI26: Personas realmente ocupadas; no equiparar vocales, puestos RPT o apoyo ministerial con plantilla | AJ26: Pendiente: sin cifra de personal ocupado verificada en el conjunto actual | AO26: Pendiente: sin coste de personal individual verificado en el conjunto actual | AV26: Pendiente: no se ha verificado gasto salarial ejecutado individual en esta versión | AW26: SIN CIFRA INDIVIDUAL VERIFICADA de presupuesto, personal ocupado y salarios ejecutados; investigación pendiente, no prueba de falta de publicación | BC26: Revisado: papel histórico CNC, hoy integrada en CNMC | BD26: Ley15/2007 original art25: en todo caso dictamina proyectos/proposiciones que afecten competencia y reglamentos de desarrollo. | BE26: No se exige consentimiento favorable ni carácter vinculante del informe en la cláusula citada; no es veto. | BF26: Histórico, no facultad actual de CNC. Art12.3 permite impugnar disposiciones inferiores a ley; no anula ni suspende por sí sola. | BG26: Ley15/2007 original arts25a,12.3 | BH26: https://www.boe.es/diario_boe/txt.php?id=BOE-A-2007-12946 | BV26: Extinguida | BW26: Extinguida | BX26: Extinguida o no constituida | BY26: 10 organismos sobre este tema entre el Estado y las CCAA (verificados) | BZ26: No | CA26: No aplica (no vigente) | CB26: Extinguida en 2013 al integrarse en la CNMC. | CE26: Autoridades de defensa de la competencia | CF26: 10 | CH26: =IF(AND(ISNUMBER(BP26),ISNUMBER(AG26),AG26>0),BP26*1000000/AG26,"")
